Workbook

Sheet Net F
B5: =TODAY() -> 45596
B6: CUENTA 1 | C6: NOMBRE | D6: CLAVE | E6: TELEFONO | F6: PIN PERFIL | G6: precio S/ | H6: PRECIO | I6: FECHA DE INICIO | J6: DIAS | K6: FECHA DE VENCIMIENTO | L6: ALARMA | M6: ESTADO
B7: NETFLIX | C7: Vasty2193 | E7: 593 93 972 8672 | F7: 3814 | G7: $2.5 | H7: =IF(I7>0,10,0) -> 10 | I7: 45572 | J7: 30 | K7: =+'Net F'!$I7+'Net F'!$J7 -> 45602 | L7: ='Net F'!$I7+'Net F'!$J7-TODAY() -> 6 | M7: =IF(L7<1,"VENCIDO","VIGENTE") -> VIGENTE
C8: Marcelo103 | E8: 594 93 972 8672 | F8: 1138 | H8: =IF(I8>0,10,0) -> 10 | I8: 45543 | J8: 60 | K8: =+'Net F'!$I8+'Net F'!$J8 -> 45603 | L8: ='Net F'!$I8+'Net F'!$J8-TODAY() -> 7 | M8: =IF(L8<1,"VENCIDO","VIGENTE") -> VIGENTE
C9: kelly92 | E9: 51 946 140 474 | F9: 8745 | H9: =IF(I9>0,10,0) -> 10 | I9: 45524 | J9: 30 | K9: =+'Net F'!$I9+'Net F'!$J9 -> 45554 | L9: ='Net F'!$I9+'Net F'!$J9-TODAY() -> -42 | M9: =IF(L9<1,"VENCIDO","VIGENTE") -> VENCIDO
C10: alme58 | E10: 51 988 684 621 | F10: 9467 | H10: =IF(I10>0,10,0) -> 10 | I10: 45567 | J10: 30 | K10: ='Net F'!$I10+'Net F'!$J10 -> 45597 | L10: ='Net F'!$I10+'Net F'!$J10-TODAY() -> 1 | M10: =IF(L10<1,"VENCIDO","VIGENTE") -> VIGENTE
C11: Ingrid829 | E11: 51 986 430 133 | F11: 1946 | H11: =IF(I11>0,10,0) -> 10 | I11: 45554 | J11: 30 | K11: ='Net F'!$I11+'Net F'!$J11 -> 45584 | L11: ='Net F'!$I11+'Net F'!$J11-TODAY() -> -12 | M11: =IF(L11<1,"VENCIDO","VIGENTE") -> VENCIDO
C12: Moises429 | E12: 51 986 430 133 | F12: 6323 | H12: =IF(I12>0,10,0) -> 10 | I12: 45539 | J12: 30 | K12: ='Net F'!$I12+'Net F'!$J12 -> 45569 | L12: ='Net F'!$I12+'Net F'!$J12-TODAY() -> -27 | M12: =IF(L12<1,"VENCIDO","VIGENTE") -> VENCIDO
C13: Alison269 | E13: 51 924 623 553 | F13: 6659 | H13: =IF(I13>0,10,0) -> 10 | I13: 45549 | J13: 30 | K13: ='Net F'!$I13+'Net F'!$J13 -> 45579 | L13: ='Net F'!$I13+'Net F'!$J13-TODAY() -> -17 | M13: =IF(L13<1,"VENCIDO","VIGENTE") -> VENCIDO
C14: Alexander922 | E14: 51 973 042 635 | F14: 8362 | H14: =IF(I14>0,10,0) -> 10 | I14: 45563 | J14: 30 | K14: ='Net F'!$I14+'Net F'!$J14 -> 45593 | L14: ='Net F'!$I14+'Net F'!$J14-TODAY() -> -3 | M14: =IF(L14<1,"VENCIDO","VIGENTE") -> VENCIDO
C15: cathe6 | E15: 51 917 020 261 | F15: 6975 | H15: =IF(I15>0,10,0) -> 10 | I15: 45572 | J15: 30 | K15: ='Net F'!$I15+'Net F'!$J15 -> 45602 | L15: ='Net F'!$I15+'Net F'!$J15-TODAY() -> 6 | M15: =IF(L15<1,"VENCIDO","VIGENTE") -> VIGENTE
C16: clinton19 | E16: 51 965 090 265 | F16: 5827 | H16: =IF(I16>0,10,0) -> 10 | I16: 45563 | J16: 30 | K16: ='Net F'!$I16+'Net F'!$J16 -> 45593 | L16: ='Net F'!$I16+'Net F'!$J16-TODAY() -> -3 | M16: =IF(L16<1,"VENCIDO","VIGENTE") -> VENCIDO
C17: Joel2655 | E17: 51 977 840 037 | F17: 6346 | H17: =IF(I17>0,10,0) -> 10 | I17: 45557 | J17: 30 | K17: ='Net F'!$I17+'Net F'!$J17 -> 45587 | L17: ='Net F'!$I17+'Net F'!$J17-TODAY() -> -9 | M17: =IF(L17<1,"VENCIDO","VIGENTE") -> VENCIDO
C18: Jilson38 | E18: 593 98 457 2028 | F18: 6975 | H18: =IF(I18>0,10,0) -> 10 | I18: 45519 | J18: 30 | K18: ='Net F'!$I18+'Net F'!$J18 -> 45549 | L18: ='Net F'!$I18+'Net F'!$J18-TODAY() -> -47 | M18: =IF(L18<1,"VENCIDO","VIGENTE") -> VENCIDO
C19: Rihanna66 | E19: 51 970 573 661 | F19: 6289 | H19: =IF(I19>0,11,0) -> 11 | I19: 45550 | J19: 30 | K19: ='Net F'!$I19+'Net F'!$J19 -> 45580 | L19: ='Net F'!$I19+'Net F'!$J19-TODAY() -> -16 | M19: =IF(L19<1,"VENCIDO","VIGENTE") -> VENCIDO
C20: Ruth648 | E20: 51 965 090 265 | F20: 6975 | H20: =IF(I20>0,10,0) -> 10 | I20: 45506 | J20: 30 | K20: ='Net F'!$I20+'Net F'!$J20 -> 45536 | L20: ='Net F'!$I20+'Net F'!$J20-TODAY() -> -60 | M20: =IF(L20<1,"VENCIDO","VIGENTE") -> VENCIDO
C21: Jose617 | E21: 51 980 621 358 | F21: 1137 | H21: =IF(I21>0,10,0) -> 10 | I21: 45567 | J21: 30 | K21: ='Net F'!$I21+'Net F'!$J21 -> 45597 | L21: ='Net F'!$I21+'Net F'!$J21-TODAY() -> 1 | M21: =IF(L21<1,"VENCIDO","VIGENTE") -> VIGENTE
C22: Mael194 | E22: 593 96 365 3101 | F22: 6975 | H22: =IF(I22>0,10,0) -> 10 | I22: 45520 | J22: 30 | K22: ='Net F'!$I22+'Net F'!$J22 -> 45550 | L22: ='Net F'!$I22+'Net F'!$J22-TODAY() -> -46 | M22: =IF(L22<1,"VENCIDO","VIGENTE") -> VENCIDO
C23: Brider CR | E23: 51 918 845 769 | F23: 4843 | H23: =IF(I23>0,10,0) -> 10 | I23: 45573 | J23: 30 | K23: ='Net F'!$I23+'Net F'!$J23 -> 45603 | L23: ='Net F'!$I23+'Net F'!$J23-TODAY() -> 7 | M23: =IF(L23<1,"VENCIDO","VIGENTE") -> VIGENTE
C24: Guissela5 | E24: 51 994 961 537 | F24: 4844 | H24: =IF(I24>0,10,0) -> 10 | I24: 45540 | J24: 30 | K24: ='Net F'!$I24+'Net F'!$J24 -> 45570 | L24: ='Net F'!$I24+'Net F'!$J24-TODAY() -> -26 | M24: =IF(L24<1,"VENCIDO","VIGENTE") -> VENCIDO
C25: Katty428 | E25: 593 96 365 3101 | F25: 7738 | H25: =IF(I25>0,10,0) -> 10 | I25: 45512 | J25: 30 | K25: ='Net F'!$I25+'Net F'!$J25 -> 45542 | L25: ='Net F'!$I25+'Net F'!$J25-TODAY() -> -54 | M25: =IF(L25<1,"VENCIDO","VIGENTE") -> VENCIDO
C26: JONATAN142 | E26: 593 99 908 6487 | F26: 1140 | G26: $9.80 | H26: =IF(I26>0,10,0) -> 10 | I26: 45530 | J26: 30 | K26: ='Net F'!$I26+'Net F'!$J26 -> 45560 | L26: ='Net F'!$I26+'Net F'!$J26-TODAY() -> -36 | M26: =IF(L26<1,"VENCIDO","VIGENTE") -> VENCIDO
C27: Leslie18 | E27: 51 946 579 911 | F27: 6499 | H27: =IF(I27>0,10,0) -> 10 | I27: 45506 | J27: 30 | K27: ='Net F'!$I27+'Net F'!$J27 -> 45536 | L27: ='Net F'!$I27+'Net F'!$J27-TODAY() -> -60 | M27: =IF(L27<1,"VENCIDO","VIGENTE") -> VENCIDO
C28: Gina92 | E28: 51 946 579 911 | F28: 6245 | H28: =IF(I28>0,10,0) -> 10 | I28: 45570 | J28: 30 | K28: ='Net F'!$I28+'Net F'!$J28 -> 45600 | L28: ='Net F'!$I28+'Net F'!$J28-TODAY() -> 4 | M28: =IF(L28<1,"VENCIDO","VIGENTE") -> VIGENTE
C29: Criswell Ostaiza | E29: 593 96 178 8067 | F29: 4699 | H29: =IF(I29>0,10,0) -> 10 | I29: 45546 | J29: 30 | K29: ='Net F'!$I29+'Net F'!$J29 -> 45576 | L29: ='Net F'!$I29+'Net F'!$J29-TODAY() -> -20 | M29: =IF(L29<1,"VENCIDO","VIGENTE") -> VENCIDO
C30: Lyaa19 | E30: 51 917 117 242 | F30: 1827 | H30: =IF(I30>0,10,0) -> 10 | I30: 45537 | J30: 30 | K30: ='Net F'!$I30+'Net F'!$J30 -> 45567 | L30: ='Net F'!$I30+'Net F'!$J30-TODAY() -> -29 | M30: =IF(L30<1,"VENCIDO","VIGENTE") -> VENCIDO
C31: German291 | E31: 51 946 579 911 | F31: 1195 | H31: =IF(I31>0,10,0) -> 10 | I31: 45529 | J31: 30 | K31: ='Net F'!$I31+'Net F'!$J31 -> 45559 | L31: ='Net F'!$I31+'Net F'!$J31-TODAY() -> -37 | M31: =IF(L31<1,"VENCIDO","VIGENTE") -> VENCIDO
C32: Thaira185 | E32: 51 946 579 911 | F32: 7383 | H32: =IF(I32>0,10,0) -> 10 | I32: 45514 | J32: 30 | K32: ='Net F'!$I32+'Net F'!$J32 -> 45544 | L32: ='Net F'!$I32+'Net F'!$J32-TODAY() -> -52 | M32: =IF(L32<1,"VENCIDO","VIGENTE") -> VENCIDO
C33: Flavio V | E33: 51 977 364 111 | F33: 5235 | H33: =IF(I33>0,10,0) -> 10 | I33: 45535 | J33: 30 | K33: ='Net F'!$I33+'Net F'!$J33 -> 45565 | L33: ='Net F'!$I33+'Net F'!$J33-TODAY() -> -31 | M33: =IF(L33<1,"VENCIDO","VIGENTE") -> VENCIDO
C34: Miguel193 | E34: 51 917 117 242 | F34: 1936 | H34: =IF(I34>0,10,0) -> 10 | I34: 45507 | J34: 30 | K34: ='Net F'!$I34+'Net F'!$J34 -> 45537 | L34: ='Net F'!$I34+'Net F'!$J34-TODAY() -> -59 | M34: =IF(L34<1,"VENCIDO","VIGENTE") -> VENCIDO
C35: Junior139 | E35: 593 98 457 2028 | F35: 3282 | H35: =IF(I35>0,10,0) -> 10 | I35: 45543 | J35: 30 | K35: ='Net F'!$I35+'Net F'!$J35 -> 45573 | L35: ='Net F'!$I35+'Net F'!$J35-TODAY() -> -23 | M35: =IF(L35<1,"VENCIDO","VIGENTE") -> VENCIDO
C36: Emily71 | E36: 51 917 117 242 | F36: 1853 | H36: =IF(I36>0,10,0) -> 10 | I36: 45531 | J36: 30 | K36: ='Net F'!$I36+'Net F'!$J36 -> 45561 | L36: ='Net F'!$I36+'Net F'!$J36-TODAY() -> -35 | M36: =IF(L36<1,"VENCIDO","VIGENTE") -> VENCIDO
C37: justin7 | E37: 593 99 681 9196 | F37: 7458 | G37: $2.5 | H37: =IF(I37>0,10,0) -> 10 | I37: 45550 | J37: 30 | K37: ='Net F'!$I37+'Net F'!$J37 -> 45580 | L37: ='Net F'!$I37+'Net F'!$J37-TODAY() -> -16 | M37: =IF(L37<1,"VENCIDO","VIGENTE") -> VENCIDO
C38: Maximiliano52 | E38: 593 96 327 7766 | F38: 2947 | G38: $2.5 | H38: =IF(I38>0,10,0) -> 10 | I38: 45568 | J38: 30 | K38: ='Net F'!$I38+'Net F'!$J38 -> 45598 | L38: ='Net F'!$I38+'Net F'!$J38-TODAY() -> 2 | M38: =IF(L38<1,"VENCIDO","VIGENTE") -> VIGENTE
C39: Carlos Aguirre111 | E39: 593 99 624 5270 | F39: 4455 | H39: =IF(I39>0,10,0) -> 10 | I39: 45546 | J39: 30 | K39: ='Net F'!$I39+'Net F'!$J39 -> 45576 | L39: ='Net F'!$I39+'Net F'!$J39-TODAY() -> -20 | M39: =IF(L39<1,"VENCIDO","VIGENTE") -> VENCIDO
C40: Carlos Aguirre222 | E40: 593 99 624 5270 | F40: 4455 | H40: =IF(I40>0,10,0) -> 10 | I40: 45546 | J40: 30 | K40: ='Net F'!$I40+'Net F'!$J40 -> 45576 | L40: ='Net F'!$I40+'Net F'!$J40-TODAY() -> -20 | M40: =IF(L40<1,"VENCIDO","VIGENTE") -> VENCIDO
C41: Carlos Aguirre333 | E41: 593 99 624 5270 | F41: 4455 | H41: =IF(I41>0,10,0) -> 10 | I41: 45546 | J41: 30 | K41: ='Net F'!$I41+'Net F'!$J41 -> 45576 | L41: ='Net F'!$I41+'Net F'!$J41-TODAY() -> -20 | M41: =IF(L41<1,"VENCIDO","VIGENTE") -> VENCIDO
C42: Carlos Aguirre444 | E42: 593 99 624 5270 | F42: 4455 | H42: =IF(I42>0,10,0) -> 10 | I42: 45546 | J42: 30 | K42: ='Net F'!$I42+'Net F'!$J42 -> 45576 | L42: ='Net F'!$I42+'Net F'!$J42-TODAY() -> -20 | M42: =IF(L42<1,"VENCIDO","VIGENTE") -> VENCIDO
C43: Carlos Aguirre555 | E43: 593 99 624 5270 | F43: 4455 | H43: =IF(I43>0,10,0) -> 10 | I43: 45546 | J43: 30 | K43: ='Net F'!$I43+'Net F'!$J43 -> 45576 | L43: ='Net F'!$I43+'Net F'!$J43-TODAY() -> -20 | M43: =IF(L43<1,"VENCIDO","VIGENTE") -> VENCIDO
C44: Carlos Aguirre666 | E44: 593 99 624 5270 | F44: 4455 | H44: =IF(I44>0,10,0) -> 10 | I44: 45546 | J44: 30 | K44: ='Net F'!$I44+'Net F'!$J44 -> 45576 | L44: ='Net F'!$I44+'Net F'!$J44-TODAY() -> -20 | M44: =IF(L44<1,"VENCIDO","VIGENTE") -> VENCIDO
C45: Carlos Aguirre777 | E45: 593 99 624 5270 | F45: 4455 | H45: =IF(I45>0,10,0) -> 10 | I45: 45546 | J45: 30 | K45: ='Net F'!$I45+'Net F'!$J45 -> 45576 | L45: ='Net F'!$I45+'Net F'!$J45-TODAY() -> -20 | M45: =IF(L45<1,"VENCIDO","VIGENTE") -> VENCIDO
C46: Eduardo Aguirre | E46: 593 99 624 5270 | F46: 1111 | H46: =IF(I46>0,10,0) -> 10 | I46: 45546 | J46: 30 | K46: ='Net F'!$I46+'Net F'!$J46 -> 45576 | L46: ='Net F'!$I46+'Net F'!$J46-TODAY() -> -20 | M46: =IF(L46<1,"VENCIDO","VIGENTE") -> VENCIDO
C47: Eduardo Aguirre1 | E47: 593 99 624 5270 | F47: 1111 | H47: =IF(I47>0,10,0) -> 10 | I47: 45546 | J47: 30 | K47: ='Net F'!$I47+'Net F'!$J47 -> 45576 | L47: ='Net F'!$I47+'Net F'!$J47-TODAY() -> -20 | M47: =IF(L47<1,"VENCIDO","VIGENTE") -> VENCIDO
C48: Jessi936 | E48: 51 946 579 911 | F48: 8467 | H48: =IF(I48>0,10,0) -> 10 | I48: 45506 | J48: 30 | K48: ='Net F'!$I48+'Net F'!$J48 -> 45536 | L48: ='Net F'!$I48+'Net F'!$J48-TODAY() -> -60 | M48: =IF(L48<1,"VENCIDO","VIGENTE") -> VENCIDO
C49: Jedyan911 | E49: 51 935 183 987 | F49: 1033 | H49: =IF(I49>0,10,0) -> 10 | I49: 45570 | J49: 30 | K49: ='Net F'!$I49+'Net F'!$J49 -> 45600 | L49: ='Net F'!$I49+'Net F'!$J49-TODAY() -> 4 | M49: =IF(L49<1,"VENCIDO","VIGENTE") -> VIGENTE
C50: Percydelia244 | E50: 51 935 183 987 | F50: 3329 | H50: =IF(I50>0,10,0) -> 10 | I50: 45570 | J50: 30 | K50: ='Net F'!$I50+'Net F'!$J50 -> 45600 | L50: ='Net F'!$I50+'Net F'!$J50-TODAY() -> 4 | M50: =IF(L50<1,"VENCIDO","VIGENTE") -> VIGENTE
... C52: oscar65 | E52: 51 946 998 173 | F52: 2566 | H52: =IF(I52>0,10,0) -> 10 | I52: 45572 | J52: 30 | K52: ='Net F'!$I52+'Net F'!$J52 -> 45602 | L52: ='Net F'!$I52+'Net F'!$J52-TODAY() -> 6 | M52: =IF(L52<1,"VENCIDO","VIGENTE") -> VIGENTE
C53: Yossy644 | E53: 51 930 641 167 | F53: 2747 | H53: =IF(I53>0,9,0) -> 9 | I53: 45577 | J53: 30 | K53: ='Net F'!$I53+'Net F'!$J53 -> 45607 | L53: ='Net F'!$I53+'Net F'!$J53-TODAY() -> 11 | M53: =IF(L53<1,"VENCIDO","VIGENTE") -> VIGENTE
C54: Zarina349 | E54: 593 93 972 8672 | F54: 4789 | H54: =IF(I54>0,10,0) -> 10 | I54: 45509 | J54: 30 | K54: ='Net F'!$I54+'Net F'!$J54 -> 45539 | L54: ='Net F'!$I54+'Net F'!$J54-TODAY() -> -57 | M54: =IF(L54<1,"VENCIDO","VIGENTE") -> VENCIDO
C55: Rose926 | E55: 51 963 728 882 | F55: 1292 | H55: =IF(I55>0,10,0) -> 10 | I55: 45550 | J55: 30 | K55: ='Net F'!$I55+'Net F'!$J55 -> 45580 | L55: ='Net F'!$I55+'Net F'!$J55-TODAY() -> -16 | M55: =IF(L55<1,"VENCIDO","VIGENTE") -> VENCIDO
C56: Don Mauricio3 | E56: 51 999 770 361 | F56: 1166 | H56: =IF(I56>0,10,0) -> 10 | I56: 45514 | J56: 30 | K56: ='Net F'!$I56+'Net F'!$J56 -> 45544 | L56: ='Net F'!$I56+'Net F'!$J56-TODAY() -> -52 | M56: =IF(L56<1,"VENCIDO","VIGENTE") -> VENCIDO
C57: Jonathan528 | E57: 593 99 569 2053 | F57: 2914 | G57: 2.5 | H57: =IF(I57>0,10,0) -> 10 | I57: 45588 | J57: 30 | K57: ='Net F'!$I57+'Net F'!$J57 -> 45618 | L57: ='Net F'!$I57+'Net F'!$J57-TODAY() -> 22 | M57: =IF(L57<1,"VENCIDO","VIGENTE") -> VIGENTE
C58: Lupita25 | E58: 51 924 818 095 | F58: 6245 | H58: =IF(I58>0,9,0) -> 9 | I58: 45568 | J58: 30 | K58: ='Net F'!$I58+'Net F'!$J58 -> 45598 | L58: ='Net F'!$I58+'Net F'!$J58-TODAY() -> 2 | M58: =IF(L58<1,"VENCIDO","VIGENTE") -> VIGENTE
C59: Neira23 | E59: 51 906 615 310 | F59: 1165 | H59: =IF(I59>0,10,0) -> 10 | I59: 45522 | J59: 30 | K59: ='Net F'!$I59+'Net F'!$J59 -> 45552 | L59: ='Net F'!$I59+'Net F'!$J59-TODAY() -> -44 | M59: =IF(L59<1,"VENCIDO","VIGENTE") -> VENCIDO
C60: Pamela945 | E60: 51 924 818 095 | F60: 4478 | H60: =IF(I60>0,9,0) -> 9 | I60: 45568 | J60: 30 | K60: ='Net F'!$I60+'Net F'!$J60 -> 45598 | L60: ='Net F'!$I60+'Net F'!$J60-TODAY() -> 2 | M60: =IF(L60<1,"VENCIDO","VIGENTE") -> VIGENTE
C61: Jhasury927 | E61: 51 946 579 911 | F61: 9273 | H61: =IF(I61>0,10,0) -> 10 | I61: 45550 | J61: 30 | K61: ='Net F'!$I61+'Net F'!$J61 -> 45580 | L61: ='Net F'!$I61+'Net F'!$J61-TODAY() -> -16 | M61: =IF(L61<1,"VENCIDO","VIGENTE") -> VENCIDO
C62: Yulissa | E62: 593 95 900 1567 | F62: 2946 | H62: =IF(I62>0,10,0) -> 10 | I62: 45552 | J62: 30 | K62: ='Net F'!$I62+'Net F'!$J62 -> 45582 | L62: ='Net F'!$I62+'Net F'!$J62-TODAY() -> -14 | M62: =IF(L62<1,"VENCIDO","VIGENTE") -> VENCIDO
C63: Jesus229 | E63: 51 933 326 508 | F63: 6975 | H63: =IF(I63>0,10,0) -> 10 | I63: 45519 | J63: 30 | K63: ='Net F'!$I63+'Net F'!$J63 -> 45549 | L63: ='Net F'!$I63+'Net F'!$J63-TODAY() -> -47 | M63: =IF(L63<1,"VENCIDO","VIGENTE") -> VENCIDO
C64: Rosmeri62 | E64: 51 979 743 711 | F64: 2318 | H64: =IF(I64>0,10,0) -> 10 | I64: 45534 | J64: 30 | K64: ='Net F'!$I64+'Net F'!$J64 -> 45564 | L64: ='Net F'!$I64+'Net F'!$J64-TODAY() -> -32 | M64: =IF(L64<1,"VENCIDO","VIGENTE") -> VENCIDO
C65: zuly93 | E65: 51 946 579 911 | F65: 8225 | H65: =IF(I65>0,10,0) -> 10 | I65: 45522 | J65: 30 | K65: ='Net F'!$I65+'Net F'!$J65 -> 45552 | L65: ='Net F'!$I65+'Net F'!$J65-TODAY() -> -44 | M65: =IF(L65<1,"VENCIDO","VIGENTE") -> VENCIDO
C66: Babas3558 | E66: 51 951 821 138 | F66: 6699 | H66: =IF(I66>0,10,0) -> 10 | I66: 45510 | J66: 30 | K66: ='Net F'!$I66+'Net F'!$J66 -> 45540 | L66: ='Net F'!$I66+'Net F'!$J66-TODAY() -> -56 | M66: =IF(L66<1,"VENCIDO","VIGENTE") -> VENCIDO
C67: Tania Silva924 | E67: 51 921 561 639 | F67: 2736 | H67: =IF(I67>0,10,0) -> 10 | I67: 45551 | J67: 30 | K67: ='Net F'!$I67+'Net F'!$J67 -> 45581 | L67: ='Net F'!$I67+'Net F'!$J67-TODAY() -> -15 | M67: =IF(L67<1,"VENCIDO","VIGENTE") -> VENCIDO
C68: George117 | E68: 51 917 117 242 | F68: 1118 | H68: =IF(I68>0,10,0) -> 10 | I68: 45528 | J68: 30 | K68: ='Net F'!$I68+'Net F'!$J68 -> 45558 | L68: ='Net F'!$I68+'Net F'!$J68-TODAY() -> -38 | M68: =IF(L68<1,"VENCIDO","VIGENTE") -> VENCIDO
C69: karelis92 | E69: 593 96 365 3101 | F69: 7293 | G69: 2.5 | H69: =IF(I69>0,10,0) -> 10 | I69: 45582 | J69: 30 | K69: ='Net F'!$I69+'Net F'!$J69 -> 45612 | L69: ='Net F'!$I69+'Net F'!$J69-TODAY() -> 16 | M69: =IF(L69<1,"VENCIDO","VIGENTE") -> VIGENTE
C70: Stefany937 | E70: 51 946 579 911 | F70: 6975 | H70: =IF(I70>0,10,0) -> 10 | I70: 45511 | J70: 30 | K70: ='Net F'!$I70+'Net F'!$J70 -> 45541 | L70: ='Net F'!$I70+'Net F'!$J70-TODAY() -> -55 | M70: =IF(L70<1,"VENCIDO","VIGENTE") -> VENCIDO
C71: Josué19 | E71: 51 965 090 265 | F71: 1194 | H71: =IF(I71>0,10,0) -> 10 | I71: 45555 | J71: 30 | K71: ='Net F'!$I71+'Net F'!$J71 -> 45585 | L71: ='Net F'!$I71+'Net F'!$J71-TODAY() -> -11 | M71: =IF(L71<1,"VENCIDO","VIGENTE") -> VENCIDO
C72: xiomara63 | E72: 51 946 579 911 | F72: 6975 | H72: =IF(I72>0,10,0) -> 10 | I72: 45523 | J72: 30 | K72: ='Net F'!$I72+'Net F'!$J72 -> 45553 | L72: ='Net F'!$I72+'Net F'!$J72-TODAY() -> -43 | M72: =IF(L72<1,"VENCIDO","VIGENTE") -> VENCIDO
C73: Nancy de la cruz | E73: 51 946 579 911 | F73: 9445 | H73: =IF(I73>0,10,0) -> 10 | I73: 45535 | J73: 30 | K73: ='Net F'!$I73+'Net F'!$J73 -> 45565 | L73: ='Net F'!$I73+'Net F'!$J73-TODAY() -> -31 | M73: =IF(L73<1,"VENCIDO","VIGENTE") -> VENCIDO
C74: Valery Medrano | E74: 51 917 073 862 | F74: 3964 | H74: =IF(I74>0,10,0) -> 10 | I74: 45556 | J74: 30 | K74: ='Net F'!$I74+'Net F'!$J74 -> 45586 | L74: ='Net F'!$I74+'Net F'!$J74-TODAY() -> -10 | M74: =IF(L74<1,"VENCIDO","VIGENTE") -> VENCIDO
C75: Jhon399 | E75: 51 917 117 242 | F75: 6975 | H75: =IF(I75>0,10,0) -> 10 | I75: 45537 | J75: 30 | K75: ='Net F'!$I75+'Net F'!$J75 -> 45567 | L75: ='Net F'!$I75+'Net F'!$J75-TODAY() -> -29 | M75: =IF(L75<1,"VENCIDO","VIGENTE") -> VENCIDO
C76: Miguel Calderón14 | E76: 51 902 266 754 | F76: 1146 | H76: =IF(I76>0,10,0) -> 10 | I76: 45557 | J76: 30 | K76: ='Net F'!$I76+'Net F'!$J76 -> 45587 | L76: ='Net F'!$I76+'Net F'!$J76-TODAY() -> -9 | M76: =IF(L76<1,"VENCIDO","VIGENTE") -> VENCIDO
C77: Kathy2942 | E77: 51 917 117 242 | F77: 6975 | H77: =IF(I77>0,10,0) -> 10 | I77: 45545 | J77: 30 | K77: ='Net F'!$I77+'Net F'!$J77 -> 45575 | L77: ='Net F'!$I77+'Net F'!$J77-TODAY() -> -21 | M77: =IF(L77<1,"VENCIDO","VIGENTE") -> VENCIDO
C78: Xiomi | E78: 51 988 684 621 | F78: 8276 | H78: =IF(I78>0,10,0) -> 10 | I78: 45544 | J78: 30 | K78: ='Net F'!$I78+'Net F'!$J78 -> 45574 | L78: ='Net F'!$I78+'Net F'!$J78-TODAY() -> -22 | M78: =IF(L78<1,"VENCIDO","VIGENTE") -> VENCIDO
C79: Joan33 | E79: 51 978 723 526 | F79: 6548 | H79: =IF(I79>0,10,0) -> 10 | I79: 45575 | J79: 30 | K79: ='Net F'!$I79+'Net F'!$J79 -> 45605 | L79: ='Net F'!$I79+'Net F'!$J79-TODAY() -> 9 | M79: =IF(L79<1,"VENCIDO","VIGENTE") -> VIGENTE
C80: Guillermo | E80: 51 988 684 621 | F80: 6975 | H80: =IF(I80>0,10,0) -> 10 | I80: 45540 | J80: 30 | K80: ='Net F'!$I80+'Net F'!$J80 -> 45570 | L80: ='Net F'!$I80+'Net F'!$J80-TODAY() -> -26 | M80: =IF(L80<1,"VENCIDO","VIGENTE") -> VENCIDO
C81: Dorian148 | E81: 51 972 422 546 | F81: 8456 | H81: =IF(I81>0,14,0) -> 14 | I81: 45538 | J81: 30 | K81: ='Net F'!$I81+'Net F'!$J81 -> 45568 | L81: ='Net F'!$I81+'Net F'!$J81-TODAY() -> -28 | M81: =IF(L81<1,"VENCIDO","VIGENTE") -> VENCIDO
C82: Jadiel812 | E82: 51 965 090 265 | F82: 6975 | H82: =IF(I82>0,10,0) -> 10 | I82: 45526 | J82: 30 | K82: ='Net F'!$I82+'Net F'!$J82 -> 45556 | L82: ='Net F'!$I82+'Net F'!$J82-TODAY() -> -40 | M82: =IF(L82<1,"VENCIDO","VIGENTE") -> VENCIDO
C83: Andrea caraguay194 | E83: 593 98 604 2431 | F83: 5277 | G83: $2.5 | H83: =IF(I83>0,10,0) -> 10 | I83: 45554 | J83: 30 | K83: ='Net F'!$I83+'Net F'!$J83 -> 45584 | L83: ='Net F'!$I83+'Net F'!$J83-TODAY() -> -12 | M83: =IF(L83<1,"VENCIDO","VIGENTE") -> VENCIDO
C84: Miguel188 | E84: 593 96 365 3101 | F84: 5597 | H84: =IF(I84>0,10,0) -> 10 | I84: 45528 | J84: 30 | K84: ='Net F'!$I84+'Net F'!$J84 -> 45558 | L84: ='Net F'!$I84+'Net F'!$J84-TODAY() -> -38 | M84: =IF(L84<1,"VENCIDO","VIGENTE") -> VENCIDO
C85: David914 | E85: 51 946 579 911 | F85: 1184 | H85: =IF(I85>0,10,0) -> 10 | I85: 45534 | J85: 30 | K85: ='Net F'!$I85+'Net F'!$J85 -> 45564 | L85: ='Net F'!$I85+'Net F'!$J85-TODAY() -> -32 | M85: =IF(L85<1,"VENCIDO","VIGENTE") -> VENCIDO
C86: Leo344 | E86: 51 955 127 083 | F86: 3455 | H86: =IF(I86>0,10,0) -> 10 | I86: 45568 | J86: 30 | K86: ='Net F'!$I86+'Net F'!$J86 -> 45598 | L86: ='Net F'!$I86+'Net F'!$J86-TODAY() -> 2 | M86: =IF(L86<1,"VENCIDO","VIGENTE") -> VIGENTE
C87: Erick243 | E87: 51 946 579 911 | F87: 2246 | H87: =IF(I87>0,10,0) -> 10 | I87: 45536 | J87: 30 | K87: ='Net F'!$I87+'Net F'!$J87 -> 45566 | L87: ='Net F'!$I87+'Net F'!$J87-TODAY() -> -30 | M87: =IF(L87<1,"VENCIDO","VIGENTE") -> VENCIDO
C88: Richar Rojas26 | E88: 593 99 106 2866 | F88: 6455 | G88: $2.5 | H88: =IF(I88>0,10,0) -> 10 | I88: 45512 | J88: 30 | K88: ='Net F'!$I88+'Net F'!$J88 -> 45542 | L88: ='Net F'!$I88+'Net F'!$J88-TODAY() -> -54 | M88: =IF(L88<1,"VENCIDO","VIGENTE") -> VENCIDO
C89: Hatsumi371 | F89: 6975 | H89: =IF(I89>0,10,0) -> 10 | I89: 45595 | J89: 30 | K89: ='Net F'!$I89+'Net F'!$J89 -> 45625 | L89: ='Net F'!$I89+'Net F'!$J89-TODAY() -> 29 | M89: =IF(L89<1,"VENCIDO","VIGENTE") -> VIGENTE
C90: Thaira822 | E90: 51 946 579 911 | F90: 2833 | H90: =IF(I90>0,10,0) -> 10 | I90: 45566 | J90: 30 | K90: ='Net F'!$I90+'Net F'!$J90 -> 45596 | L90: ='Net F'!$I90+'Net F'!$J90-TODAY() -> 0 | M90: =IF(L90<1,"VENCIDO","VIGENTE") -> VENCIDO
C91: oscar65 | E91: 51 946 998 173 | F91: 2566 | H91: =IF(I91>0,10,0) -> 10 | I91: 45572 | J91: 30 | K91: ='Net F'!$I91+'Net F'!$J91 -> 45602 | L91: ='Net F'!$I91+'Net F'!$J91-TODAY() -> 6 | M91: =IF(L91<1,"VENCIDO","VIGENTE") -> VIGENTE
C92: Jachelit18 | E92: 51 988 684 621 | F92: 6728 | H92: =IF(I92>0,9,0) -> 9 | I92: 45573 | J92: 30 | K92: ='Net F'!$I92+'Net F'!$J92 -> 45603 | L92: ='Net F'!$I92+'Net F'!$J92-TODAY() -> 7 | M92: =IF(L92<1,"VENCIDO","VIGENTE") -> VIGENTE
C93: Sr:jp | E93: 593 98 484 3636 | F93: 1583 | G93: $2.5 | H93: =IF(I93>0,10,0) -> 10 | I93: 45565 | J93: 30 | K93: ='Net F'!$I93+'Net F'!$J93 -> 45595 | L93: ='Net F'!$I93+'Net F'!$J93-TODAY() -> -1 | M93: =IF(L93<1,"VENCIDO","VIGENTE") -> VENCIDO
C94: Andrea25 | E94: 593 96 365 3101 | F94: 3569 | G94: $2.5 | H94: =IF(I94>0,10,0) -> 10 | I94: 45572 | J94: 30 | K94: ='Net F'!$I94+'Net F'!$J94 -> 45602 | L94: ='Net F'!$I94+'Net F'!$J94-TODAY() -> 6 | M94: =IF(L94<1,"VENCIDO","VIGENTE") -> VIGENTE
C95: García Moreira36 | E95: 593 96 905 2056 | F95: 2979 | G95: $2.5 | H95: =IF(I95>0,10,0) -> 10 | I95: 45553 | J95: 30 | K95: ='Net F'!$I95+'Net F'!$J95 -> 45583 | L95: ='Net F'!$I95+'Net F'!$J95-TODAY() -> -13 | M95: =IF(L95<1,"VENCIDO","VIGENTE") -> VENCIDO
C96: Cesia72 | E96: 51 935 106 616 | F96: 2833 | H96: =IF(I96>0,10,0) -> 10 | I96: 45546 | J96: 30 | K96: ='Net F'!$I96+'Net F'!$J96 -> 45576 | L96: ='Net F'!$I96+'Net F'!$J96-TODAY() -> -20 | M96: =IF(L96<1,"VENCIDO","VIGENTE") -> VENCIDO
C97: Geraldine22 | E97: 51 946 579 911 | F97: 1195 | H97: =IF(I97>0,10,0) -> 10 | I97: 45572 | J97: 30 | K97: ='Net F'!$I97+'Net F'!$J97 -> 45602 | L97: ='Net F'!$I97+'Net F'!$J97-TODAY() -> 6 | M97: =IF(L97<1,"VENCIDO","VIGENTE") -> VIGENTE
C98: Vásquez832 | E98: 51 917 117 242 | F98: 5844 | H98: =IF(I98>0,8,0) -> 8 | I98: 45567 | J98: 30 | K98: ='Net F'!$I98+'Net F'!$J98 -> 45597 | L98: ='Net F'!$I98+'Net F'!$J98-TODAY() -> 1 | M98: =IF(L98<1,"VENCIDO","VIGENTE") -> VIGENTE
C99: Joselin27 | E99: 593 98 306 6636 | F99: 9467 | H99: =IF(I99>0,10,0) -> 10 | I99: 45402 | J99: 30 | K99: ='Net F'!$I99+'Net F'!$J99 -> 45432 | L99: ='Net F'!$I99+'Net F'!$J99-TODAY() -> -164 | M99: =IF(L99<1,"VENCIDO","VIGENTE") -> VENCIDO
C100: Hatsumi8744 | E100: 51 946 579 911 | F100: 4468 | H100: =IF(I100>0,10,0) -> 10 | I100: 45574 | J100: 30 | K100: ='Net F'!$I100+'Net F'!$J100 -> 45604 | L100: ='Net F'!$I100+'Net F'!$J100-TODAY() -> 8 | M100: =IF(L100<1,"VENCIDO","VIGENTE") -> VIGENTE
B101: fiado | C101: Emerson13 | E101: 51 977 445 276 | F101: 7881 | H101: =IF(I101>0,10,0) -> 10 | I101: 45575 | J101: 30 | K101: ='Net F'!$I101+'Net F'!$J101 -> 45605 | L101: ='Net F'!$I101+'Net F'!$J101-TODAY() -> 9 | M101: =IF(L101<1,"VENCIDO","VIGENTE") -> VIGENTE
C102: Nancy664 | E102: 51 946 579 911 | F102: 5466 | H102: =IF(I102>0,10,0) -> 10 | I102: 45573 | J102: 30 | K102: ='Net F'!$I102+'Net F'!$J102 -> 45603 | L102: ='Net F'!$I102+'Net F'!$J102-TODAY() -> 7 | M102: =IF(L102<1,"VENCIDO","VIGENTE") -> VIGENTE
C103: Estrella36 | E103: 51 917 117 242 | F103: 4476 | H103: =IF(I103>0,8,0) -> 8 | I103: 45571 | J103: 30 | K103: ='Net F'!$I103+'Net F'!$J103 -> 45601 | L103: ='Net F'!$I103+'Net F'!$J103-TODAY() -> 5 | M103: =IF(L103<1,"VENCIDO","VIGENTE") -> VIGENTE
C104: Jhonatan817 | E104: 593 99 803 3836 | F104: 1134 | G104: $2.5 | H104: =IF(I104>0,10,0) -> 10 | I104: 45558 | J104: 30 | K104: ='Net F'!$I104+'Net F'!$J104 -> 45588 | L104: ='Net F'!$I104+'Net F'!$J104-TODAY() -> -8 | M104: =IF(L104<1,"VENCIDO","VIGENTE") -> VENCIDO
B105: de jero | C105: Gabo173 | F105: 2843 | H105: =IF(I105>0,10,0) -> 10 | I105: 45611 | J105: 30 | K105: ='Net F'!$I105+'Net F'!$J105 -> 45641 | L105: ='Net F'!$I105+'Net F'!$J105-TODAY() -> 45 | M105: =IF(L105<1,"VENCIDO","VIGENTE") -> VIGENTE
...

Sheet Net R
B6: =TODAY() -> 45596
B7: CUENTA | C7: Contraseña | D7: CLAVE | E7: Facturacion | F7: PIN PERFIL | G7: PRECIO | H7: FECHA DE INICIO | I7: DIAS | J7: FECHA DE VENCIMIENTO | K7: ALARMA | L7: ESTADO
B8: correo: byhimhas@uma3.be | C8: dek53ver4521n | G8: =IF(H8>0,30,0) -> 30 | H8: 45350 | I8: 30 | J8: =+'Net R'!$H8+'Net R'!$I8 -> 45380 | K8: ='Net R'!$H8+'Net R'!$I8-TODAY() -> -216 | L8: =IF(K8<1,"VENCIDO","VIGENTE") -> VENCIDO
G9: =IF(H9>0,30,0) -> 0 | I9: 30 | J9: =+'Net R'!$H9+'Net R'!$I9 -> 30 | K9: ='Net R'!$H9+'Net R'!$I9-TODAY() -> -45566 | L9: =IF(K9<1,"VENCIDO","VIGENTE") -> VENCIDO
G10: =IF(H10>0,30,0) -> 0 | I10: 30 | J10: =+'Net R'!$H10+'Net R'!$I10 -> 30 | K10: ='Net R'!$H10+'Net R'!$I10-TODAY() -> -45566 | L10: =IF(K10<1,"VENCIDO","VIGENTE") -> VENCIDO
G11: =IF(H11>0,30,0) -> 0 | I11: 30 | J11: =+'Net R'!$H11+'Net R'!$I11 -> 30 | K11: ='Net R'!$H11+'Net R'!$I11-TODAY() -> -45566 | L11: =IF(K11<1,"VENCIDO","VIGENTE") -> VENCIDO
G12: =IF(H12>0,30,0) -> 0 | I12: 30 | J12: =+'Net R'!$H12+'Net R'!$I12 -> 30 | K12: ='Net R'!$H12+'Net R'!$I12-TODAY() -> -45566 | L12: =IF(K12<1,"VENCIDO","VIGENTE") -> VENCIDO
G13: =IF(H13>0,30,0) -> 0 | I13: 30 | J13: =+'Net R'!$H13+'Net R'!$I13 -> 30 | K13: ='Net R'!$H13+'Net R'!$I13-TODAY() -> -45566 | L13: =IF(K13<1,"VENCIDO","VIGENTE") -> VENCIDO
G14: =IF(H14>0,30,0) -> 0 | I14: 30 | J14: =+'Net R'!$H14+'Net R'!$I14 -> 30 | K14: ='Net R'!$H14+'Net R'!$I14-TODAY() -> -45566 | L14: =IF(K14<1,"VENCIDO","VIGENTE") -> VENCIDO
G15: =IF(H15>0,30,0) -> 0 | I15: 30 | J15: =+'Net R'!$H15+'Net R'!$I15 -> 30 | K15: ='Net R'!$H15+'Net R'!$I15-TODAY() -> -45566 | L15: =IF(K15<1,"VENCIDO","VIGENTE") -> VENCIDO
G16: =IF(H16>0,30,0) -> 0 | I16: 30 | J16: =+'Net R'!$H16+'Net R'!$I16 -> 30 | K16: ='Net R'!$H16+'Net R'!$I16-TODAY() -> -45566 | L16: =IF(K16<1,"VENCIDO","VIGENTE") -> VENCIDO
G17: =IF(H17>0,30,0) -> 0 | I17: 30 | J17: =+'Net R'!$H17+'Net R'!$I17 -> 30 | K17: ='Net R'!$H17+'Net R'!$I17-TODAY() -> -45566 | L17: =IF(K17<1,"VENCIDO","VIGENTE") -> VENCIDO
G18: =IF(H18>0,30,0) -> 0 | I18: 30 | J18: =+'Net R'!$H18+'Net R'!$I18 -> 30 | K18: ='Net R'!$H18+'Net R'!$I18-TODAY() -> -45566 | L18: =IF(K18<1,"VENCIDO","VIGENTE") -> VENCIDO
G19: =IF(H19>0,30,0) -> 0 | I19: 30 | J19: =+'Net R'!$H19+'Net R'!$I19 -> 30 | K19: ='Net R'!$H19+'Net R'!$I19-TODAY() -> -45566 | L19: =IF(K19<1,"VENCIDO","VIGENTE") -> VENCIDO
G20: =IF(H20>0,30,0) -> 0 | I20: 30 | J20: =+'Net R'!$H20+'Net R'!$I20 -> 30 | K20: ='Net R'!$H20+'Net R'!$I20-TODAY() -> -45566 | L20: =IF(K20<1,"VENCIDO","VIGENTE") -> VENCIDO
G21: =SUM(G8:G20) -> 30
B26: Cuentas Disney
B27: =TODAY() -> 45596
B28: CUENTA | C28: Contraseña | D28: CLAVE | E28: Facturacion | F28: PIN PERFIL | G28: PRECIO | H28: FECHA DE INICIO | I28: DIAS | J28: FECHA DE VENCIMIENTO | K28: ALARMA | L28: ESTADO
G29: =IF(H29>0,30,0) -> 0 | I29: 30 | J29: =+'Net R'!$H29+'Net R'!$I29 -> 30 | K29: ='Net R'!$H29+'Net R'!$I29-TODAY() -> -45566 | L29: =IF(K29<1,"VENCIDO","VIGENTE") -> VENCIDO
G30: =IF(H30>0,30,0) -> 0 | I30: 30 | J30: =+'Net R'!$H30+'Net R'!$I30 -> 30 | K30: ='Net R'!$H30+'Net R'!$I30-TODAY() -> -45566 | L30: =IF(K30<1,"VENCIDO","VIGENTE") -> VENCIDO
G31: =IF(H31>0,30,0) -> 0 | I31: 30 | J31: =+'Net R'!$H31+'Net R'!$I31 -> 30 | K31: ='Net R'!$H31+'Net R'!$I31-TODAY() -> -45566 | L31: =IF(K31<1,"VENCIDO","VIGENTE") -> VENCIDO
G32: =IF(H32>0,30,0) -> 0 | I32: 30 | J32: =+'Net R'!$H32+'Net R'!$I32 -> 30 | K32: ='Net R'!$H32+'Net R'!$I32-TODAY() -> -45566 | L32: =IF(K32<1,"VENCIDO","VIGENTE") -> VENCIDO
G33: =IF(H33>0,30,0) -> 0 | I33: 30 | J33: =+'Net R'!$H33+'Net R'!$I33 -> 30 | K33: ='Net R'!$H33+'Net R'!$I33-TODAY() -> -45566 | L33: =IF(K33<1,"VENCIDO","VIGENTE") -> VENCIDO
G34: =IF(H34>0,30,0) -> 0 | I34: 30 | J34: =+'Net R'!$H34+'Net R'!$I34 -> 30 | K34: ='Net R'!$H34+'Net R'!$I34-TODAY() -> -45566 | L34: =IF(K34<1,"VENCIDO","VIGENTE") -> VENCIDO
G35: =IF(H35>0,30,0) -> 0 | I35: 30 | J35: =+'Net R'!$H35+'Net R'!$I35 -> 30 | K35: ='Net R'!$H35+'Net R'!$I35-TODAY() -> -45566 | L35: =IF(K35<1,"VENCIDO","VIGENTE") -> VENCIDO
G36: =IF(H36>0,30,0) -> 0 | I36: 30 | J36: =+'Net R'!$H36+'Net R'!$I36 -> 30 | K36: ='Net R'!$H36+'Net R'!$I36-TODAY() -> -45566 | L36: =IF(K36<1,"VENCIDO","VIGENTE") -> VENCIDO
G37: =IF(H37>0,30,0) -> 0 | I37: 30 | J37: =+'Net R'!$H37+'Net R'!$I37 -> 30 | K37: ='Net R'!$H37+'Net R'!$I37-TODAY() -> -45566 | L37: =IF(K37<1,"VENCIDO","VIGENTE") -> VENCIDO
G38: =IF(H38>0,30,0) -> 0 | I38: 30 | J38: =+'Net R'!$H38+'Net R'!$I38 -> 30 | K38: ='Net R'!$H38+'Net R'!$I38-TODAY() -> -45566 | L38: =IF(K38<1,"VENCIDO","VIGENTE") -> VENCIDO
G39: =IF(H39>0,30,0) -> 0 | I39: 30 | J39: =+'Net R'!$H39+'Net R'!$I39 -> 30 | K39: ='Net R'!$H39+'Net R'!$I39-TODAY() -> -45566 | L39: =IF(K39<1,"VENCIDO","VIGENTE") -> VENCIDO
G40: =IF(H40>0,30,0) -> 0 | I40: 30 | J40: =+'Net R'!$H40+'Net R'!$I40 -> 30 | K40: ='Net R'!$H40+'Net R'!$I40-TODAY() -> -45566 | L40: =IF(K40<1,"VENCIDO","VIGENTE") -> VENCIDO
G41: =IF(H41>0,30,0) -> 0 | I41: 30 | J41: =+'Net R'!$H41+'Net R'!$I41 -> 30 | K41: ='Net R'!$H41+'Net R'!$I41-TODAY() -> -45566 | L41: =IF(K41<1,"VENCIDO","VIGENTE") -> VENCIDO
G42: =SUM(G29:G41) -> 0
B48: =TODAY() -> 45596
B49: CUENTA | C49: Contraseña | D49: CLAVE | E49: Facturacion | F49: PIN PERFIL | G49: PRECIO | H49: FECHA DE INICIO | I49: DIAS | J49: FECHA DE VENCIMIENTO | K49: ALARMA | L49: ESTADO
G50: =IF(H50>0,30,0) -> 0 | I50: 30 | J50: =+'Net R'!$H50+'Net R'!$I50 -> 30 | K50: ='Net R'!$H50+'Net R'!$I50-TODAY() -> -45566 | L50: =IF(K50<1,"VENCIDO","VIGENTE") -> VENCIDO
G51: =IF(H51>0,30,0) -> 0 | I51: 30 | J51: =+'Net R'!$H51+'Net R'!$I51 -> 30 | K51: ='Net R'!$H51+'Net R'!$I51-TODAY() -> -45566 | L51: =IF(K51<1,"VENCIDO","VIGENTE") -> VENCIDO
G52: =IF(H52>0,30,0) -> 0 | I52: 30 | J52: =+'Net R'!$H52+'Net R'!$I52 -> 30 | K52: ='Net R'!$H52+'Net R'!$I52-TODAY() -> -45566 | L52: =IF(K52<1,"VENCIDO","VIGENTE") -> VENCIDO
G53: =IF(H53>0,30,0) -> 0 | I53: 30 | J53: =+'Net R'!$H53+'Net R'!$I53 -> 30 | K53: ='Net R'!$H53+'Net R'!$I53-TODAY() -> -45566 | L53: =IF(K53<1,"VENCIDO","VIGENTE") -> VENCIDO
G54: =IF(H54>0,30,0) -> 0 | I54: 30 | J54: =+'Net R'!$H54+'Net R'!$I54 -> 30 | K54: ='Net R'!$H54+'Net R'!$I54-TODAY() -> -45566 | L54: =IF(K54<1,"VENCIDO","VIGENTE") -> VENCIDO
G55: =IF(H55>0,30,0) -> 0 | I55: 30 | J55: =+'Net R'!$H55+'Net R'!$I55 -> 30 | K55: ='Net R'!$H55+'Net R'!$I55-TODAY() -> -45566 | L55: =IF(K55<1,"VENCIDO","VIGENTE") -> VENCIDO
G56: =IF(H56>0,30,0) -> 0 | I56: 30 | J56: =+'Net R'!$H56+'Net R'!$I56 -> 30 | K56: ='Net R'!$H56+'Net R'!$I56-TODAY() -> -45566 | L56: =IF(K56<1,"VENCIDO","VIGENTE") -> VENCIDO
G57: =IF(H57>0,30,0) -> 0 | I57: 30 | J57: =+'Net R'!$H57+'Net R'!$I57 -> 30 | K57: ='Net R'!$H57+'Net R'!$I57-TODAY() -> -45566 | L57: =IF(K57<1,"VENCIDO","VIGENTE") -> VENCIDO
G58: =IF(H58>0,30,0) -> 0 | I58: 30 | J58: =+'Net R'!$H58+'Net R'!$I58 -> 30 | K58: ='Net R'!$H58+'Net R'!$I58-TODAY() -> -45566 | L58: =IF(K58<1,"VENCIDO","VIGENTE") -> VENCIDO
G59: =IF(H59>0,30,0) -> 0 | I59: 30 | J59: =+'Net R'!$H59+'Net R'!$I59 -> 30 | K59: ='Net R'!$H59+'Net R'!$I59-TODAY() -> -45566 | L59: =IF(K59<1,"VENCIDO","VIGENTE") -> VENCIDO
G60: =IF(H60>0,30,0) -> 0 | I60: 30 | J60: =+'Net R'!$H60+'Net R'!$I60 -> 30 | K60: ='Net R'!$H60+'Net R'!$I60-TODAY() -> -45566 | L60: =IF(K60<1,"VENCIDO","VIGENTE") -> VENCIDO
G61: =IF(H61>0,30,0) -> 0 | I61: 30 | J61: =+'Net R'!$H61+'Net R'!$I61 -> 30 | K61: ='Net R'!$H61+'Net R'!$I61-TODAY() -> -45566 | L61: =IF(K61<1,"VENCIDO","VIGENTE") -> VENCIDO
G62: =IF(H62>0,30,0) -> 0 | I62: 30 | J62: =+'Net R'!$H62+'Net R'!$I62 -> 30 | K62: ='Net R'!$H62+'Net R'!$I62-TODAY() -> -45566 | L62: =IF(K62<1,"VENCIDO","VIGENTE") -> VENCIDO
G63: =SUM(G50:G62) -> 0
B69: =TODAY() -> 45596
B70: CUENTA | C70: Contraseña | D70: CLAVE | E70: Facturacion | F70: PIN PERFIL | G70: PRECIO | H70: FECHA DE INICIO | I70: DIAS | J70: FECHA DE VENCIMIENTO | K70: ALARMA | L70: ESTADO
G71: =IF(H71>0,30,0) -> 0 | I71: 30 | J71: =+'Net R'!$H71+'Net R'!$I71 -> 30 | K71: ='Net R'!$H71+'Net R'!$I71-TODAY() -> -45566 | L71: =IF(K71<1,"VENCIDO","VIGENTE") -> VENCIDO
G72: =IF(H72>0,30,0) -> 0 | I72: 30 | J72: =+'Net R'!$H72+'Net R'!$I72 -> 30 | K72: ='Net R'!$H72+'Net R'!$I72-TODAY() -> -45566 | L72: =IF(K72<1,"VENCIDO","VIGENTE") -> VENCIDO
G73: =IF(H73>0,30,0) -> 0 | I73: 30 | J73: =+'Net R'!$H73+'Net R'!$I73 -> 30 | K73: ='Net R'!$H73+'Net R'!$I73-TODAY() -> -45566 | L73: =IF(K73<1,"VENCIDO","VIGENTE") -> VENCIDO
G74: =IF(H74>0,30,0) -> 0 | I74: 30 | J74: =+'Net R'!$H74+'Net R'!$I74 -> 30 | K74: ='Net R'!$H74+'Net R'!$I74-TODAY() -> -45566 | L74: =IF(K74<1,"VENCIDO","VIGENTE") -> VENCIDO
G75: =IF(H75>0,30,0) -> 0 | I75: 30 | J75: =+'Net R'!$H75+'Net R'!$I75 -> 30 | K75: ='Net R'!$H75+'Net R'!$I75-TODAY() -> -45566 | L75: =IF(K75<1,"VENCIDO","VIGENTE") -> VENCIDO
G76: =IF(H76>0,30,0) -> 0 | I76: 30 | J76: =+'Net R'!$H76+'Net R'!$I76 -> 30 | K76: ='Net R'!$H76+'Net R'!$I76-TODAY() -> -45566 | L76: =IF(K76<1,"VENCIDO","VIGENTE") -> VENCIDO
G77: =IF(H77>0,30,0) -> 0 | I77: 30 | J77: =+'Net R'!$H77+'Net R'!$I77 -> 30 | K77: ='Net R'!$H77+'Net R'!$I77-TODAY() -> -45566 | L77: =IF(K77<1,"VENCIDO","VIGENTE") -> VENCIDO
G78: =IF(H78>0,30,0) -> 0 | I78: 30 | J78: =+'Net R'!$H78+'Net R'!$I78 -> 30 | K78: ='Net R'!$H78+'Net R'!$I78-TODAY() -> -45566 | L78: =IF(K78<1,"VENCIDO","VIGENTE") -> VENCIDO
G79: =IF(H79>0,30,0) -> 0 | I79: 30 | J79: =+'Net R'!$H79+'Net R'!$I79 -> 30 | K79: ='Net R'!$H79+'Net R'!$I79-TODAY() -> -45566 | L79: =IF(K79<1,"VENCIDO","VIGENTE") -> VENCIDO
G80: =IF(H80>0,30,0) -> 0 | I80: 30 | J80: =+'Net R'!$H80+'Net R'!$I80 -> 30 | K80: ='Net R'!$H80+'Net R'!$I80-TODAY() -> -45566 | L80: =IF(K80<1,"VENCIDO","VIGENTE") -> VENCIDO
G81: =IF(H81>0,30,0) -> 0 | I81: 30 | J81: =+'Net R'!$H81+'Net R'!$I81 -> 30 | K81: ='Net R'!$H81+'Net R'!$I81-TODAY() -> -45566 | L81: =IF(K81<1,"VENCIDO","VIGENTE") -> VENCIDO
G82: =IF(H82>0,30,0) -> 0 | I82: 30 | J82: =+'Net R'!$H82+'Net R'!$I82 -> 30 | K82: ='Net R'!$H82+'Net R'!$I82-TODAY() -> -45566 | L82: =IF(K82<1,"VENCIDO","VIGENTE") -> VENCIDO
G83: =IF(H83>0,30,0) -> 0 | I83: 30 | J83: =+'Net R'!$H83+'Net R'!$I83 -> 30 | K83: ='Net R'!$H83+'Net R'!$I83-TODAY() -> -45566 | L83: =IF(K83<1,"VENCIDO","VIGENTE") -> VENCIDO
G84: =SUM(G71:G83) -> 0
B90: =TODAY() -> 45596
B91: CUENTA | C91: Contraseña | D91: CLAVE | E91: Facturacion | F91: PIN PERFIL | G91: PRECIO | H91: FECHA DE INICIO | I91: DIAS | J91: FECHA DE VENCIMIENTO | K91: ALARMA | L91: ESTADO
G92: =IF(H92>0,30,0) -> 0 | I92: 30 | J92: =+'Net R'!$H92+'Net R'!$I92 -> 30 | K92: ='Net R'!$H92+'Net R'!$I92-TODAY() -> -45566 | L92: =IF(K92<1,"VENCIDO","VIGENTE") -> VENCIDO
G93: =IF(H93>0,30,0) -> 0 | I93: 30 | J93: =+'Net R'!$H93+'Net R'!$I93 -> 30 | K93: ='Net R'!$H93+'Net R'!$I93-TODAY() -> -45566 | L93: =IF(K93<1,"VENCIDO","VIGENTE") -> VENCIDO
G94: =IF(H94>0,30,0) -> 0 | I94: 30 | J94: =+'Net R'!$H94+'Net R'!$I94 -> 30 | K94: ='Net R'!$H94+'Net R'!$I94-TODAY() -> -45566 | L94: =IF(K94<1,"VENCIDO","VIGENTE") -> VENCIDO
G95: =IF(H95>0,30,0) -> 0 | I95: 30 | J95: =+'Net R'!$H95+'Net R'!$I95 -> 30 | K95: ='Net R'!$H95+'Net R'!$I95-TODAY() -> -45566 | L95: =IF(K95<1,"VENCIDO","VIGENTE") -> VENCIDO
G96: =IF(H96>0,30,0) -> 0 | I96: 30 | J96: =+'Net R'!$H96+'Net R'!$I96 -> 30 | K96: ='Net R'!$H96+'Net R'!$I96-TODAY() -> -45566 | L96: =IF(K96<1,"VENCIDO","VIGENTE") -> VENCIDO
G97: =IF(H97>0,30,0) -> 0 | I97: 30 | J97: =+'Net R'!$H97+'Net R'!$I97 -> 30 | K97: ='Net R'!$H97+'Net R'!$I97-TODAY() -> -45566 | L97: =IF(K97<1,"VENCIDO","VIGENTE") -> VENCIDO
G98: =IF(H98>0,30,0) -> 0 | I98: 30 | J98: =+'Net R'!$H98+'Net R'!$I98 -> 30 | K98: ='Net R'!$H98+'Net R'!$I98-TODAY() -> -45566 | L98: =IF(K98<1,"VENCIDO","VIGENTE") -> VENCIDO
G99: =IF(H99>0,30,0) -> 0 | I99: 30 | J99: =+'Net R'!$H99+'Net R'!$I99 -> 30 | K99: ='Net R'!$H99+'Net R'!$I99-TODAY() -> -45566 | L99: =IF(K99<1,"VENCIDO","VIGENTE") -> VENCIDO
G100: =IF(H100>0,30,0) -> 0 | I100: 30 | J100: =+'Net R'!$H100+'Net R'!$I100 -> 30 | K100: ='Net R'!$H100+'Net R'!$I100-TODAY() -> -45566 | L100: =IF(K100<1,"VENCIDO","VIGENTE") -> VENCIDO
G101: =IF(H101>0,30,0) -> 0 | I101: 30 | J101: =+'Net R'!$H101+'Net R'!$I101 -> 30 | K101: ='Net R'!$H101+'Net R'!$I101-TODAY() -> -45566 | L101: =IF(K101<1,"VENCIDO","VIGENTE") -> VENCIDO
G102: =IF(H102>0,30,0) -> 0 | I102: 30 | J102: =+'Net R'!$H102+'Net R'!$I102 -> 30 | K102: ='Net R'!$H102+'Net R'!$I102-TODAY() -> -45566 | L102: =IF(K102<1,"VENCIDO","VIGENTE") -> VENCIDO
G103: =IF(H103>0,30,0) -> 0 | I103: 30 | J103: =+'Net R'!$H103+'Net R'!$I103 -> 30 | K103: ='Net R'!$H103+'Net R'!$I103-TODAY() -> -45566 | L103: =IF(K103<1,"VENCIDO","VIGENTE") -> VENCIDO
G104: =IF(H104>0,30,0) -> 0 | I104: 30 | J104: =+'Net R'!$H104+'Net R'!$I104 -> 30 | K104: ='Net R'!$H104+'Net R'!$I104-TODAY() -> -45566 | L104: =IF(K104<1,"VENCIDO","VIGENTE") -> VENCIDO
G105: =SUM(G92:G104) -> 0
B111: =TODAY() -> 45596
B112: CUENTA | C112: Contraseña | D112: CLAVE | E112: Facturacion | F112: PIN PERFIL | G112: PRECIO | H112: FECHA DE INICIO | I112: DIAS | J112: FECHA DE VENCIMIENTO | K112: ALARMA | L112: ESTADO
G113: =IF(H113>0,30,0) -> 0 | I113: 30 | J113: =+'Net R'!$H113+'Net R'!$I113 -> 30 | K113: ='Net R'!$H113+'Net R'!$I113-TODAY() -> -45566 | L113: =IF(K113<1,"VENCIDO","VIGENTE") -> VENCIDO
G114: =IF(H114>0,30,0) -> 0 | I114: 30 | J114: =+'Net R'!$H114+'Net R'!$I114 -> 30 | K114: ='Net R'!$H114+'Net R'!$I114-TODAY() -> -45566 | L114: =IF(K114<1,"VENCIDO","VIGENTE") -> VENCIDO
G115: =IF(H115>0,30,0) -> 0 | I115: 30 | J115: =+'Net R'!$H115+'Net R'!$I115 -> 30 | K115: ='Net R'!$H115+'Net R'!$I115-TODAY() -> -45566 | L115: =IF(K115<1,"VENCIDO","VIGENTE") -> VENCIDO
G116: =IF(H116>0,30,0) -> 0 | I116: 30 | J116: =+'Net R'!$H116+'Net R'!$I116 -> 30 | K116: ='Net R'!$H116+'Net R'!$I116-TODAY() -> -45566 | L116: =IF(K116<1,"VENCIDO","VIGENTE") -> VENCIDO
G117: =IF(H117>0,30,0) -> 0 | I117: 30 | J117: =+'Net R'!$H117+'Net R'!$I117 -> 30 | K117: ='Net R'!$H117+'Net R'!$I117-TODAY() -> -45566 | L117: =IF(K117<1,"VENCIDO","VIGENTE") -> VENCIDO
G118: =IF(H118>0,30,0) -> 0 | I118: 30 | J118: =+'Net R'!$H118+'Net R'!$I118 -> 30 | K118: ='Net R'!$H118+'Net R'!$I118-TODAY() -> -45566 | L118: =IF(K118<1,"VENCIDO","VIGENTE") -> VENCIDO
G119: =IF(H119>0,30,0) -> 0 | I119: 30 | J119: =+'Net R'!$H119+'Net R'!$I119 -> 30 | K119: ='Net R'!$H119+'Net R'!$I119-TODAY() -> -45566 | L119: =IF(K119<1,"VENCIDO","VIGENTE") -> VENCIDO
G120: =IF(H120>0,30,0) -> 0 | I120: 30 | J120: =+'Net R'!$H120+'Net R'!$I120 -> 30 | K120: ='Net R'!$H120+'Net R'!$I120-TODAY() -> -45566 | L120: =IF(K120<1,"VENCIDO","VIGENTE") -> VENCIDO
G121: =IF(H121>0,30,0) -> 0 | I121: 30 | J121: =+'Net R'!$H121+'Net R'!$I121 -> 30 | K121: ='Net R'!$H121+'Net R'!$I121-TODAY() -> -45566 | L121: =IF(K121<1,"VENCIDO","VIGENTE") -> VENCIDO
G122: =IF(H122>0,30,0) -> 0 | I122: 30 | J122: =+'Net R'!$H122+'Net R'!$I122 -> 30 | K122: ='Net R'!$H122+'Net R'!$I122-TODAY() -> -45566 | L122: =IF(K122<1,"VENCIDO","VIGENTE") -> VENCIDO
G123: =IF(H123>0,30,0) -> 0 | I123: 30 | J123: =+'Net R'!$H123+'Net R'!$I123 -> 30 | K123: ='Net R'!$H123+'Net R'!$I123-TODAY() -> -45566 | L123: =IF(K123<1,"VENCIDO","VIGENTE") -> VENCIDO
G124: =IF(H124>0,30,0) -> 0 | I124: 30 | J124: =+'Net R'!$H124+'Net R'!$I124 -> 30 | K124: ='Net R'!$H124+'Net R'!$I124-TODAY() -> -45566 | L124: =IF(K124<1,"VENCIDO","VIGENTE") -> VENCIDO
G125: =IF(H125>0,30,0) -> 0 | I125: 30 | J125: =+'Net R'!$H125+'Net R'!$I125 -> 30 | K125: ='Net R'!$H125+'Net R'!$I125-TODAY() -> -45566 | L125: =IF(K125<1,"VENCIDO","VIGENTE") -> VENCIDO
G126: =SUM(G113:G125) -> 0
B132: =TODAY() -> 45596
B133: CUENTA | C133: Contraseña | D133: CLAVE | E133: Facturacion | F133: PIN PERFIL | G133: PRECIO | H133: FECHA DE INICIO | I133: DIAS | J133: FECHA DE VENCIMIENTO | K133: ALARMA | L133: ESTADO
G134: =IF(H134>0,30,0) -> 0 | I134: 30 | J134: =+'Net R'!$H134+'Net R'!$I134 -> 30 | K134: ='Net R'!$H134+'Net R'!$I134-TODAY() -> -45566 | L134: =IF(K134<1,"VENCIDO","VIGENTE") -> VENCIDO
...

Sheet star F (2)
B5: ALERTA DIAS
B6: =TODAY() -> 45596
B7: CUENTA 1 | C7: NOMBRE | D7: CLAVE | E7: TELEFONO | F7: PIN PERFIL | G7: PRECIO | H7: FECHA DE INICIO | I7: DIAS | J7: FECHA DE VENCIMIENTO | K7: ALARMA | L7: ESTADO
B8: CORREO: guert2303dek@gmail.com CONTRASEÑA: de334me213 | C8: Cristhian933 | F8: 1876 | G8: 3.5 | H8: 45360 | I8: 30 | J8: =CORREOSnetflix!J4 -> 45608 | K8: ='star F (2)'!$H8+'star F (2)'!$I8-TODAY() -> -206 | L8: =IF(K8<1,"VENCIDO","VIGENTE") -> VENCIDO
C9: guillermo354 | F9: 5056 | G9: 3.5 | H9: 45346 | I9: 30 | J9: =+'star F (2)'!$H9+'star F (2)'!$I9 -> 45376 | K9: ='star F (2)'!$H9+'star F (2)'!$I9-TODAY() -> -220 | L9: =IF(K9<1,"VENCIDO","VIGENTE") -> VENCIDO
C10: josue245 | F10: 5058 | G10: 3.5 | H10: 45351 | I10: 30 | J10: =+'star F (2)'!$H10+'star F (2)'!$I10 -> 45381 | K10: ='star F (2)'!$H10+'star F (2)'!$I10-TODAY() -> -215 | L10: =IF(K10<1,"VENCIDO","VIGENTE") -> VENCIDO
C11: Luis61 | F11: 2748 | G11: 3.5 | H11: 45354 | I11: 30 | J11: =+'star F (2)'!$H11+'star F (2)'!$I11 -> 45384 | K11: ='star F (2)'!$H11+'star F (2)'!$I11-TODAY() -> -212 | L11: =IF(K11<1,"VENCIDO","VIGENTE") -> VENCIDO
C12: Luis732 | F12: 4699 | G12: 3.5 | H12: 45360 | I12: 30 | J12: =+'star F (2)'!$H12+'star F (2)'!$I12 -> 45390 | K12: ='star F (2)'!$H12+'star F (2)'!$I12-TODAY() -> -206 | L12: =IF(K12<1,"VENCIDO","VIGENTE") -> VENCIDO
C13: MAyreli64 | F13: 5103 | G13: 3.5 | H13: 45350 | I13: 30 | J13: =+'star F (2)'!$H13+'star F (2)'!$I13 -> 45380 | K13: ='star F (2)'!$H13+'star F (2)'!$I13-TODAY() -> -216 | L13: =IF(K13<1,"VENCIDO","VIGENTE") -> VENCIDO
C14: rosmery64 | G14: =IF(H14>0,7,0) -> 7 | H14: 45350 | I14: 30 | J14: =+'star F (2)'!$H14+'star F (2)'!$I14 -> 45380 | K14: ='star F (2)'!$H14+'star F (2)'!$I14-TODAY() -> -216 | L14: =IF(K14<1,"VENCIDO","VIGENTE") -> VENCIDO
C15: PERFILES : | F15: =SUM(F8:F14) -> 24540 | G15: =SUM(G8:G14) -> 28 | I15: 30 | J15: =+'star F (2)'!$H15+'star F (2)'!$I15 -> 30 | K15: ='star F (2)'!$H15+'star F (2)'!$I15-TODAY() -> -45566
B22: ALERTA DIAS
B23: =TODAY() -> 45596
B24: CUENTA | C24: NOMBRE | D24: CLAVE | E24: TELEFONO | F24: PIN PERFIL | G24: PRECIO | H24: FECHA DE INICIO | I24: DIAS | J24: FECHA DE VENCIMIENTO | K24: ALARMA | L24: ESTADO
B25: CORREO : lunigu332dek@gmail.com CONTRASEÑA: verde75144 | F25: 4268 | G25: 3.5 | I25: 30 | J25: =+'star F (2)'!$H25+'star F (2)'!$I25 -> 30 | K25: ='star F (2)'!$H25+'star F (2)'!$I25-TODAY() -> -45566 | L25: =IF(K25<1,"VENCIDO","VIGENTE") -> VENCIDO
F26: 4068 | G26: 3.5 | I26: 30 | J26: =+'star F (2)'!$H26+'star F (2)'!$I26 -> 30 | K26: ='star F (2)'!$H26+'star F (2)'!$I26-TODAY() -> -45566 | L26: =IF(K26<1,"VENCIDO","VIGENTE") -> VENCIDO
C27: emanuel7 | F27: 4728 | G27: 3.5 | H27: 45251 | I27: 30 | J27: =+'star F (2)'!$H27+'star F (2)'!$I27 -> 45281 | K27: ='star F (2)'!$H27+'star F (2)'!$I27-TODAY() -> -315 | L27: =IF(K27<1,"VENCIDO","VIGENTE") -> VENCIDO
C28: jesus | F28: 4545 | G28: 3.5 | H28: 45241 | I28: 30 | J28: =+'star F (2)'!$H28+'star F (2)'!$I28 -> 45271 | K28: ='star F (2)'!$H28+'star F (2)'!$I28-TODAY() -> -325 | L28: =IF(K28<1,"VENCIDO","VIGENTE") -> VENCIDO
F29: 7474 | G29: 3.5 | I29: 30 | J29: =+'star F (2)'!$H29+'star F (2)'!$I29 -> 30 | K29: ='star F (2)'!$H29+'star F (2)'!$I29-TODAY() -> -45566 | L29: =IF(K29<1,"VENCIDO","VIGENTE") -> VENCIDO
C30: miguel | F30: 4545 | G30: 3.5 | H30: 45234 | I30: 30 | J30: =+'star F (2)'!$H30+'star F (2)'!$I30 -> 45264 | K30: ='star F (2)'!$H30+'star F (2)'!$I30-TODAY() -> -332 | L30: =IF(K30<1,"VENCIDO","VIGENTE") -> VENCIDO
G31: =IF(H31>0,7,0) -> 0 | I31: 30 | J31: =+'star F (2)'!$H31+'star F (2)'!$I31 -> 30 | K31: ='star F (2)'!$H31+'star F (2)'!$I31-TODAY() -> -45566 | L31: =IF(K31<1,"VENCIDO","VIGENTE") -> VENCIDO
C32: PERFILES : | F32: =SUM(F25:F31) -> 29628 | G32: =SUM(G25:G31) -> 21 | I32: 30 | J32: =+'star F (2)'!$H32+'star F (2)'!$I32 -> 30 | K32: ='star F (2)'!$H32+'star F (2)'!$I32-TODAY() -> -45566
B39: ALERTA DIAS
B40: =TODAY() -> 45596
B41: CUENTA | C41: NOMBRE | D41: CLAVE | E41: TELEFONO | F41: PIN PERFIL | G41: PRECIO | H41: FECHA DE INICIO | I41: DIAS | J41: FECHA DE VENCIMIENTO | K41: ALARMA | L41: ESTADO
B42: CORREO : lunigu332dek@gmail.com CONTRASEÑA: verde75144 | C42: Joan | F42: 6548 | G42: 3.5 | H42: 45239 | I42: 30 | J42: =+'star F (2)'!$H42+'star F (2)'!$I42 -> 45269 | K42: ='star F (2)'!$H42+'star F (2)'!$I42-TODAY() -> -327 | L42: =IF(K42<1,"VENCIDO","VIGENTE") -> VENCIDO
C43: ana | F43: 3696 | G43: 3.5 | H43: 45248 | I43: 30 | J43: =+'star F (2)'!$H43+'star F (2)'!$I43 -> 45278 | K43: ='star F (2)'!$H43+'star F (2)'!$I43-TODAY() -> -318 | L43: =IF(K43<1,"VENCIDO","VIGENTE") -> VENCIDO
C44: mari | F44: 3712 | G44: 3.5 | H44: 45235 | I44: 30 | J44: =+'star F (2)'!$H44+'star F (2)'!$I44 -> 45265 | K44: ='star F (2)'!$H44+'star F (2)'!$I44-TODAY() -> -331 | L44: =IF(K44<1,"VENCIDO","VIGENTE") -> VENCIDO
G45: 3.5 | I45: 30 | J45: =+'star F (2)'!$H45+'star F (2)'!$I45 -> 30 | K45: ='star F (2)'!$H45+'star F (2)'!$I45-TODAY() -> -45566 | L45: =IF(K45<1,"VENCIDO","VIGENTE") -> VENCIDO
C46: moises | F46: 6323 | G46: 3.5 | H46: 45233 | I46: 30 | J46: =+'star F (2)'!$H46+'star F (2)'!$I46 -> 45263 | K46: ='star F (2)'!$H46+'star F (2)'!$I46-TODAY() -> -333 | L46: =IF(K46<1,"VENCIDO","VIGENTE") -> VENCIDO
G47: 3.5 | I47: 30 | J47: =+'star F (2)'!$H47+'star F (2)'!$I47 -> 30 | K47: ='star F (2)'!$H47+'star F (2)'!$I47-TODAY() -> -45566 | L47: =IF(K47<1,"VENCIDO","VIGENTE") -> VENCIDO
G48: 3.5 | I48: 30 | J48: =+'star F (2)'!$H48+'star F (2)'!$I48 -> 30 | K48: ='star F (2)'!$H48+'star F (2)'!$I48-TODAY() -> -45566 | L48: =IF(K48<1,"VENCIDO","VIGENTE") -> VENCIDO
C49: PERFILES : | F49: =SUM(F42:F48) -> 20279 | G49: =SUM(G42:G48) -> 24.5 | I49: 30 | J49: =+'star F (2)'!$H49+'star F (2)'!$I49 -> 30 | K49: ='star F (2)'!$H49+'star F (2)'!$I49-TODAY() -> -45566
B57: ALERTA DIAS
B58: =TODAY() -> 45596
B59: CUENTA | C59: NOMBRE | D59: CLAVE | E59: TELEFONO | F59: PIN PERFIL | G59: PRECIO | H59: FECHA DE INICIO | I59: DIAS | J59: FECHA DE VENCIMIENTO | K59: ALARMA | L59: ESTADO
B60: Correo : deku75490stream@gmail.com Contraseña : dek457n64ge | C60: iris9 | G60: =IF(H60>0,7,0) -> 7 | H60: 45242 | I60: 30 | J60: =+'star F (2)'!$H60+'star F (2)'!$I60 -> 45272 | K60: ='star F (2)'!$H60+'star F (2)'!$I60-TODAY() -> -324 | L60: =IF(K60<1,"VENCIDO","VIGENTE") -> VENCIDO
C61: david7 | F61: 6017 | G61: =IF(H61>0,7,0) -> 7 | H61: 45245 | I61: 30 | J61: =+'star F (2)'!$H61+'star F (2)'!$I61 -> 45275 | K61: ='star F (2)'!$H61+'star F (2)'!$I61-TODAY() -> -321 | L61: =IF(K61<1,"VENCIDO","VIGENTE") -> VENCIDO
C62: gabo16 | G62: =IF(H62>0,7,0) -> 7 | H62: 45260 | I62: 30 | J62: =+'star F (2)'!$H62+'star F (2)'!$I62 -> 45290 | K62: ='star F (2)'!$H62+'star F (2)'!$I62-TODAY() -> -306 | L62: =IF(K62<1,"VENCIDO","VIGENTE") -> VENCIDO
C63: gabo18 | G63: =IF(H63>0,7,0) -> 7 | H63: 45260 | I63: 30 | J63: =+'star F (2)'!$H63+'star F (2)'!$I63 -> 45290 | K63: ='star F (2)'!$H63+'star F (2)'!$I63-TODAY() -> -306 | L63: =IF(K63<1,"VENCIDO","VIGENTE") -> VENCIDO
C64: jack | G64: =IF(H64>0,7,0) -> 7 | H64: 45242 | I64: 30 | J64: =+'star F (2)'!$H64+'star F (2)'!$I64 -> 45272 | K64: ='star F (2)'!$H64+'star F (2)'!$I64-TODAY() -> -324 | L64: =IF(K64<1,"VENCIDO","VIGENTE") -> VENCIDO
G65: =IF(H65>0,7,0) -> 0 | I65: 30 | J65: =+'star F (2)'!$H65+'star F (2)'!$I65 -> 30 | K65: ='star F (2)'!$H65+'star F (2)'!$I65-TODAY() -> -45566 | L65: =IF(K65<1,"VENCIDO","VIGENTE") -> VENCIDO
G66: =IF(H66>0,7,0) -> 0 | I66: 30 | J66: =+'star F (2)'!$H66+'star F (2)'!$I66 -> 30 | K66: ='star F (2)'!$H66+'star F (2)'!$I66-TODAY() -> -45566 | L66: =IF(K66<1,"VENCIDO","VIGENTE") -> VENCIDO
C67: PERFILES : | F67: =SUM(F60:F66) -> 6017 | G67: =SUM(G60:G66) -> 35 | I67: 30 | J67: =+'star F (2)'!$H67+'star F (2)'!$I67 -> 30 | K67: ='star F (2)'!$H67+'star F (2)'!$I67-TODAY() -> -45566

Sheet CORREOSnetflix
A1: ALERTA DIAS
A2: =TODAY() -> 45596
A3: CUENTA | B3: NOMBRE | C3: CLAVE | D3: TELEFONO | E3: PIN PERFIL | F3: PRECIO US | G3: PRECIO | H3: FECHA DE INICIO | I3: DIAS | J3: FECHA DE VENCIMIENTO | K3: ALARMA | L3: ESTADO
A4: Correo : real945@lowxvr.com Contraseña : frio923 | B4: Angel63 | D4: +51 946 579 911 | E4: 2548 | G4: 10 | H4: 45578 | I4: 30 | J4: =+Table_714[[#This Row],[FECHA DE INICIO]]+Table_714[[#This Row],[DIAS]] -> 45608 | K4: =+Table_714[[#This Row],[FECHA DE INICIO]]+Table_714[[#This Row],[DIAS]]-TODAY() -> 12 | L4: =IF(K4<1,"VENCIDO","VIGENTE") -> VIGENTE
B5: xiomara433 | D5: 51 946 579 911 | E5: 8225 | G5: 10 | H5: 45565 | I5: 30 | J5: =+Table_714[[#This Row],[FECHA DE INICIO]]+Table_714[[#This Row],[DIAS]] -> 45595 | K5: =+Table_714[[#This Row],[FECHA DE INICIO]]+Table_714[[#This Row],[DIAS]]-TODAY() -> -1 | L5: =IF(K5<1,"VENCIDO","VIGENTE") -> VENCIDO
B6: Dannis peña3 | D6: 51 994 876 608 | E6: 9458 | G6: 10 | H6: 45580 | I6: 30 | J6: =+Table_714[[#This Row],[FECHA DE INICIO]]+Table_714[[#This Row],[DIAS]] -> 45610 | K6: =+Table_714[[#This Row],[FECHA DE INICIO]]+Table_714[[#This Row],[DIAS]]-TODAY() -> 14 | L6: =IF(K6<1,"VENCIDO","VIGENTE") -> VIGENTE
B7: Stward17 | D7: 593 96 365 3101 | E7: 3323 | F7: $2.5 | H7: 45582 | I7: 30 | J7: =+Table_714[[#This Row],[FECHA DE INICIO]]+Table_714[[#This Row],[DIAS]] -> 45612 | K7: =+Table_714[[#This Row],[FECHA DE INICIO]]+Table_714[[#This Row],[DIAS]]-TODAY() -> 16 | L7: =IF(K7<1,"VENCIDO","VIGENTE") -> VIGENTE
B8: Tania Silva924 | D8: 51921561639 | E8: 2736 | G8: 10 | H8: 45585 | I8: 30 | J8: =+Table_714[[#This Row],[FECHA DE INICIO]]+Table_714[[#This Row],[DIAS]] -> 45615 | K8: =+Table_714[[#This Row],[FECHA DE INICIO]]+Table_714[[#This Row],[DIAS]]-TODAY() -> 19 | L8: =IF(K8<1,"VENCIDO","VIGENTE") -> VIGENTE
B9: PERFILES : | E9: =SUM(E4:E8) -> 26290 | G9: =SUM(G4:G8) -> 40 | I9: 30 | J9: =+'star F (2)'!$H11+'star F (2)'!$I11 -> 45384 | K9: ='star F (2)'!$H11+'star F (2)'!$I11-TODAY() -> -212
A12: ALERTA DIAS
A13: =TODAY() -> 45596
A14: CUENTA | B14: NOMBRE | C14: CLAVE | D14: TELEFONO | E14: PIN PERFIL | F14: PRECIO US | G14: PRECIO | H14: FECHA DE INICIO | I14: DIAS | J14: FECHA DE VENCIMIENTO | K14: ALARMA | L14: ESTADO
A15: correo: cien678@lowxvr.com Contraseña: fast654 | B15: Jhessi144 | D15: +51 946 579 911 | E15: 1444 | G15: 10 | H15: 45565 | I15: 30 | J15: =+Table_7145[[#This Row],[FECHA DE INICIO]]+Table_7145[[#This Row],[DIAS]] -> 45595 | K15: =+Table_7145[[#This Row],[FECHA DE INICIO]]+Table_7145[[#This Row],[DIAS]]-TODAY() -> -1 | L15: =IF(K15<1,"VENCIDO","VIGENTE") -> VENCIDO
B16: Nancita93 | E16: 9373 | I16: 30 | J16: =+Table_7145[[#This Row],[FECHA DE INICIO]]+Table_7145[[#This Row],[DIAS]] -> 30 | K16: =+Table_7145[[#This Row],[FECHA DE INICIO]]+Table_7145[[#This Row],[DIAS]]-TODAY() -> -45566 | L16: =IF(K16<1,"VENCIDO","VIGENTE") -> VENCIDO
B17: Jadiel992 | D17: +51 965 090 265 | E17: 1152 | G17: 9 | H17: 45575 | I17: 30 | J17: =+Table_7145[[#This Row],[FECHA DE INICIO]]+Table_7145[[#This Row],[DIAS]] -> 45605 | K17: =+Table_7145[[#This Row],[FECHA DE INICIO]]+Table_7145[[#This Row],[DIAS]]-TODAY() -> 9 | L17: =IF(K17<1,"VENCIDO","VIGENTE") -> VIGENTE
B18: Moises429 | D18: +51 986 430 133 | E18: 6323 | G18: 10 | H18: 45570 | I18: 30 | J18: =+Table_7145[[#This Row],[FECHA DE INICIO]]+Table_7145[[#This Row],[DIAS]] -> 45600 | K18: =+Table_7145[[#This Row],[FECHA DE INICIO]]+Table_7145[[#This Row],[DIAS]]-TODAY() -> 4 | L18: =IF(K18<1,"VENCIDO","VIGENTE") -> VIGENTE
B19: Cathe6 | D19: 51 917 020 261 | E19: 3468 | G19: 10 | H19: 45572 | I19: 30 | J19: =+Table_7145[[#This Row],[FECHA DE INICIO]]+Table_7145[[#This Row],[DIAS]] -> 45602 | K19: =+Table_7145[[#This Row],[FECHA DE INICIO]]+Table_7145[[#This Row],[DIAS]]-TODAY() -> 6 | L19: =IF(K19<1,"VENCIDO","VIGENTE") -> VIGENTE
B20: PERFILES : | E20: =SUM(E15:E19) -> 21760 | G20: =SUM(G15:G19) -> 39 | I20: 30 | J20: =+'star F (2)'!$H23+'star F (2)'!$I23 -> 0 | K20: ='star F (2)'!$H23+'star F (2)'!$I23-TODAY() -> -45596
A29: ALERTA DIAS
A30: =TODAY() -> 45596
A31: CUENTA | B31: NOMBRE | C31: CLAVE | D31: TELEFONO | E31: PIN PERFIL | F31: PRECIO US | G31: PRECIO | H31: FECHA DE INICIO | I31: DIAS | J31: FECHA DE VENCIMIENTO | K31: ALARMA | L31: ESTADO
A32: correo:prem139@lowcute.com contraseña:de16ku46ver | B32: Rose926 | D32: 51 963 728 882 | E32: 1292 | G32: 10 | H32: 45550 | I32: 30 | J32: =+Table_71457[[#This Row],[FECHA DE INICIO]]+Table_71457[[#This Row],[DIAS]] -> 45580 | K32: =+Table_71457[[#This Row],[FECHA DE INICIO]]+Table_71457[[#This Row],[DIAS]]-TODAY() -> -16 | L32: =IF(K32<1,"VENCIDO","VIGENTE") -> VENCIDO
B33: Abraham Obregón | D33: 51 942 257 254 | E33: 3467 | G33: 10 | H33: 45583 | I33: 30 | J33: =+Table_71457[[#This Row],[FECHA DE INICIO]]+Table_71457[[#This Row],[DIAS]] -> 45613 | K33: =+Table_71457[[#This Row],[FECHA DE INICIO]]+Table_71457[[#This Row],[DIAS]]-TODAY() -> 17 | L33: =IF(K33<1,"VENCIDO","VIGENTE") -> VIGENTE
B34: Sr:jp | D34: 593 98 484 3636 | E34: 1583 | F34: $2.5 | H34: 45596 | I34: 30 | J34: =+Table_71457[[#This Row],[FECHA DE INICIO]]+Table_71457[[#This Row],[DIAS]] -> 45626 | K34: =+Table_71457[[#This Row],[FECHA DE INICIO]]+Table_71457[[#This Row],[DIAS]]-TODAY() -> 30 | L34: =IF(K34<1,"VENCIDO","VIGENTE") -> VIGENTE
B35: Vasty2193 | D35: 593 93 972 8672 | E35: 3823 | F35: 2.5 | H35: 45572 | I35: 30 | J35: =+Table_71457[[#This Row],[FECHA DE INICIO]]+Table_71457[[#This Row],[DIAS]] -> 45602 | K35: =+Table_71457[[#This Row],[FECHA DE INICIO]]+Table_71457[[#This Row],[DIAS]]-TODAY() -> 6 | L35: =IF(K35<1,"VENCIDO","VIGENTE") -> VIGENTE
B36: Nicol399 | D36: 51 946 579 911 | E36: 1566 | G36: 10 | H36: 45578 | I36: 30 | J36: =+Table_71457[[#This Row],[FECHA DE INICIO]]+Table_71457[[#This Row],[DIAS]] -> 45608 | K36: =+Table_71457[[#This Row],[FECHA DE INICIO]]+Table_71457[[#This Row],[DIAS]]-TODAY() -> 12 | L36: =IF(K36<1,"VENCIDO","VIGENTE") -> VIGENTE
B37: PERFILES : | E37: =SUM(E32:E36) -> 11731 | G37: =SUM(G32:G36) -> 30 | I37: 30 | J37: =+'star F (2)'!$H40+'star F (2)'!$I40 -> 0 | K37: ='star F (2)'!$H40+'star F (2)'!$I40-TODAY() -> -45596
D43: jerik nose fecha de pago
A44: ALERTA DIAS
A45: =TODAY() -> 45596
A46: CUENTA | B46: NOMBRE | C46: CLAVE | D46: TELEFONO | E46: PIN PERFIL | F46: PRECIO US | G46: PRECIO | H46: FECHA DE INICIO | I46: DIAS | J46: FECHA DE VENCIMIENTO | K46: ALARMA | L46: ESTADO
A47: Correo : atjuggod@stayhome.li Contraseña: deke73ku82 | B47: Marcelo103 | E47: 1138 | F47: $5 | H47: 45542 | I47: 60 | J47: =+Table_714578[[#This Row],[FECHA DE INICIO]]+Table_714578[[#This Row],[DIAS]] -> 45602 | K47: =+Table_714578[[#This Row],[FECHA DE INICIO]]+Table_714578[[#This Row],[DIAS]]-TODAY() -> 6 | L47: =IF(K47<1,"VENCIDO","VIGENTE") -> VIGENTE
B48: Lyaa19 | D48: +51 917 117 242 | E48: 1827 | G48: 8 | H48: 45538 | I48: 30 | J48: =+Table_714578[[#This Row],[FECHA DE INICIO]]+Table_714578[[#This Row],[DIAS]] -> 45568 | K48: =+Table_714578[[#This Row],[FECHA DE INICIO]]+Table_714578[[#This Row],[DIAS]]-TODAY() -> -28 | L48: =IF(K48<1,"VENCIDO","VIGENTE") -> VENCIDO
B49: Yulissa184 | D49: +593 95 900 1567 | E49: 2946 | I49: 30 | J49: =+Table_714578[[#This Row],[FECHA DE INICIO]]+Table_714578[[#This Row],[DIAS]] -> 30 | K49: =+Table_714578[[#This Row],[FECHA DE INICIO]]+Table_714578[[#This Row],[DIAS]]-TODAY() -> -45566 | L49: =IF(K49<1,"VENCIDO","VIGENTE") -> VENCIDO
B50: Miguel193 | D50: +51 917 117 242 | E50: 1936 | G50: 8 | H50: 45564 | I50: 30 | J50: =+Table_714578[[#This Row],[FECHA DE INICIO]]+Table_714578[[#This Row],[DIAS]] -> 45594 | K50: =+Table_714578[[#This Row],[FECHA DE INICIO]]+Table_714578[[#This Row],[DIAS]]-TODAY() -> -2 | L50: =IF(K50<1,"VENCIDO","VIGENTE") -> VENCIDO
B51: Ingrid829 | D51: 51 986 430 133 | E51: 1946 | G51: 9 | H51: 45570 | I51: 30 | J51: =+Table_714578[[#This Row],[FECHA DE INICIO]]+Table_714578[[#This Row],[DIAS]] -> 45600 | K51: =+Table_714578[[#This Row],[FECHA DE INICIO]]+Table_714578[[#This Row],[DIAS]]-TODAY() -> 4 | L51: =IF(K51<1,"VENCIDO","VIGENTE") -> VIGENTE
B52: PERFILES : | E52: =SUM(E47:E51) -> 9793 | G52: =SUM(G47:G51) -> 25 | I52: 30 | J52: =+'star F (2)'!$H55+'star F (2)'!$I55 -> 0 | K52: ='star F (2)'!$H55+'star F (2)'!$I55-TODAY() -> -45596
A57: ALERTA DIAS
A58: =TODAY() -> 45596
A59: CUENTA | B59: NOMBRE | C59: CLAVE | D59: TELEFONO | E59: PIN PERFIL | F59: PRECIO US | G59: PRECIO | H59: FECHA DE INICIO | I59: DIAS | J59: FECHA DE VENCIMIENTO | K59: ALARMA | L59: ESTADO
A60: Correo: jum167@lowcute.com Contraseña: ber35deku | B60: Cesia72 | D60: 51 935 106 616 | E60: 2833 | G60: 10 | H60: 45546 | I60: 30 | J60: =+Table_7145789[[#This Row],[FECHA DE INICIO]]+Table_7145789[[#This Row],[DIAS]] -> 45576 | K60: =+Table_7145789[[#This Row],[FECHA DE INICIO]]+Table_7145789[[#This Row],[DIAS]]-TODAY() -> -20 | L60: =IF(K60<1,"VENCIDO","VIGENTE") -> VENCIDO
B61: Daniela82 | D61: 51 946 579 911 | E61: 8337 | G61: 10 | H61: 45565 | I61: 30 | J61: =+Table_7145789[[#This Row],[FECHA DE INICIO]]+Table_7145789[[#This Row],[DIAS]] -> 45595 | K61: =+Table_7145789[[#This Row],[FECHA DE INICIO]]+Table_7145789[[#This Row],[DIAS]]-TODAY() -> -1 | L61: =IF(K61<1,"VENCIDO","VIGENTE") -> VENCIDO
B62: Joel2655 | D62: 51 977 840 037 | E62: 6346 | G62: 10 | H62: 45557 | I62: 30 | J62: =+Table_7145789[[#This Row],[FECHA DE INICIO]]+Table_7145789[[#This Row],[DIAS]] -> 45587 | K62: =+Table_7145789[[#This Row],[FECHA DE INICIO]]+Table_7145789[[#This Row],[DIAS]]-TODAY() -> -9 | L62: =IF(K62<1,"VENCIDO","VIGENTE") -> VENCIDO
B63: Jose617 | D63: 51 980 621 358 | E63: 1137 | G63: 10 | H63: 45567 | I63: 30 | J63: =+Table_7145789[[#This Row],[FECHA DE INICIO]]+Table_7145789[[#This Row],[DIAS]] -> 45597 | K63: =+Table_7145789[[#This Row],[FECHA DE INICIO]]+Table_7145789[[#This Row],[DIAS]]-TODAY() -> 1 | L63: =IF(K63<1,"VENCIDO","VIGENTE") -> VIGENTE
I64: 30 | J64: =+Table_7145789[[#This Row],[FECHA DE INICIO]]+Table_7145789[[#This Row],[DIAS]] -> 30 | K64: =+Table_7145789[[#This Row],[FECHA DE INICIO]]+Table_7145789[[#This Row],[DIAS]]-TODAY() -> -45566 | L64: =IF(K64<1,"VENCIDO","VIGENTE") -> VENCIDO
B65: PERFILES : | E65: =SUM(E60:E64) -> 18653 | G65: =SUM(G60:G64) -> 40 | I65: 30 | J65: =+'star F (2)'!$H68+'star F (2)'!$I68 -> 0 | K65: ='star F (2)'!$H68+'star F (2)'!$I68-TODAY() -> -45596
A69: ALERTA DIAS
A70: =TODAY() -> 45596
A71: CUENTA | B71: NOMBRE | C71: CLAVE | D71: TELEFONO | E71: PIN PERFIL | F71: PRECIO US | G71: PRECIO | H71: FECHA DE INICIO | I71: DIAS | J71: FECHA DE VENCIMIENTO | K71: ALARMA | L71: ESTADO
A72: Correo : jhodelyn26602v@hotmail.com Contraseña : deku5243de | I72: 30 | J72: =+Table_714578920[[#This Row],[FECHA DE INICIO]]+Table_714578920[[#This Row],[DIAS]] -> 30 | K72: =+Table_714578920[[#This Row],[FECHA DE INICIO]]+Table_714578920[[#This Row],[DIAS]]-TODAY() -> -45566 | L72: =IF(K72<1,"VENCIDO","VIGENTE") -> VENCIDO
I73: 30 | J73: =+Table_714578920[[#This Row],[FECHA DE INICIO]]+Table_714578920[[#This Row],[DIAS]] -> 30 | K73: =+Table_714578920[[#This Row],[FECHA DE INICIO]]+Table_714578920[[#This Row],[DIAS]]-TODAY() -> -45566 | L73: =IF(K73<1,"VENCIDO","VIGENTE") -> VENCIDO
I74: 30 | J74: =+Table_714578920[[#This Row],[FECHA DE INICIO]]+Table_714578920[[#This Row],[DIAS]] -> 30 | K74: =+Table_714578920[[#This Row],[FECHA DE INICIO]]+Table_714578920[[#This Row],[DIAS]]-TODAY() -> -45566 | L74: =IF(K74<1,"VENCIDO","VIGENTE") -> VENCIDO
I75: 30 | J75: =+Table_714578920[[#This Row],[FECHA DE INICIO]]+Table_714578920[[#This Row],[DIAS]] -> 30 | K75: =+Table_714578920[[#This Row],[FECHA DE INICIO]]+Table_714578920[[#This Row],[DIAS]]-TODAY() -> -45566 | L75: =IF(K75<1,"VENCIDO","VIGENTE") -> VENCIDO
I76: 30 | J76: =+Table_714578920[[#This Row],[FECHA DE INICIO]]+Table_714578920[[#This Row],[DIAS]] -> 30 | K76: =+Table_714578920[[#This Row],[FECHA DE INICIO]]+Table_714578920[[#This Row],[DIAS]]-TODAY() -> -45566 | L76: =IF(K76<1,"VENCIDO","VIGENTE") -> VENCIDO
B77: PERFILES : | E77: =SUM(E72:E76) -> 0 | G77: =SUM(G72:G76) -> 0 | I77: 30 | J77: =+'star F (2)'!$H80+'star F (2)'!$I80 -> 0 | K77: ='star F (2)'!$H80+'star F (2)'!$I80-TODAY() -> -45596
A82: ALERTA DIASA82:L92
A83: =TODAY() -> 45596
A84: CUENTA | B84: NOMBRE | C84: CLAVE | D84: TELEFONO | E84: PIN PERFIL | F84: PRECIO US | G84: PRECIO | H84: FECHA DE INICIO | I84: DIAS | J84: FECHA DE VENCIMIENTO | K84: ALARMA | L84: ESTADO
A85: Correo : jhodelyn71movies26service10@hotmail.com Contraseña : Deku1846deg | B85: Geraldine22 | D85: 51 946 579 911 | E85: 1195 | G85: 10 | H85: 45572 | I85: 30 | J85: =+Table_71457891015[[#This Row],[FECHA DE INICIO]]+Table_71457891015[[#This Row],[DIAS]] -> 45602 | K85: =+Table_71457891015[[#This Row],[FECHA DE INICIO]]+Table_71457891015[[#This Row],[DIAS]]-TODAY() -> 6 | L85: =IF(K85<1,"VENCIDO","VIGENTE") -> VIGENTE
I86: 30 | J86: =+Table_71457891015[[#This Row],[FECHA DE INICIO]]+Table_71457891015[[#This Row],[DIAS]] -> 30 | K86: =+Table_71457891015[[#This Row],[FECHA DE INICIO]]+Table_71457891015[[#This Row],[DIAS]]-TODAY() -> -45566 | L86: =IF(K86<1,"VENCIDO","VIGENTE") -> VENCIDO
I87: 30 | J87: =+Table_71457891015[[#This Row],[FECHA DE INICIO]]+Table_71457891015[[#This Row],[DIAS]] -> 30 | K87: =+Table_71457891015[[#This Row],[FECHA DE INICIO]]+Table_71457891015[[#This Row],[DIAS]]-TODAY() -> -45566 | L87: =IF(K87<1,"VENCIDO","VIGENTE") -> VENCIDO
I88: 30 | J88: =+Table_71457891015[[#This Row],[FECHA DE INICIO]]+Table_71457891015[[#This Row],[DIAS]] -> 30 | K88: =+Table_71457891015[[#This Row],[FECHA DE INICIO]]+Table_71457891015[[#This Row],[DIAS]]-TODAY() -> -45566 | L88: =IF(K88<1,"VENCIDO","VIGENTE") -> VENCIDO
I89: 30 | J89: =+Table_71457891015[[#This Row],[FECHA DE INICIO]]+Table_71457891015[[#This Row],[DIAS]] -> 30 | K89: =+Table_71457891015[[#This Row],[FECHA DE INICIO]]+Table_71457891015[[#This Row],[DIAS]]-TODAY() -> -45566 | L89: =IF(K89<1,"VENCIDO","VIGENTE") -> VENCIDO
B90: PERFILES : | E90: =SUM(E85:E89) -> 1195 | G90: =SUM(G85:G89) -> 10 | I90: 30 | J90: =+'star F (2)'!$H104+'star F (2)'!$I104 -> 0 | K90: ='star F (2)'!$H104+'star F (2)'!$I104-TODAY() -> -45596
A96: ALERTA DIASA82:L92
A97: =TODAY() -> 45596
A98: CUENTA | B98: NOMBRE | C98: CLAVE | D98: TELEFONO | E98: PIN PERFIL | F98: PRECIO US | G98: PRECIO | H98: FECHA DE INICIO | I98: DIAS | J98: FECHA DE VENCIMIENTO | K98: ALARMA | L98: ESTADO
A99: Correo : hogfatpad@eay.jp Contraseña : dku613cer | B99: Jachelit18 | D99: 51 988 684 621 | E99: 6728 | H99: 45573 | I99: 30 | J99: =+Table_71457891011[[#This Row],[FECHA DE INICIO]]+Table_71457891011[[#This Row],[DIAS]] -> 45603 | K99: =+Table_71457891011[[#This Row],[FECHA DE INICIO]]+Table_71457891011[[#This Row],[DIAS]]-TODAY() -> 7 | L99: =IF(K99<1,"VENCIDO","VIGENTE") -> VIGENTE
B100: Andrea25 | D100: 593 96 365 3101 | E100: 3569 | F100: $2.5 | H100: 45572 | I100: 30 | J100: =+Table_71457891011[[#This Row],[FECHA DE INICIO]]+Table_71457891011[[#This Row],[DIAS]] -> 45602 | K100: =+Table_71457891011[[#This Row],[FECHA DE INICIO]]+Table_71457891011[[#This Row],[DIAS]]-TODAY() -> 6 | L100: =IF(K100<1,"VENCIDO","VIGENTE") -> VIGENTE
B101: Miguel calderon14 | D101: 51 902 266 754 | E101: 1146 | G101: 10 | H101: 45595 | I101: 30 | J101: =+Table_71457891011[[#This Row],[FECHA DE INICIO]]+Table_71457891011[[#This Row],[DIAS]] -> 45625 | K101: =+Table_71457891011[[#This Row],[FECHA DE INICIO]]+Table_71457891011[[#This Row],[DIAS]]-TODAY() -> 29 | L101: =IF(K101<1,"VENCIDO","VIGENTE") -> VIGENTE
B102: Edwin09 | D102: 593 96 365 3101 | E102: 2848 | F102: $2.5 | H102: 45582 | I102: 30 | J102: =+Table_71457891011[[#This Row],[FECHA DE INICIO]]+Table_71457891011[[#This Row],[DIAS]] -> 45612 | K102: =+Table_71457891011[[#This Row],[FECHA DE INICIO]]+Table_71457891011[[#This Row],[DIAS]]-TODAY() -> 16 | L102: =IF(K102<1,"VENCIDO","VIGENTE") -> VIGENTE
B103: Fabio V | D103: 51 977 364 111 | E103: 5235 | G103: 10 | H103: 45582 | I103: 30 | J103: =+Table_71457891011[[#This Row],[FECHA DE INICIO]]+Table_71457891011[[#This Row],[DIAS]] -> 45612 | K103: =+Table_71457891011[[#This Row],[FECHA DE INICIO]]+Table_71457891011[[#This Row],[DIAS]]-TODAY() -> 16 | L103: =IF(K103<1,"VENCIDO","VIGENTE") -> VIGENTE
B104: PERFILES : | E104: =SUM(E99:E103) -> 19526 | G104: =SUM(G99:G103) -> 20 | I104: 30 | J104: =+'star F (2)'!$H119+'star F (2)'!$I119 -> 0 | K104: ='star F (2)'!$H119+'star F (2)'!$I119-TODAY() -> -45596
A109: ALERTA DIASA82:L92
A110: =TODAY() -> 45596
A111: CUENTA | B111: NOMBRE | C111: CLAVE | D111: TELEFONO | E111: PIN PERFIL | F111: PRECIO US | G111: PRECIO | H111: FECHA DE INICIO | I111: DIAS | J111: FECHA DE VENCIMIENTO | K111: ALARMA | L111: ESTADO
A112: Correo : jhodelyn26478@hotmail.com Contraseña : de6bku73 | B112: luis349 | D112: 51 946 579 911 | E112: 1672 | G112: 10 | H112: 45570 | I112: 30 | J112: =+Table_7145789101112[[#This Row],[FECHA DE INICIO]]+Table_7145789101112[[#This Row],[DIAS]] -> 45600 | K112: =+Table_7145789101112[[#This Row],[FECHA DE INICIO]]+Table_7145789101112[[#This Row],[DIAS]]-TODAY() -> 4 | L112: =IF(K112<1,"VENCIDO","VIGENTE") -> VIGENTE
B113: Alex319 | D113: 51 918 950 157 | E113: 6455 | G113: 10 | H113: 45572 | I113: 30 | J113: =+Table_7145789101112[[#This Row],[FECHA DE INICIO]]+Table_7145789101112[[#This Row],[DIAS]] -> 45602 | K113: =+Table_7145789101112[[#This Row],[FECHA DE INICIO]]+Table_7145789101112[[#This Row],[DIAS]]-TODAY() -> 6 | L113: =IF(K113<1,"VENCIDO","VIGENTE") -> VIGENTE
B114: García Moreira36 | D114: 593 96 905 2056 | E114: 2979 | F114: $2.5 | H114: 45572 | I114: 30 | J114: =+Table_7145789101112[[#This Row],[FECHA DE INICIO]]+Table_7145789101112[[#This Row],[DIAS]] -> 45602 | K114: =+Table_7145789101112[[#This Row],[FECHA DE INICIO]]+Table_7145789101112[[#This Row],[DIAS]]-TODAY() -> 6 | L114: =IF(K114<1,"VENCIDO","VIGENTE") -> VIGENTE
B115: Babas3558 | D115: 51 951 821 138 | E115: 6699 | G115: 4.5 | H115: 45572 | I115: 30 | J115: =+Table_7145789101112[[#This Row],[FECHA DE INICIO]]+Table_7145789101112[[#This Row],[DIAS]] -> 45602 | K115: =+Table_7145789101112[[#This Row],[FECHA DE INICIO]]+Table_7145789101112[[#This Row],[DIAS]]-TODAY() -> 6 | L115: =IF(K115<1,"VENCIDO","VIGENTE") -> VIGENTE
B116: Aly9226 | D116: 51 935 853 158 | E116: 1623 | G116: 10 | H116: 45544 | I116: 30 | J116: =+Table_7145789101112[[#This Row],[FECHA DE INICIO]]+Table_7145789101112[[#This Row],[DIAS]] -> 45574 | K116: =+Table_7145789101112[[#This Row],[FECHA DE INICIO]]+Table_7145789101112[[#This Row],[DIAS]]-TODAY() -> -22 | L116: =IF(K116<1,"VENCIDO","VIGENTE") -> VENCIDO
B117: PERFILES : | E117: =SUM(E112:E116) -> 19428 | G117: =SUM(G112:G116) -> 34.5 | I117: 30 | J117: =+'star F (2)'!$H132+'star F (2)'!$I132 -> 0 | K117: ='star F (2)'!$H132+'star F (2)'!$I132-TODAY() -> -45596
A123: ALERTA DIASA82:L92
A124: =TODAY() -> 45596
A125: CUENTA | B125: NOMBRE | C125: CLAVE | D125: TELEFONO | E125: PIN PERFIL | F125: PRECIO US | G125: PRECIO | H125: FECHA DE INICIO | I125: DIAS | J125: FECHA DE VENCIMIENTO | K125: ALARMA | L125: ESTADO
A126: Correo: abc241@lowcute.com Contraseña: dek25gw445 | B126: Juan03 | D126: 593 96 365 3101 | E126: 8255 | F126: $2.5 | H126: 45582 | I126: 30 | J126: =+Table_714578910111213[[#This Row],[FECHA DE INICIO]]+Table_714578910111213[[#This Row],[DIAS]] -> 45612 | K126: =+Table_714578910111213[[#This Row],[FECHA DE INICIO]]+Table_714578910111213[[#This Row],[DIAS]]-TODAY() -> 16 | L126: =IF(K126<1,"VENCIDO","VIGENTE") -> VIGENTE
B127: Andrea caraguay194 | D127: 593 98 604 2431 | E127: 5277 | F127: $2.5 | H127: 45554 | I127: 30 | J127: =+Table_714578910111213[[#This Row],[FECHA DE INICIO]]+Table_714578910111213[[#This Row],[DIAS]] -> 45584 | K127: =+Table_714578910111213[[#This Row],[FECHA DE INICIO]]+Table_714578910111213[[#This Row],[DIAS]]-TODAY() -> -12 | L127: =IF(K127<1,"VENCIDO","VIGENTE") -> VENCIDO
B128: Leo344 | D128: 51 955 127 083 | E128: 3455 | G128: 10 | H128: 45568 | I128: 30 | J128: =+Table_714578910111213[[#This Row],[FECHA DE INICIO]]+Table_714578910111213[[#This Row],[DIAS]] -> 45598 | K128: =+Table_714578910111213[[#This Row],[FECHA DE INICIO]]+Table_714578910111213[[#This Row],[DIAS]]-TODAY() -> 2 | L128: =IF(K128<1,"VENCIDO","VIGENTE") -> VIGENTE
B129: Percydelia244 | D129: 51 935 183 987 | E129: 3329 | G129: 10 | H129: 45570 | I129: 30 | J129: =+Table_714578910111213[[#This Row],[FECHA DE INICIO]]+Table_714578910111213[[#This Row],[DIAS]] -> 45600 | K129: =+Table_714578910111213[[#This Row],[FECHA DE INICIO]]+Table_714578910111213[[#This Row],[DIAS]]-TODAY() -> 4 | L129: =IF(K129<1,"VENCIDO","VIGENTE") -> VIGENTE
B130: Rosita | D130: 51 927 518 145 | E130: 3635 | G130: 8 | H130: 45582 | I130: 30 | J130: =+Table_714578910111213[[#This Row],[FECHA DE INICIO]]+Table_714578910111213[[#This Row],[DIAS]] -> 45612 | K130: =+Table_714578910111213[[#This Row],[FECHA DE INICIO]]+Table_714578910111213[[#This Row],[DIAS]]-TODAY() -> 16 | L130: =IF(K130<1,"VENCIDO","VIGENTE") -> VIGENTE
B131: PERFILES : | E131: =SUM(E126:E130) -> 23951 | G131: =SUM(G126:G130) -> 28 | I131: 30 | J131: =+'star F (2)'!$H146+'star F (2)'!$I146 -> 0 | K131: ='star F (2)'!$H146+'star F (2)'!$I146-TODAY() -> -45596
A136: ALERTA DIASA82:L92
A137: =TODAY() -> 45596
A138: CUENTA | B138: NOMBRE | C138: CLAVE | D138: TELEFONO | E138: PIN PERFIL | F138: PRECIO US | G138: PRECIO | H138: FECHA DE INICIO | I138: DIAS | J138: FECHA DE VENCIMIENTO | K138: ALARMA | L138: ESTADO
A139: Correo : mono264@lowxvr.com Contraseña : mango7164 | B139: Fernando Cunalata52 | E139: 5333 | F139: $2.5 | H139: 45596 | I139: 30 | J139: =+Table_714578910111214[[#This Row],[FECHA DE INICIO]]+Table_714578910111214[[#This Row],[DIAS]] -> 45626 | K139: =+Table_714578910111214[[#This Row],[FECHA DE INICIO]]+Table_714578910111214[[#This Row],[DIAS]]-TODAY() -> 30 | L139: =IF(K139<1,"VENCIDO","VIGENTE") -> VIGENTE
B140: Nayelly94 | D140: 51 977 270 883 | E140: 9337 | G140: 8 | H140: 45583 | I140: 30 | J140: =+Table_714578910111214[[#This Row],[FECHA DE INICIO]]+Table_714578910111214[[#This Row],[DIAS]] -> 45613 | K140: =+Table_714578910111214[[#This Row],[FECHA DE INICIO]]+Table_714578910111214[[#This Row],[DIAS]]-TODAY() -> 17 | L140: =IF(K140<1,"VENCIDO","VIGENTE") -> VIGENTE
B141: Alex319 | D141: 51 918 950 157 | E141: 6455 | G141: 10 | H141: 45572 | I141: 30 | J141: =+Table_714578910111214[[#This Row],[FECHA DE INICIO]]+Table_714578910111214[[#This Row],[DIAS]] -> 45602 | K141: =+Table_714578910111214[[#This Row],[FECHA DE INICIO]]+Table_714578910111214[[#This Row],[DIAS]]-TODAY() -> 6 | L141: =IF(K141<1,"VENCIDO","VIGENTE") -> VIGENTE
B142: Ingrid829 | E142: 1946 | H142: 45570 | I142: 30 | J142: =+Table_714578910111214[[#This Row],[FECHA DE INICIO]]+Table_714578910111214[[#This Row],[DIAS]] -> 45600 | K142: =+Table_714578910111214[[#This Row],[FECHA DE INICIO]]+Table_714578910111214[[#This Row],[DIAS]]-TODAY() -> 4 | L142: =IF(K142<1,"VENCIDO","VIGENTE") -> VIGENTE
I143: 30 | J143: =+Table_714578910111214[[#This Row],[FECHA DE INICIO]]+Table_714578910111214[[#This Row],[DIAS]] -> 30 | K143: =+Table_714578910111214[[#This Row],[FECHA DE INICIO]]+Table_714578910111214[[#This Row],[DIAS]]-TODAY() -> -45566 | L143: =IF(K143<1,"VENCIDO","VIGENTE") -> VENCIDO
B144: PERFILES : | E144: =SUM(E139:E143) -> 23071 | G144: =SUM(G139:G143) -> 18 | I144: 30 | J144: =+'star F (2)'!$H159+'star F (2)'!$I159 -> 0 | K144: ='star F (2)'!$H159+'star F (2)'!$I159-TODAY() -> -45596
...

Sheet Dis F
B5: ALERTA DIAS
B6: =TODAY() -> 45596
B7: CUENTA | C7: NOMBRE | D7: CLAVE | E7: TELEFONO | F7: PIN PERFIL | G7: PRECIO | H7: FECHA DE INICIO | I7: DIAS | J7: FECHA DE VENCIMIENTO | K7: ALARMA | L7: ESTADO
B8: Correo: cl294309@gmail.com Contraseña: dek548k | C8: joan | F8: 6548 | G8: 3.5 | H8: 45237 | I8: 30 | J8: =+'Dis F'!$H8+'Dis F'!$I8 -> 45267 | K8: ='Dis F'!$H8+'Dis F'!$I8-TODAY() -> -329 | L8: =IF(K8<1,"VENCIDO","VIGENTE") -> VENCIDO
C9: moises | F9: 6323 | G9: 3.5 | H9: 45233 | I9: 30 | J9: =+'Dis F'!$H9+'Dis F'!$I9 -> 45263 | K9: ='Dis F'!$H9+'Dis F'!$I9-TODAY() -> -333 | L9: =IF(K9<1,"VENCIDO","VIGENTE") -> VENCIDO
C10: akemi | F10: 2796 | G10: 3.5 | H10: 45238 | I10: 30 | J10: =+'Dis F'!$H10+'Dis F'!$I10 -> 45268 | K10: ='Dis F'!$H10+'Dis F'!$I10-TODAY() -> -328 | L10: =IF(K10<1,"VENCIDO","VIGENTE") -> VENCIDO
C11: ana | F11: 3696 | G11: 3.5 | H11: 45248 | I11: 30 | J11: =+'Dis F'!$H11+'Dis F'!$I11 -> 45278 | K11: ='Dis F'!$H11+'Dis F'!$I11-TODAY() -> -318 | L11: =IF(K11<1,"VENCIDO","VIGENTE") -> VENCIDO
C12: araceli | F12: 4333 | G12: 3.5 | H12: 45250 | I12: 30 | J12: =+'Dis F'!$H12+'Dis F'!$I12 -> 45280 | K12: ='Dis F'!$H12+'Dis F'!$I12-TODAY() -> -316 | L12: =IF(K12<1,"VENCIDO","VIGENTE") -> VENCIDO
C13: jimy | F13: 7812 | G13: 3.5 | H13: 45262 | I13: 30 | J13: =+'Dis F'!$H13+'Dis F'!$I13 -> 45292 | K13: ='Dis F'!$H13+'Dis F'!$I13-TODAY() -> -304 | L13: =IF(K13<1,"VENCIDO","VIGENTE") -> VENCIDO
C14: zuly7 | F14: 9349 | G14: 3.5 | H14: 45265 | I14: 30 | J14: =+'Dis F'!$H14+'Dis F'!$I14 -> 45295 | K14: ='Dis F'!$H14+'Dis F'!$I14-TODAY() -> -301 | L14: =IF(K14<1,"VENCIDO","VIGENTE") -> VENCIDO
C15: PERFILES : | F15: =SUM(F8:F14) -> 40857 | G15: =SUM(G8:G14) -> 24.5 | I15: 30 | J15: =+'Dis F'!$H15+'Dis F'!$I15 -> 30 | K15: ='Dis F'!$H15+'Dis F'!$I15-TODAY() -> -45566
B22: ALERTA DIAS
B23: =TODAY() -> 45596
B24: CUENTA | C24: NOMBRE | D24: CLAVE | E24: TELEFONO | F24: PIN PERFIL | G24: PRECIO | H24: FECHA DE INICIO | I24: DIAS | J24: FECHA DE VENCIMIENTO | K24: ALARMA | L24: ESTADO
B25: CORREO: guert2303dek@gmail.com CONTRASEÑA: de334me213 | C25: xioamara | F25: *876 | G25: 3.5 | H25: 45260 | I25: 30 | J25: =+'Dis F'!$H25+'Dis F'!$I25 -> 45290 | K25: ='Dis F'!$H25+'Dis F'!$I25-TODAY() -> -306 | L25: =IF(K25<1,"VENCIDO","VIGENTE") -> VENCIDO
C26: carlos | F26: 2559 | G26: 3.5 | H26: 45227 | I26: 60 | J26: =+'Dis F'!$H26+'Dis F'!$I26 -> 45287 | K26: ='Dis F'!$H26+'Dis F'!$I26-TODAY() -> -309 | L26: =IF(K26<1,"VENCIDO","VIGENTE") -> VENCIDO
C27: jean piere | F27: 1111 | G27: 3.5 | H27: 45253 | I27: 30 | J27: =+'Dis F'!$H27+'Dis F'!$I27 -> 45283 | K27: ='Dis F'!$H27+'Dis F'!$I27-TODAY() -> -313 | L27: =IF(K27<1,"VENCIDO","VIGENTE") -> VENCIDO
C28: keren | F28: 9468 | G28: 3.5 | H28: 45251 | I28: 30 | J28: =+'Dis F'!$H28+'Dis F'!$I28 -> 45281 | K28: ='Dis F'!$H28+'Dis F'!$I28-TODAY() -> -315 | L28: =IF(K28<1,"VENCIDO","VIGENTE") -> VENCIDO
C29: rosmery | F29: *785 | G29: 3.5 | H29: 45262 | I29: 30 | J29: =+'Dis F'!$H29+'Dis F'!$I29 -> 45292 | K29: ='Dis F'!$H29+'Dis F'!$I29-TODAY() -> -304 | L29: =IF(K29<1,"VENCIDO","VIGENTE") -> VENCIDO
C30: oriana | G30: 3.5 | H30: 45253 | I30: 30 | J30: =+'Dis F'!$H30+'Dis F'!$I30 -> 45283 | K30: ='Dis F'!$H30+'Dis F'!$I30-TODAY() -> -313 | L30: =IF(K30<1,"VENCIDO","VIGENTE") -> VENCIDO
F31: *876 | G31: 3.5 | I31: 30 | J31: =+'Dis F'!$H31+'Dis F'!$I31 -> 30 | K31: ='Dis F'!$H31+'Dis F'!$I31-TODAY() -> -45566 | L31: =IF(K31<1,"VENCIDO","VIGENTE") -> VENCIDO
C32: PERFILES : | F32: =SUM(F25:F31) -> 13138 | G32: =SUM(G25:G31) -> 24.5 | I32: 30 | J32: =+'Dis F'!$H32+'Dis F'!$I32 -> 30 | K32: ='Dis F'!$H32+'Dis F'!$I32-TODAY() -> -45566
B39: ALERTA DIAS
B40: =TODAY() -> 45596
B41: CUENTA | C41: NOMBRE | D41: CLAVE | E41: TELEFONO | F41: PIN PERFIL | G41: PRECIO | H41: FECHA DE INICIO | I41: DIAS | J41: FECHA DE VENCIMIENTO | K41: ALARMA | L41: ESTADO
B42: CORREO : lunigu332dek@gmail.com CONTRASEÑA: dek65mer573 | C42: diego9 | F42: 3456 | G42: 3.5 | H42: 45252 | I42: 30 | J42: =+'Dis F'!$H42+'Dis F'!$I42 -> 45282 | K42: ='Dis F'!$H42+'Dis F'!$I42-TODAY() -> -314 | L42: =IF(K42<1,"VENCIDO","VIGENTE") -> VENCIDO
C43: briseida | F43: 6975 | G43: 3.5 | H43: 45237 | I43: 30 | J43: =+'Dis F'!$H43+'Dis F'!$I43 -> 45267 | K43: ='Dis F'!$H43+'Dis F'!$I43-TODAY() -> -329 | L43: =IF(K43<1,"VENCIDO","VIGENTE") -> VENCIDO
C44: aleksandro | F44: 864 | G44: 3.5 | H44: 45248 | I44: 30 | J44: =+'Dis F'!$H44+'Dis F'!$I44 -> 45278 | K44: ='Dis F'!$H44+'Dis F'!$I44-TODAY() -> -318 | L44: =IF(K44<1,"VENCIDO","VIGENTE") -> VENCIDO
C45: jesus | F45: 4545 | G45: 3.5 | H45: 45241 | I45: 30 | J45: =+'Dis F'!$H45+'Dis F'!$I45 -> 45271 | K45: ='Dis F'!$H45+'Dis F'!$I45-TODAY() -> -325 | L45: =IF(K45<1,"VENCIDO","VIGENTE") -> VENCIDO
C46: miguel | F46: 4545 | G46: 3.5 | H46: 45234 | I46: 30 | J46: =+'Dis F'!$H46+'Dis F'!$I46 -> 45264 | K46: ='Dis F'!$H46+'Dis F'!$I46-TODAY() -> -332 | L46: =IF(K46<1,"VENCIDO","VIGENTE") -> VENCIDO
C47: aleksandro | F47: ***3 | G47: 3.5 | H47: 45248 | I47: 30 | J47: =+'Dis F'!$H47+'Dis F'!$I47 -> 45278 | K47: ='Dis F'!$H47+'Dis F'!$I47-TODAY() -> -318 | L47: =IF(K47<1,"VENCIDO","VIGENTE") -> VENCIDO
C48: dany e | G48: 3.5 | H48: 45260 | I48: 30 | J48: =+'Dis F'!$H48+'Dis F'!$I48 -> 45290 | K48: ='Dis F'!$H48+'Dis F'!$I48-TODAY() -> -306 | L48: =IF(K48<1,"VENCIDO","VIGENTE") -> VENCIDO
C49: PERFILES : | F49: =SUM(F42:F48) -> 20385 | G49: =SUM(G42:G48) -> 24.5 | I49: 30 | J49: =+'Dis F'!$H49+'Dis F'!$I49 -> 30 | K49: ='Dis F'!$H49+'Dis F'!$I49-TODAY() -> -45566
B57: ALERTA DIAS
B58: =TODAY() -> 45596
B59: CUENTA | C59: NOMBRE | D59: CLAVE | E59: TELEFONO | F59: PIN PERFIL | G59: PRECIO | H59: FECHA DE INICIO | I59: DIAS | J59: FECHA DE VENCIMIENTO | K59: ALARMA | L59: ESTADO
B60: Correo : deku75490stream@gmail.com Contraseña : dek852mure | C60: gabo16 | F60: 2838 | G60: =IF(H60>0,7,0) -> 7 | H60: 45260 | I60: 30 | J60: =+'Dis F'!$H60+'Dis F'!$I60 -> 45290 | K60: ='Dis F'!$H60+'Dis F'!$I60-TODAY() -> -306 | L60: =IF(K60<1,"VENCIDO","VIGENTE") -> VENCIDO
C61: gabo18 | F61: 2937 | G61: =IF(H61>0,7,0) -> 7 | H61: 45260 | I61: 30 | J61: =+'Dis F'!$H61+'Dis F'!$I61 -> 45290 | K61: ='Dis F'!$H61+'Dis F'!$I61-TODAY() -> -306 | L61: =IF(K61<1,"VENCIDO","VIGENTE") -> VENCIDO
G62: =IF(H62>0,7,0) -> 0 | I62: 30 | J62: =+'Dis F'!$H62+'Dis F'!$I62 -> 30 | K62: ='Dis F'!$H62+'Dis F'!$I62-TODAY() -> -45566 | L62: =IF(K62<1,"VENCIDO","VIGENTE") -> VENCIDO
G63: =IF(H63>0,7,0) -> 0 | I63: 30 | J63: =+'Dis F'!$H63+'Dis F'!$I63 -> 30 | K63: ='Dis F'!$H63+'Dis F'!$I63-TODAY() -> -45566 | L63: =IF(K63<1,"VENCIDO","VIGENTE") -> VENCIDO
G64: =IF(H64>0,7,0) -> 0 | I64: 30 | J64: =+'Dis F'!$H64+'Dis F'!$I64 -> 30 | K64: ='Dis F'!$H64+'Dis F'!$I64-TODAY() -> -45566 | L64: =IF(K64<1,"VENCIDO","VIGENTE") -> VENCIDO
G65: =IF(H65>0,7,0) -> 0 | I65: 30 | J65: =+'Dis F'!$H65+'Dis F'!$I65 -> 30 | K65: ='Dis F'!$H65+'Dis F'!$I65-TODAY() -> -45566 | L65: =IF(K65<1,"VENCIDO","VIGENTE") -> VENCIDO
G66: =IF(H66>0,7,0) -> 0 | I66: 30 | J66: =+'Dis F'!$H66+'Dis F'!$I66 -> 30 | K66: ='Dis F'!$H66+'Dis F'!$I66-TODAY() -> -45566 | L66: =IF(K66<1,"VENCIDO","VIGENTE") -> VENCIDO
C67: PERFILES : | F67: =SUM(F60:F66) -> 5775 | G67: =SUM(G60:G66) -> 14 | I67: 30 | J67: =+'Dis F'!$H67+'Dis F'!$I67 -> 30 | K67: ='Dis F'!$H67+'Dis F'!$I67-TODAY() -> -45566
B74: ALERTA DIAS
B75: =TODAY() -> 45596
B76: CUENTA | C76: NOMBRE | D76: CLAVE | E76: TELEFONO | F76: PIN PERFIL | G76: PRECIO | H76: FECHA DE INICIO | I76: DIAS | J76: FECHA DE VENCIMIENTO | K76: ALARMA | L76: ESTADO
B77: Correo: dekhu12deku467ger@hotmail.com Contraseña: dek43##defs15 | C77: lupita4 | F77: 2838 | G77: =IF(H77>0,7,0) -> 0 | I77: 30 | J77: =+'Dis F'!$H77+'Dis F'!$I77 -> 30 | K77: ='Dis F'!$H77+'Dis F'!$I77-TODAY() -> -45566 | L77: =IF(K77<1,"VENCIDO","VIGENTE") -> VENCIDO
C78: lunita9 | F78: 2937 | G78: =IF(H78>0,7,0) -> 7 | H78: 45326 | I78: 30 | J78: =+'Dis F'!$H78+'Dis F'!$I78 -> 45356 | K78: ='Dis F'!$H78+'Dis F'!$I78-TODAY() -> -240 | L78: =IF(K78<1,"VENCIDO","VIGENTE") -> VENCIDO
G79: =IF(H79>0,7,0) -> 0 | I79: 30 | J79: =+'Dis F'!$H79+'Dis F'!$I79 -> 30 | K79: ='Dis F'!$H79+'Dis F'!$I79-TODAY() -> -45566 | L79: =IF(K79<1,"VENCIDO","VIGENTE") -> VENCIDO
G80: =IF(H80>0,7,0) -> 0 | I80: 30 | J80: =+'Dis F'!$H80+'Dis F'!$I80 -> 30 | K80: ='Dis F'!$H80+'Dis F'!$I80-TODAY() -> -45566 | L80: =IF(K80<1,"VENCIDO","VIGENTE") -> VENCIDO
G81: =IF(H81>0,7,0) -> 0 | I81: 30 | J81: =+'Dis F'!$H81+'Dis F'!$I81 -> 30 | K81: ='Dis F'!$H81+'Dis F'!$I81-TODAY() -> -45566 | L81: =IF(K81<1,"VENCIDO","VIGENTE") -> VENCIDO
G82: =IF(H82>0,7,0) -> 0 | I82: 30 | J82: =+'Dis F'!$H82+'Dis F'!$I82 -> 30 | K82: ='Dis F'!$H82+'Dis F'!$I82-TODAY() -> -45566 | L82: =IF(K82<1,"VENCIDO","VIGENTE") -> VENCIDO
G83: =IF(H83>0,7,0) -> 0 | I83: 30 | J83: =+'Dis F'!$H83+'Dis F'!$I83 -> 30 | K83: ='Dis F'!$H83+'Dis F'!$I83-TODAY() -> -45566 | L83: =IF(K83<1,"VENCIDO","VIGENTE") -> VENCIDO
C84: PERFILES : | F84: =SUM(F77:F83) -> 5775 | G84: =SUM(G77:G83) -> 7 | I84: 30 | J84: =+'Dis F'!$H84+'Dis F'!$I84 -> 30 | K84: ='Dis F'!$H84+'Dis F'!$I84-TODAY() -> -45566
B87: ALERTA DIAS | C87: disney-star
B88: =TODAY() -> 45596
B89: CUENTA | C89: NOMBRE | D89: CLAVE | E89: TELEFONO | F89: PIN PERFIL | G89: PRECIO | H89: FECHA DE INICIO | I89: DIAS | J89: FECHA DE VENCIMIENTO | K89: ALARMA | L89: ESTADO
B90: CORREO : deku24net@heisei.be CONTRASEÑA: d2t45deku5d | C90: Guillermo194 | E90: 51 988 684 621 | F90: 1937 | G90: =IF(H90>0,7,0) -> 0 | I90: 30 | J90: =+'Dis F'!$H90+'Dis F'!$I90 -> 30 | K90: ='Dis F'!$H90+'Dis F'!$I90-TODAY() -> -45566 | L90: =IF(K90<1,"VENCIDO","VIGENTE") -> VENCIDO
G91: =IF(H91>0,7,0) -> 0 | I91: 30 | J91: =+'Dis F'!$H91+'Dis F'!$I91 -> 30 | K91: ='Dis F'!$H91+'Dis F'!$I91-TODAY() -> -45566 | L91: =IF(K91<1,"VENCIDO","VIGENTE") -> VENCIDO
G92: =IF(H92>0,7,0) -> 0 | I92: 30 | J92: =+'Dis F'!$H92+'Dis F'!$I92 -> 30 | K92: ='Dis F'!$H92+'Dis F'!$I92-TODAY() -> -45566 | L92: =IF(K92<1,"VENCIDO","VIGENTE") -> VENCIDO
G93: =IF(H93>0,7,0) -> 0 | I93: 30 | J93: =+'Dis F'!$H93+'Dis F'!$I93 -> 30 | K93: ='Dis F'!$H93+'Dis F'!$I93-TODAY() -> -45566 | L93: =IF(K93<1,"VENCIDO","VIGENTE") -> VENCIDO
G94: =IF(H94>0,7,0) -> 0 | I94: 30 | J94: =+'Dis F'!$H94+'Dis F'!$I94 -> 30 | K94: ='Dis F'!$H94+'Dis F'!$I94-TODAY() -> -45566 | L94: =IF(K94<1,"VENCIDO","VIGENTE") -> VENCIDO
G95: =IF(H95>0,7,0) -> 0 | I95: 30 | J95: =+'Dis F'!$H95+'Dis F'!$I95 -> 30 | K95: ='Dis F'!$H95+'Dis F'!$I95-TODAY() -> -45566 | L95: =IF(K95<1,"VENCIDO","VIGENTE") -> VENCIDO
G96: =IF(H96>0,7,0) -> 0 | I96: 30 | J96: =+'Dis F'!$H96+'Dis F'!$I96 -> 30 | K96: ='Dis F'!$H96+'Dis F'!$I96-TODAY() -> -45566 | L96: =IF(K96<1,"VENCIDO","VIGENTE") -> VENCIDO
C97: PERFILES : | F97: =SUM(F90:F96) -> 1937 | G97: =SUM(G90:G96) -> 0 | I97: 30 | J97: =+'Dis F'!$H97+'Dis F'!$I97 -> 30 | K97: ='Dis F'!$H97+'Dis F'!$I97-TODAY() -> -45566
B100: ALERTA DIAS
B101: =TODAY() -> 45596
B102: CUENTA | C102: NOMBRE | D102: CLAVE | E102: TELEFONO | F102: PIN PERFIL | G102: PRECIO | H102: FECHA DE INICIO | I102: DIAS | J102: FECHA DE VENCIMIENTO | K102: ALARMA | L102: ESTADO
B103: Correo : deku001streamu@simaenaga.com Contraseña: dek356bert3 | C103: Xio116 | E103: 51 988 684 621 | F103: 3488 | G103: =IF(H103>0,4,0) -> 4 | H103: 45587 | I103: 30 | J103: =+'Dis F'!$H103+'Dis F'!$I103 -> 45617 | K103: ='Dis F'!$H103+'Dis F'!$I103-TODAY() -> 21 | L103: =IF(K103<1,"VENCIDO","VIGENTE") -> VIGENTE
C104: akemi371 | E104: 51 963 931 721 | F104: 9239 | G104: =IF(H104>0,3.5,0) -> 3.5 | H104: 45567 | I104: 30 | J104: =+'Dis F'!$H104+'Dis F'!$I104 -> 45597 | K104: ='Dis F'!$H104+'Dis F'!$I104-TODAY() -> 1 | L104: =IF(K104<1,"VENCIDO","VIGENTE") -> VIGENTE
I105: 30 | J105: =+'Dis F'!$H105+'Dis F'!$I105 -> 30 | K105: ='Dis F'!$H105+'Dis F'!$I105-TODAY() -> -45566 | L105: =IF(K105<1,"VENCIDO","VIGENTE") -> VENCIDO
G106: =IF(H106>0,7,0) -> 0 | I106: 30 | J106: =+'Dis F'!$H106+'Dis F'!$I106 -> 30 | K106: ='Dis F'!$H106+'Dis F'!$I106-TODAY() -> -45566 | L106: =IF(K106<1,"VENCIDO","VIGENTE") -> VENCIDO
G107: =IF(H107>0,7,0) -> 0 | I107: 30 | J107: =+'Dis F'!$H107+'Dis F'!$I107 -> 30 | K107: ='Dis F'!$H107+'Dis F'!$I107-TODAY() -> -45566 | L107: =IF(K107<1,"VENCIDO","VIGENTE") -> VENCIDO
G108: =IF(H108>0,7,0) -> 0 | I108: 30 | J108: =+'Dis F'!$H108+'Dis F'!$I108 -> 30 | K108: ='Dis F'!$H108+'Dis F'!$I108-TODAY() -> -45566 | L108: =IF(K108<1,"VENCIDO","VIGENTE") -> VENCIDO
C109: PERFILES : | F109: =SUM(F103:F108) -> 12727 | G109: =SUM(G103:G108) -> 7.5 | I109: 30 | J109: =+'Dis F'!$H109+'Dis F'!$I109 -> 30 | K109: ='Dis F'!$H109+'Dis F'!$I109-TODAY() -> -45566

Sheet Dis R
B5: Jhosut
B6: =TODAY() -> 45596
B7: CUENTA | C7: Contraseña | D7: CLAVE | E7: Facturacion | F7: PIN PERFIL | G7: PRECIO | H7: FECHA DE INICIO | I7: DIAS | J7: FECHA DE VENCIMIENTO | K7: ALARMA | L7: ESTADO
C8: dek356bert3 | D8: Junior2847 | F8: 6885 | G8: =IF(H8>0,5,0) -> 5 | H8: 45560 | I8: 30 | J8: =+'Dis R'!$H8+'Dis R'!$I8 -> 45590 | K8: ='Dis R'!$H8+'Dis R'!$I8-TODAY() -> -6 | L8: =IF(K8<1,"VENCIDO","VIGENTE") -> VENCIDO
G9: =IF(H9>0,10,0) -> 0 | I9: 30 | J9: =+'Dis R'!$H9+'Dis R'!$I9 -> 30 | K9: ='Dis R'!$H9+'Dis R'!$I9-TODAY() -> -45566 | L9: =IF(K9<1,"VENCIDO","VIGENTE") -> VENCIDO
G10: =IF(H10>0,10,0) -> 0 | I10: 30 | J10: =+'Dis R'!$H10+'Dis R'!$I10 -> 30 | K10: ='Dis R'!$H10+'Dis R'!$I10-TODAY() -> -45566 | L10: =IF(K10<1,"VENCIDO","VIGENTE") -> VENCIDO
G11: =IF(H11>0,10,0) -> 0 | I11: 30 | J11: =+'Dis R'!$H11+'Dis R'!$I11 -> 30 | K11: ='Dis R'!$H11+'Dis R'!$I11-TODAY() -> -45566 | L11: =IF(K11<1,"VENCIDO","VIGENTE") -> VENCIDO
G12: =IF(H12>0,10,0) -> 0 | I12: 30 | J12: =+'Dis R'!$H12+'Dis R'!$I12 -> 30 | K12: ='Dis R'!$H12+'Dis R'!$I12-TODAY() -> -45566 | L12: =IF(K12<1,"VENCIDO","VIGENTE") -> VENCIDO
G13: =IF(H13>0,10,0) -> 0 | I13: 30 | J13: =+'Dis R'!$H13+'Dis R'!$I13 -> 30 | K13: ='Dis R'!$H13+'Dis R'!$I13-TODAY() -> -45566 | L13: =IF(K13<1,"VENCIDO","VIGENTE") -> VENCIDO
G14: =IF(H14>0,10,0) -> 0 | I14: 30 | J14: =+'Dis R'!$H14+'Dis R'!$I14 -> 30 | K14: ='Dis R'!$H14+'Dis R'!$I14-TODAY() -> -45566 | L14: =IF(K14<1,"VENCIDO","VIGENTE") -> VENCIDO
G15: =IF(H15>0,10,0) -> 0 | I15: 30 | J15: =+'Dis R'!$H15+'Dis R'!$I15 -> 30 | K15: ='Dis R'!$H15+'Dis R'!$I15-TODAY() -> -45566 | L15: =IF(K15<1,"VENCIDO","VIGENTE") -> VENCIDO
G16: =IF(H16>0,10,0) -> 0 | I16: 30 | J16: =+'Dis R'!$H16+'Dis R'!$I16 -> 30 | K16: ='Dis R'!$H16+'Dis R'!$I16-TODAY() -> -45566 | L16: =IF(K16<1,"VENCIDO","VIGENTE") -> VENCIDO
G17: =IF(H17>0,10,0) -> 0 | I17: 30 | J17: =+'Dis R'!$H17+'Dis R'!$I17 -> 30 | K17: ='Dis R'!$H17+'Dis R'!$I17-TODAY() -> -45566 | L17: =IF(K17<1,"VENCIDO","VIGENTE") -> VENCIDO
G18: =IF(H18>0,10,0) -> 0 | I18: 30 | J18: =+'Dis R'!$H18+'Dis R'!$I18 -> 30 | K18: ='Dis R'!$H18+'Dis R'!$I18-TODAY() -> -45566 | L18: =IF(K18<1,"VENCIDO","VIGENTE") -> VENCIDO
G19: =IF(H19>0,10,0) -> 0 | I19: 30 | J19: =+'Dis R'!$H19+'Dis R'!$I19 -> 30 | K19: ='Dis R'!$H19+'Dis R'!$I19-TODAY() -> -45566 | L19: =IF(K19<1,"VENCIDO","VIGENTE") -> VENCIDO
G20: =IF(H20>0,10,0) -> 0 | I20: 30 | J20: =+'Dis R'!$H20+'Dis R'!$I20 -> 30 | K20: ='Dis R'!$H20+'Dis R'!$I20-TODAY() -> -45566 | L20: =IF(K20<1,"VENCIDO","VIGENTE") -> VENCIDO
G21: =SUM(G8:G20) -> 5
B26: Yaear
B27: =TODAY() -> 45596 | C27: cl294309@gmail.com | G27: saya dolares
B28: CUENTA | C28: Contraseña | D28: CLAVE | E28: Facturacion | F28: PIN PERFIL | G28: PRECIO | H28: FECHA DE INICIO | I28: DIAS | J28: FECHA DE VENCIMIENTO | K28: ALARMA | L28: ESTADO
B29: saya37 | C29: dek35ner46 | F29: 6004 | G29: =IF(H29>0,1.5,0) -> 1.5 | H29: 45428 | I29: 30 | J29: =+'Dis R'!$H29+'Dis R'!$I29 -> 45458 | K29: ='Dis R'!$H29+'Dis R'!$I29-TODAY() -> -138 | L29: =IF(K29<1,"VENCIDO","VIGENTE") -> VENCIDO
B30: Pamela64 | C30: dek35ner47 | F30: 8445 | G30: =IF(H30>0,5,0) -> 5 | H30: 45428 | I30: 30 | J30: =+'Dis R'!$H30+'Dis R'!$I30 -> 45458 | K30: ='Dis R'!$H30+'Dis R'!$I30-TODAY() -> -138 | L30: =IF(K30<1,"VENCIDO","VIGENTE") -> VENCIDO
G31: =IF(H31>0,10,0) -> 0 | I31: 30 | J31: =+'Dis R'!$H31+'Dis R'!$I31 -> 30 | K31: ='Dis R'!$H31+'Dis R'!$I31-TODAY() -> -45566 | L31: =IF(K31<1,"VENCIDO","VIGENTE") -> VENCIDO
G32: =IF(H32>0,10,0) -> 0 | I32: 30 | J32: =+'Dis R'!$H32+'Dis R'!$I32 -> 30 | K32: ='Dis R'!$H32+'Dis R'!$I32-TODAY() -> -45566 | L32: =IF(K32<1,"VENCIDO","VIGENTE") -> VENCIDO
G33: =IF(H33>0,10,0) -> 0 | I33: 30 | J33: =+'Dis R'!$H33+'Dis R'!$I33 -> 30 | K33: ='Dis R'!$H33+'Dis R'!$I33-TODAY() -> -45566 | L33: =IF(K33<1,"VENCIDO","VIGENTE") -> VENCIDO
G34: =IF(H34>0,10,0) -> 0 | I34: 30 | J34: =+'Dis R'!$H34+'Dis R'!$I34 -> 30 | K34: ='Dis R'!$H34+'Dis R'!$I34-TODAY() -> -45566 | L34: =IF(K34<1,"VENCIDO","VIGENTE") -> VENCIDO
G35: =IF(H35>0,10,0) -> 0 | I35: 30 | J35: =+'Dis R'!$H35+'Dis R'!$I35 -> 30 | K35: ='Dis R'!$H35+'Dis R'!$I35-TODAY() -> -45566 | L35: =IF(K35<1,"VENCIDO","VIGENTE") -> VENCIDO
G36: =IF(H36>0,10,0) -> 0 | I36: 30 | J36: =+'Dis R'!$H36+'Dis R'!$I36 -> 30 | K36: ='Dis R'!$H36+'Dis R'!$I36-TODAY() -> -45566 | L36: =IF(K36<1,"VENCIDO","VIGENTE") -> VENCIDO
G37: =IF(H37>0,10,0) -> 0 | I37: 30 | J37: =+'Dis R'!$H37+'Dis R'!$I37 -> 30 | K37: ='Dis R'!$H37+'Dis R'!$I37-TODAY() -> -45566 | L37: =IF(K37<1,"VENCIDO","VIGENTE") -> VENCIDO
G38: =IF(H38>0,10,0) -> 0 | I38: 30 | J38: =+'Dis R'!$H38+'Dis R'!$I38 -> 30 | K38: ='Dis R'!$H38+'Dis R'!$I38-TODAY() -> -45566 | L38: =IF(K38<1,"VENCIDO","VIGENTE") -> VENCIDO
G39: =IF(H39>0,10,0) -> 0 | I39: 30 | J39: =+'Dis R'!$H39+'Dis R'!$I39 -> 30 | K39: ='Dis R'!$H39+'Dis R'!$I39-TODAY() -> -45566 | L39: =IF(K39<1,"VENCIDO","VIGENTE") -> VENCIDO
G40: =IF(H40>0,10,0) -> 0 | I40: 30 | J40: =+'Dis R'!$H40+'Dis R'!$I40 -> 30 | K40: ='Dis R'!$H40+'Dis R'!$I40-TODAY() -> -45566 | L40: =IF(K40<1,"VENCIDO","VIGENTE") -> VENCIDO
G41: =IF(H41>0,10,0) -> 0 | I41: 30 | J41: =+'Dis R'!$H41+'Dis R'!$I41 -> 30 | K41: ='Dis R'!$H41+'Dis R'!$I41-TODAY() -> -45566 | L41: =IF(K41<1,"VENCIDO","VIGENTE") -> VENCIDO
G42: =SUM(G29:G41) -> 6.5
B47: Franco Jeyli
B48: =TODAY() -> 45596
B49: CUENTA | C49: Contraseña | D49: CLAVE | E49: Facturacion | F49: PIN PERFIL | G49: PRECIO | H49: FECHA DE INICIO | I49: DIAS | J49: FECHA DE VENCIMIENTO | K49: ALARMA | L49: ESTADO
G50: =IF(H50>0,10,0) -> 0 | I50: 30 | J50: =+'Dis R'!$H50+'Dis R'!$I50 -> 30 | K50: ='Dis R'!$H50+'Dis R'!$I50-TODAY() -> -45566 | L50: =IF(K50<1,"VENCIDO","VIGENTE") -> VENCIDO
G51: =IF(H51>0,10,0) -> 0 | I51: 30 | J51: =+'Dis R'!$H51+'Dis R'!$I51 -> 30 | K51: ='Dis R'!$H51+'Dis R'!$I51-TODAY() -> -45566 | L51: =IF(K51<1,"VENCIDO","VIGENTE") -> VENCIDO
G52: =IF(H52>0,10,0) -> 0 | I52: 30 | J52: =+'Dis R'!$H52+'Dis R'!$I52 -> 30 | K52: ='Dis R'!$H52+'Dis R'!$I52-TODAY() -> -45566 | L52: =IF(K52<1,"VENCIDO","VIGENTE") -> VENCIDO
G53: =IF(H53>0,10,0) -> 0 | I53: 30 | J53: =+'Dis R'!$H53+'Dis R'!$I53 -> 30 | K53: ='Dis R'!$H53+'Dis R'!$I53-TODAY() -> -45566 | L53: =IF(K53<1,"VENCIDO","VIGENTE") -> VENCIDO
G54: =IF(H54>0,10,0) -> 0 | I54: 30 | J54: =+'Dis R'!$H54+'Dis R'!$I54 -> 30 | K54: ='Dis R'!$H54+'Dis R'!$I54-TODAY() -> -45566 | L54: =IF(K54<1,"VENCIDO","VIGENTE") -> VENCIDO
G55: =IF(H55>0,10,0) -> 0 | I55: 30 | J55: =+'Dis R'!$H55+'Dis R'!$I55 -> 30 | K55: ='Dis R'!$H55+'Dis R'!$I55-TODAY() -> -45566 | L55: =IF(K55<1,"VENCIDO","VIGENTE") -> VENCIDO
G56: =IF(H56>0,10,0) -> 0 | I56: 30 | J56: =+'Dis R'!$H56+'Dis R'!$I56 -> 30 | K56: ='Dis R'!$H56+'Dis R'!$I56-TODAY() -> -45566 | L56: =IF(K56<1,"VENCIDO","VIGENTE") -> VENCIDO
G57: =IF(H57>0,10,0) -> 0 | I57: 30 | J57: =+'Dis R'!$H57+'Dis R'!$I57 -> 30 | K57: ='Dis R'!$H57+'Dis R'!$I57-TODAY() -> -45566 | L57: =IF(K57<1,"VENCIDO","VIGENTE") -> VENCIDO
G58: =IF(H58>0,10,0) -> 0 | I58: 30 | J58: =+'Dis R'!$H58+'Dis R'!$I58 -> 30 | K58: ='Dis R'!$H58+'Dis R'!$I58-TODAY() -> -45566 | L58: =IF(K58<1,"VENCIDO","VIGENTE") -> VENCIDO
G59: =IF(H59>0,10,0) -> 0 | I59: 30 | J59: =+'Dis R'!$H59+'Dis R'!$I59 -> 30 | K59: ='Dis R'!$H59+'Dis R'!$I59-TODAY() -> -45566 | L59: =IF(K59<1,"VENCIDO","VIGENTE") -> VENCIDO
G60: =IF(H60>0,10,0) -> 0 | I60: 30 | J60: =+'Dis R'!$H60+'Dis R'!$I60 -> 30 | K60: ='Dis R'!$H60+'Dis R'!$I60-TODAY() -> -45566 | L60: =IF(K60<1,"VENCIDO","VIGENTE") -> VENCIDO
G61: =IF(H61>0,10,0) -> 0 | I61: 30 | J61: =+'Dis R'!$H61+'Dis R'!$I61 -> 30 | K61: ='Dis R'!$H61+'Dis R'!$I61-TODAY() -> -45566 | L61: =IF(K61<1,"VENCIDO","VIGENTE") -> VENCIDO
G62: =IF(H62>0,10,0) -> 0 | I62: 30 | J62: =+'Dis R'!$H62+'Dis R'!$I62 -> 30 | K62: ='Dis R'!$H62+'Dis R'!$I62-TODAY() -> -45566 | L62: =IF(K62<1,"VENCIDO","VIGENTE") -> VENCIDO
G63: =SUM(G50:G62) -> 0
B69: =TODAY() -> 45596
B70: CUENTA | C70: Contraseña | D70: CLAVE | E70: Facturacion | F70: PIN PERFIL | G70: PRECIO | H70: FECHA DE INICIO | I70: DIAS | J70: FECHA DE VENCIMIENTO | K70: ALARMA | L70: ESTADO
G71: =IF(H71>0,10,0) -> 0 | I71: 30 | J71: =+'Dis R'!$H71+'Dis R'!$I71 -> 30 | K71: ='Dis R'!$H71+'Dis R'!$I71-TODAY() -> -45566 | L71: =IF(K71<1,"VENCIDO","VIGENTE") -> VENCIDO
G72: =IF(H72>0,10,0) -> 0 | I72: 30 | J72: =+'Dis R'!$H72+'Dis R'!$I72 -> 30 | K72: ='Dis R'!$H72+'Dis R'!$I72-TODAY() -> -45566 | L72: =IF(K72<1,"VENCIDO","VIGENTE") -> VENCIDO
G73: =IF(H73>0,10,0) -> 0 | I73: 30 | J73: =+'Dis R'!$H73+'Dis R'!$I73 -> 30 | K73: ='Dis R'!$H73+'Dis R'!$I73-TODAY() -> -45566 | L73: =IF(K73<1,"VENCIDO","VIGENTE") -> VENCIDO
G74: =IF(H74>0,10,0) -> 0 | I74: 30 | J74: =+'Dis R'!$H74+'Dis R'!$I74 -> 30 | K74: ='Dis R'!$H74+'Dis R'!$I74-TODAY() -> -45566 | L74: =IF(K74<1,"VENCIDO","VIGENTE") -> VENCIDO
G75: =IF(H75>0,10,0) -> 0 | I75: 30 | J75: =+'Dis R'!$H75+'Dis R'!$I75 -> 30 | K75: ='Dis R'!$H75+'Dis R'!$I75-TODAY() -> -45566 | L75: =IF(K75<1,"VENCIDO","VIGENTE") -> VENCIDO
G76: =IF(H76>0,10,0) -> 0 | I76: 30 | J76: =+'Dis R'!$H76+'Dis R'!$I76 -> 30 | K76: ='Dis R'!$H76+'Dis R'!$I76-TODAY() -> -45566 | L76: =IF(K76<1,"VENCIDO","VIGENTE") -> VENCIDO
G77: =IF(H77>0,10,0) -> 0 | I77: 30 | J77: =+'Dis R'!$H77+'Dis R'!$I77 -> 30 | K77: ='Dis R'!$H77+'Dis R'!$I77-TODAY() -> -45566 | L77: =IF(K77<1,"VENCIDO","VIGENTE") -> VENCIDO
G78: =IF(H78>0,10,0) -> 0 | I78: 30 | J78: =+'Dis R'!$H78+'Dis R'!$I78 -> 30 | K78: ='Dis R'!$H78+'Dis R'!$I78-TODAY() -> -45566 | L78: =IF(K78<1,"VENCIDO","VIGENTE") -> VENCIDO
G79: =IF(H79>0,10,0) -> 0 | I79: 30 | J79: =+'Dis R'!$H79+'Dis R'!$I79 -> 30 | K79: ='Dis R'!$H79+'Dis R'!$I79-TODAY() -> -45566 | L79: =IF(K79<1,"VENCIDO","VIGENTE") -> VENCIDO
G80: =IF(H80>0,10,0) -> 0 | I80: 30 | J80: =+'Dis R'!$H80+'Dis R'!$I80 -> 30 | K80: ='Dis R'!$H80+'Dis R'!$I80-TODAY() -> -45566 | L80: =IF(K80<1,"VENCIDO","VIGENTE") -> VENCIDO
G81: =IF(H81>0,10,0) -> 0 | I81: 30 | J81: =+'Dis R'!$H81+'Dis R'!$I81 -> 30 | K81: ='Dis R'!$H81+'Dis R'!$I81-TODAY() -> -45566 | L81: =IF(K81<1,"VENCIDO","VIGENTE") -> VENCIDO
G82: =IF(H82>0,10,0) -> 0 | I82: 30 | J82: =+'Dis R'!$H82+'Dis R'!$I82 -> 30 | K82: ='Dis R'!$H82+'Dis R'!$I82-TODAY() -> -45566 | L82: =IF(K82<1,"VENCIDO","VIGENTE") -> VENCIDO
G83: =IF(H83>0,10,0) -> 0 | I83: 30 | J83: =+'Dis R'!$H83+'Dis R'!$I83 -> 30 | K83: ='Dis R'!$H83+'Dis R'!$I83-TODAY() -> -45566 | L83: =IF(K83<1,"VENCIDO","VIGENTE") -> VENCIDO
G84: =SUM(G71:G83) -> 0
B89: Jhosut
B90: =TODAY() -> 45596
B91: CUENTA | C91: Contraseña | D91: CLAVE | E91: Facturacion | F91: PIN PERFIL | G91: PRECIO | H91: FECHA DE INICIO | I91: DIAS | J91: FECHA DE VENCIMIENTO | K91: ALARMA | L91: ESTADO
G92: =IF(H92>0,10,0) -> 0 | I92: 30 | J92: =+'Dis R'!$H92+'Dis R'!$I92 -> 30 | K92: ='Dis R'!$H92+'Dis R'!$I92-TODAY() -> -45566 | L92: =IF(K92<1,"VENCIDO","VIGENTE") -> VENCIDO
G93: =IF(H93>0,10,0) -> 0 | I93: 30 | J93: =+'Dis R'!$H93+'Dis R'!$I93 -> 30 | K93: ='Dis R'!$H93+'Dis R'!$I93-TODAY() -> -45566 | L93: =IF(K93<1,"VENCIDO","VIGENTE") -> VENCIDO
G94: =IF(H94>0,10,0) -> 0 | I94: 30 | J94: =+'Dis R'!$H94+'Dis R'!$I94 -> 30 | K94: ='Dis R'!$H94+'Dis R'!$I94-TODAY() -> -45566 | L94: =IF(K94<1,"VENCIDO","VIGENTE") -> VENCIDO
G95: =IF(H95>0,10,0) -> 0 | I95: 30 | J95: =+'Dis R'!$H95+'Dis R'!$I95 -> 30 | K95: ='Dis R'!$H95+'Dis R'!$I95-TODAY() -> -45566 | L95: =IF(K95<1,"VENCIDO","VIGENTE") -> VENCIDO
G96: =IF(H96>0,10,0) -> 0 | I96: 30 | J96: =+'Dis R'!$H96+'Dis R'!$I96 -> 30 | K96: ='Dis R'!$H96+'Dis R'!$I96-TODAY() -> -45566 | L96: =IF(K96<1,"VENCIDO","VIGENTE") -> VENCIDO
G97: =IF(H97>0,10,0) -> 0 | I97: 30 | J97: =+'Dis R'!$H97+'Dis R'!$I97 -> 30 | K97: ='Dis R'!$H97+'Dis R'!$I97-TODAY() -> -45566 | L97: =IF(K97<1,"VENCIDO","VIGENTE") -> VENCIDO
G98: =IF(H98>0,10,0) -> 0 | I98: 30 | J98: =+'Dis R'!$H98+'Dis R'!$I98 -> 30 | K98: ='Dis R'!$H98+'Dis R'!$I98-TODAY() -> -45566 | L98: =IF(K98<1,"VENCIDO","VIGENTE") -> VENCIDO
G99: =IF(H99>0,10,0) -> 0 | I99: 30 | J99: =+'Dis R'!$H99+'Dis R'!$I99 -> 30 | K99: ='Dis R'!$H99+'Dis R'!$I99-TODAY() -> -45566 | L99: =IF(K99<1,"VENCIDO","VIGENTE") -> VENCIDO
G100: =IF(H100>0,10,0) -> 0 | I100: 30 | J100: =+'Dis R'!$H100+'Dis R'!$I100 -> 30 | K100: ='Dis R'!$H100+'Dis R'!$I100-TODAY() -> -45566 | L100: =IF(K100<1,"VENCIDO","VIGENTE") -> VENCIDO
G101: =IF(H101>0,10,0) -> 0 | I101: 30 | J101: =+'Dis R'!$H101+'Dis R'!$I101 -> 30 | K101: ='Dis R'!$H101+'Dis R'!$I101-TODAY() -> -45566 | L101: =IF(K101<1,"VENCIDO","VIGENTE") -> VENCIDO
G102: =IF(H102>0,10,0) -> 0 | I102: 30 | J102: =+'Dis R'!$H102+'Dis R'!$I102 -> 30 | K102: ='Dis R'!$H102+'Dis R'!$I102-TODAY() -> -45566 | L102: =IF(K102<1,"VENCIDO","VIGENTE") -> VENCIDO
G103: =IF(H103>0,10,0) -> 0 | I103: 30 | J103: =+'Dis R'!$H103+'Dis R'!$I103 -> 30 | K103: ='Dis R'!$H103+'Dis R'!$I103-TODAY() -> -45566 | L103: =IF(K103<1,"VENCIDO","VIGENTE") -> VENCIDO
G104: =IF(H104>0,10,0) -> 0 | I104: 30 | J104: =+'Dis R'!$H104+'Dis R'!$I104 -> 30 | K104: ='Dis R'!$H104+'Dis R'!$I104-TODAY() -> -45566 | L104: =IF(K104<1,"VENCIDO","VIGENTE") -> VENCIDO
G105: =SUM(G92:G104) -> 0
B111: =TODAY() -> 45596
B112: CUENTA | C112: Contraseña | D112: CLAVE | E112: Facturacion | F112: PIN PERFIL | G112: PRECIO | H112: FECHA DE INICIO | I112: DIAS | J112: FECHA DE VENCIMIENTO | K112: ALARMA | L112: ESTADO
G113: =IF(H113>0,10,0) -> 0 | I113: 30 | J113: =+'Dis R'!$H113+'Dis R'!$I113 -> 30 | K113: ='Dis R'!$H113+'Dis R'!$I113-TODAY() -> -45566 | L113: =IF(K113<1,"VENCIDO","VIGENTE") -> VENCIDO
G114: =IF(H114>0,10,0) -> 0 | I114: 30 | J114: =+'Dis R'!$H114+'Dis R'!$I114 -> 30 | K114: ='Dis R'!$H114+'Dis R'!$I114-TODAY() -> -45566 | L114: =IF(K114<1,"VENCIDO","VIGENTE") -> VENCIDO
G115: =IF(H115>0,10,0) -> 0 | I115: 30 | J115: =+'Dis R'!$H115+'Dis R'!$I115 -> 30 | K115: ='Dis R'!$H115+'Dis R'!$I115-TODAY() -> -45566 | L115: =IF(K115<1,"VENCIDO","VIGENTE") -> VENCIDO
G116: =IF(H116>0,10,0) -> 0 | I116: 30 | J116: =+'Dis R'!$H116+'Dis R'!$I116 -> 30 | K116: ='Dis R'!$H116+'Dis R'!$I116-TODAY() -> -45566 | L116: =IF(K116<1,"VENCIDO","VIGENTE") -> VENCIDO
G117: =IF(H117>0,10,0) -> 0 | I117: 30 | J117: =+'Dis R'!$H117+'Dis R'!$I117 -> 30 | K117: ='Dis R'!$H117+'Dis R'!$I117-TODAY() -> -45566 | L117: =IF(K117<1,"VENCIDO","VIGENTE") -> VENCIDO
G118: =IF(H118>0,10,0) -> 0 | I118: 30 | J118: =+'Dis R'!$H118+'Dis R'!$I118 -> 30 | K118: ='Dis R'!$H118+'Dis R'!$I118-TODAY() -> -45566 | L118: =IF(K118<1,"VENCIDO","VIGENTE") -> VENCIDO
G119: =IF(H119>0,10,0) -> 0 | I119: 30 | J119: =+'Dis R'!$H119+'Dis R'!$I119 -> 30 | K119: ='Dis R'!$H119+'Dis R'!$I119-TODAY() -> -45566 | L119: =IF(K119<1,"VENCIDO","VIGENTE") -> VENCIDO
G120: =IF(H120>0,10,0) -> 0 | I120: 30 | J120: =+'Dis R'!$H120+'Dis R'!$I120 -> 30 | K120: ='Dis R'!$H120+'Dis R'!$I120-TODAY() -> -45566 | L120: =IF(K120<1,"VENCIDO","VIGENTE") -> VENCIDO
G121: =IF(H121>0,10,0) -> 0 | I121: 30 | J121: =+'Dis R'!$H121+'Dis R'!$I121 -> 30 | K121: ='Dis R'!$H121+'Dis R'!$I121-TODAY() -> -45566 | L121: =IF(K121<1,"VENCIDO","VIGENTE") -> VENCIDO
G122: =IF(H122>0,10,0) -> 0 | I122: 30 | J122: =+'Dis R'!$H122+'Dis R'!$I122 -> 30 | K122: ='Dis R'!$H122+'Dis R'!$I122-TODAY() -> -45566 | L122: =IF(K122<1,"VENCIDO","VIGENTE") -> VENCIDO
G123: =IF(H123>0,10,0) -> 0 | I123: 30 | J123: =+'Dis R'!$H123+'Dis R'!$I123 -> 30 | K123: ='Dis R'!$H123+'Dis R'!$I123-TODAY() -> -45566 | L123: =IF(K123<1,"VENCIDO","VIGENTE") -> VENCIDO
G124: =IF(H124>0,10,0) -> 0 | I124: 30 | J124: =+'Dis R'!$H124+'Dis R'!$I124 -> 30 | K124: ='Dis R'!$H124+'Dis R'!$I124-TODAY() -> -45566 | L124: =IF(K124<1,"VENCIDO","VIGENTE") -> VENCIDO
G125: =IF(H125>0,10,0) -> 0 | I125: 30 | J125: =+'Dis R'!$H125+'Dis R'!$I125 -> 30 | K125: ='Dis R'!$H125+'Dis R'!$I125-TODAY() -> -45566 | L125: =IF(K125<1,"VENCIDO","VIGENTE") -> VENCIDO
G126: =SUM(G113:G125) -> 0
...

Sheet Com R
B5: Hector
B6: =TODAY() -> 45596
B7: CUENTA | C7: Contraseña | D7: CLAVE | E7: Facturacion | F7: PIN PERFIL | G7: PRECIO | H7: FECHA DE INICIO | I7: DIAS | J7: FECHA DE VENCIMIENTO | K7: ALARMA | L7: ESTADO
C8: vwh9yEe5tX | G8: =IF(H8>0,17,0) -> 0 | I8: 30 | J8: =+'Com R'!$H8+'Com R'!$I8 -> 30 | K8: ='Com R'!$H8+'Com R'!$I8-TODAY() -> -45566 | L8: =IF(K8<1,"VENCIDO","VIGENTE") -> VENCIDO
G9: =IF(H9>0,17,0) -> 0 | I9: 30 | J9: =+'Com R'!$H9+'Com R'!$I9 -> 30 | K9: ='Com R'!$H9+'Com R'!$I9-TODAY() -> -45566 | L9: =IF(K9<1,"VENCIDO","VIGENTE") -> VENCIDO
G10: =IF(H10>0,17,0) -> 0 | I10: 30 | J10: =+'Com R'!$H10+'Com R'!$I10 -> 30 | K10: ='Com R'!$H10+'Com R'!$I10-TODAY() -> -45566 | L10: =IF(K10<1,"VENCIDO","VIGENTE") -> VENCIDO
G11: =IF(H11>0,17,0) -> 0 | I11: 30 | J11: =+'Com R'!$H11+'Com R'!$I11 -> 30 | K11: ='Com R'!$H11+'Com R'!$I11-TODAY() -> -45566 | L11: =IF(K11<1,"VENCIDO","VIGENTE") -> VENCIDO
G12: =IF(H12>0,17,0) -> 0 | I12: 30 | J12: =+'Com R'!$H12+'Com R'!$I12 -> 30 | K12: ='Com R'!$H12+'Com R'!$I12-TODAY() -> -45566 | L12: =IF(K12<1,"VENCIDO","VIGENTE") -> VENCIDO
G13: =IF(H13>0,17,0) -> 0 | I13: 30 | J13: =+'Com R'!$H13+'Com R'!$I13 -> 30 | K13: ='Com R'!$H13+'Com R'!$I13-TODAY() -> -45566 | L13: =IF(K13<1,"VENCIDO","VIGENTE") -> VENCIDO
G14: =IF(H14>0,17,0) -> 0 | I14: 30 | J14: =+'Com R'!$H14+'Com R'!$I14 -> 30 | K14: ='Com R'!$H14+'Com R'!$I14-TODAY() -> -45566 | L14: =IF(K14<1,"VENCIDO","VIGENTE") -> VENCIDO
G15: =IF(H15>0,17,0) -> 0 | I15: 30 | J15: =+'Com R'!$H15+'Com R'!$I15 -> 30 | K15: ='Com R'!$H15+'Com R'!$I15-TODAY() -> -45566 | L15: =IF(K15<1,"VENCIDO","VIGENTE") -> VENCIDO
G16: =IF(H16>0,17,0) -> 0 | I16: 30 | J16: =+'Com R'!$H16+'Com R'!$I16 -> 30 | K16: ='Com R'!$H16+'Com R'!$I16-TODAY() -> -45566 | L16: =IF(K16<1,"VENCIDO","VIGENTE") -> VENCIDO
G17: =IF(H17>0,17,0) -> 0 | I17: 30 | J17: =+'Com R'!$H17+'Com R'!$I17 -> 30 | K17: ='Com R'!$H17+'Com R'!$I17-TODAY() -> -45566 | L17: =IF(K17<1,"VENCIDO","VIGENTE") -> VENCIDO
G18: =IF(H18>0,17,0) -> 0 | I18: 30 | J18: =+'Com R'!$H18+'Com R'!$I18 -> 30 | K18: ='Com R'!$H18+'Com R'!$I18-TODAY() -> -45566 | L18: =IF(K18<1,"VENCIDO","VIGENTE") -> VENCIDO
G19: =IF(H19>0,17,0) -> 0 | I19: 30 | J19: =+'Com R'!$H19+'Com R'!$I19 -> 30 | K19: ='Com R'!$H19+'Com R'!$I19-TODAY() -> -45566 | L19: =IF(K19<1,"VENCIDO","VIGENTE") -> VENCIDO
G20: =IF(H20>0,17,0) -> 0 | I20: 30 | J20: =+'Com R'!$H20+'Com R'!$I20 -> 30 | K20: ='Com R'!$H20+'Com R'!$I20-TODAY() -> -45566 | L20: =IF(K20<1,"VENCIDO","VIGENTE") -> VENCIDO
G21: =SUM(G8:G20) -> 0
B26: Jhosut
B27: =TODAY() -> 45596
B28: CUENTA | C28: Contraseña | D28: CLAVE | E28: Facturacion | F28: PIN PERFIL | G28: PRECIO | H28: FECHA DE INICIO | I28: DIAS | J28: FECHA DE VENCIMIENTO | K28: ALARMA | L28: ESTADO
G29: =IF(H29>0,17,0) -> 0 | I29: 30 | J29: =+'Com R'!$H29+'Com R'!$I29 -> 30 | K29: ='Com R'!$H29+'Com R'!$I29-TODAY() -> -45566 | L29: =IF(K29<1,"VENCIDO","VIGENTE") -> VENCIDO
G30: =IF(H30>0,17,0) -> 0 | I30: 30 | J30: =+'Com R'!$H30+'Com R'!$I30 -> 30 | K30: ='Com R'!$H30+'Com R'!$I30-TODAY() -> -45566 | L30: =IF(K30<1,"VENCIDO","VIGENTE") -> VENCIDO
G31: =IF(H31>0,17,0) -> 0 | I31: 30 | J31: =+'Com R'!$H31+'Com R'!$I31 -> 30 | K31: ='Com R'!$H31+'Com R'!$I31-TODAY() -> -45566 | L31: =IF(K31<1,"VENCIDO","VIGENTE") -> VENCIDO
G32: =IF(H32>0,17,0) -> 0 | I32: 30 | J32: =+'Com R'!$H32+'Com R'!$I32 -> 30 | K32: ='Com R'!$H32+'Com R'!$I32-TODAY() -> -45566 | L32: =IF(K32<1,"VENCIDO","VIGENTE") -> VENCIDO
G33: =IF(H33>0,17,0) -> 0 | I33: 30 | J33: =+'Com R'!$H33+'Com R'!$I33 -> 30 | K33: ='Com R'!$H33+'Com R'!$I33-TODAY() -> -45566 | L33: =IF(K33<1,"VENCIDO","VIGENTE") -> VENCIDO
G34: =IF(H34>0,17,0) -> 0 | I34: 30 | J34: =+'Com R'!$H34+'Com R'!$I34 -> 30 | K34: ='Com R'!$H34+'Com R'!$I34-TODAY() -> -45566 | L34: =IF(K34<1,"VENCIDO","VIGENTE") -> VENCIDO
G35: =IF(H35>0,17,0) -> 0 | I35: 30 | J35: =+'Com R'!$H35+'Com R'!$I35 -> 30 | K35: ='Com R'!$H35+'Com R'!$I35-TODAY() -> -45566 | L35: =IF(K35<1,"VENCIDO","VIGENTE") -> VENCIDO
G36: =IF(H36>0,17,0) -> 0 | I36: 30 | J36: =+'Com R'!$H36+'Com R'!$I36 -> 30 | K36: ='Com R'!$H36+'Com R'!$I36-TODAY() -> -45566 | L36: =IF(K36<1,"VENCIDO","VIGENTE") -> VENCIDO
G37: =IF(H37>0,17,0) -> 0 | I37: 30 | J37: =+'Com R'!$H37+'Com R'!$I37 -> 30 | K37: ='Com R'!$H37+'Com R'!$I37-TODAY() -> -45566 | L37: =IF(K37<1,"VENCIDO","VIGENTE") -> VENCIDO
G38: =IF(H38>0,17,0) -> 0 | I38: 30 | J38: =+'Com R'!$H38+'Com R'!$I38 -> 30 | K38: ='Com R'!$H38+'Com R'!$I38-TODAY() -> -45566 | L38: =IF(K38<1,"VENCIDO","VIGENTE") -> VENCIDO
G39: =IF(H39>0,17,0) -> 0 | I39: 30 | J39: =+'Com R'!$H39+'Com R'!$I39 -> 30 | K39: ='Com R'!$H39+'Com R'!$I39-TODAY() -> -45566 | L39: =IF(K39<1,"VENCIDO","VIGENTE") -> VENCIDO
G40: =IF(H40>0,17,0) -> 0 | I40: 30 | J40: =+'Com R'!$H40+'Com R'!$I40 -> 30 | K40: ='Com R'!$H40+'Com R'!$I40-TODAY() -> -45566 | L40: =IF(K40<1,"VENCIDO","VIGENTE") -> VENCIDO
G41: =IF(H41>0,17,0) -> 0 | I41: 30 | J41: =+'Com R'!$H41+'Com R'!$I41 -> 30 | K41: ='Com R'!$H41+'Com R'!$I41-TODAY() -> -45566 | L41: =IF(K41<1,"VENCIDO","VIGENTE") -> VENCIDO
G42: =SUM(G29:G41) -> 0
B48: =TODAY() -> 45596
B49: CUENTA | C49: Contraseña | D49: CLAVE | E49: Facturacion | F49: PIN PERFIL | G49: PRECIO | H49: FECHA DE INICIO | I49: DIAS | J49: FECHA DE VENCIMIENTO | K49: ALARMA | L49: ESTADO
G50: =IF(H50>0,17,0) -> 0 | I50: 30 | J50: =+'Com R'!$H50+'Com R'!$I50 -> 30 | K50: ='Com R'!$H50+'Com R'!$I50-TODAY() -> -45566 | L50: =IF(K50<1,"VENCIDO","VIGENTE") -> VENCIDO
G51: =IF(H51>0,17,0) -> 0 | I51: 30 | J51: =+'Com R'!$H51+'Com R'!$I51 -> 30 | K51: ='Com R'!$H51+'Com R'!$I51-TODAY() -> -45566 | L51: =IF(K51<1,"VENCIDO","VIGENTE") -> VENCIDO
G52: =IF(H52>0,17,0) -> 0 | I52: 30 | J52: =+'Com R'!$H52+'Com R'!$I52 -> 30 | K52: ='Com R'!$H52+'Com R'!$I52-TODAY() -> -45566 | L52: =IF(K52<1,"VENCIDO","VIGENTE") -> VENCIDO
G53: =IF(H53>0,17,0) -> 0 | I53: 30 | J53: =+'Com R'!$H53+'Com R'!$I53 -> 30 | K53: ='Com R'!$H53+'Com R'!$I53-TODAY() -> -45566 | L53: =IF(K53<1,"VENCIDO","VIGENTE") -> VENCIDO
G54: =IF(H54>0,17,0) -> 0 | I54: 30 | J54: =+'Com R'!$H54+'Com R'!$I54 -> 30 | K54: ='Com R'!$H54+'Com R'!$I54-TODAY() -> -45566 | L54: =IF(K54<1,"VENCIDO","VIGENTE") -> VENCIDO
G55: =IF(H55>0,17,0) -> 0 | I55: 30 | J55: =+'Com R'!$H55+'Com R'!$I55 -> 30 | K55: ='Com R'!$H55+'Com R'!$I55-TODAY() -> -45566 | L55: =IF(K55<1,"VENCIDO","VIGENTE") -> VENCIDO
G56: =IF(H56>0,17,0) -> 0 | I56: 30 | J56: =+'Com R'!$H56+'Com R'!$I56 -> 30 | K56: ='Com R'!$H56+'Com R'!$I56-TODAY() -> -45566 | L56: =IF(K56<1,"VENCIDO","VIGENTE") -> VENCIDO
G57: =IF(H57>0,17,0) -> 0 | I57: 30 | J57: =+'Com R'!$H57+'Com R'!$I57 -> 30 | K57: ='Com R'!$H57+'Com R'!$I57-TODAY() -> -45566 | L57: =IF(K57<1,"VENCIDO","VIGENTE") -> VENCIDO
G58: =IF(H58>0,17,0) -> 0 | I58: 30 | J58: =+'Com R'!$H58+'Com R'!$I58 -> 30 | K58: ='Com R'!$H58+'Com R'!$I58-TODAY() -> -45566 | L58: =IF(K58<1,"VENCIDO","VIGENTE") -> VENCIDO
G59: =IF(H59>0,17,0) -> 0 | I59: 30 | J59: =+'Com R'!$H59+'Com R'!$I59 -> 30 | K59: ='Com R'!$H59+'Com R'!$I59-TODAY() -> -45566 | L59: =IF(K59<1,"VENCIDO","VIGENTE") -> VENCIDO
G60: =IF(H60>0,17,0) -> 0 | I60: 30 | J60: =+'Com R'!$H60+'Com R'!$I60 -> 30 | K60: ='Com R'!$H60+'Com R'!$I60-TODAY() -> -45566 | L60: =IF(K60<1,"VENCIDO","VIGENTE") -> VENCIDO
G61: =IF(H61>0,17,0) -> 0 | I61: 30 | J61: =+'Com R'!$H61+'Com R'!$I61 -> 30 | K61: ='Com R'!$H61+'Com R'!$I61-TODAY() -> -45566 | L61: =IF(K61<1,"VENCIDO","VIGENTE") -> VENCIDO
G62: =IF(H62>0,17,0) -> 0 | I62: 30 | J62: =+'Com R'!$H62+'Com R'!$I62 -> 30 | K62: ='Com R'!$H62+'Com R'!$I62-TODAY() -> -45566 | L62: =IF(K62<1,"VENCIDO","VIGENTE") -> VENCIDO
G63: =SUM(G50:G62) -> 0
B68: Jose Luis
B69: =TODAY() -> 45596
B70: CUENTA | C70: Contraseña | D70: CLAVE | E70: Facturacion | F70: PIN PERFIL | G70: PRECIO | H70: FECHA DE INICIO | I70: DIAS | J70: FECHA DE VENCIMIENTO | K70: ALARMA | L70: ESTADO
G71: =IF(H71>0,17,0) -> 0 | I71: 30 | J71: =+'Com R'!$H71+'Com R'!$I71 -> 30 | K71: ='Com R'!$H71+'Com R'!$I71-TODAY() -> -45566 | L71: =IF(K71<1,"VENCIDO","VIGENTE") -> VENCIDO
G72: =IF(H72>0,17,0) -> 0 | I72: 30 | J72: =+'Com R'!$H72+'Com R'!$I72 -> 30 | K72: ='Com R'!$H72+'Com R'!$I72-TODAY() -> -45566 | L72: =IF(K72<1,"VENCIDO","VIGENTE") -> VENCIDO
G73: =IF(H73>0,17,0) -> 0 | I73: 30 | J73: =+'Com R'!$H73+'Com R'!$I73 -> 30 | K73: ='Com R'!$H73+'Com R'!$I73-TODAY() -> -45566 | L73: =IF(K73<1,"VENCIDO","VIGENTE") -> VENCIDO
G74: =IF(H74>0,17,0) -> 0 | I74: 30 | J74: =+'Com R'!$H74+'Com R'!$I74 -> 30 | K74: ='Com R'!$H74+'Com R'!$I74-TODAY() -> -45566 | L74: =IF(K74<1,"VENCIDO","VIGENTE") -> VENCIDO
G75: =IF(H75>0,17,0) -> 0 | I75: 30 | J75: =+'Com R'!$H75+'Com R'!$I75 -> 30 | K75: ='Com R'!$H75+'Com R'!$I75-TODAY() -> -45566 | L75: =IF(K75<1,"VENCIDO","VIGENTE") -> VENCIDO
G76: =IF(H76>0,17,0) -> 0 | I76: 30 | J76: =+'Com R'!$H76+'Com R'!$I76 -> 30 | K76: ='Com R'!$H76+'Com R'!$I76-TODAY() -> -45566 | L76: =IF(K76<1,"VENCIDO","VIGENTE") -> VENCIDO
G77: =IF(H77>0,17,0) -> 0 | I77: 30 | J77: =+'Com R'!$H77+'Com R'!$I77 -> 30 | K77: ='Com R'!$H77+'Com R'!$I77-TODAY() -> -45566 | L77: =IF(K77<1,"VENCIDO","VIGENTE") -> VENCIDO
G78: =IF(H78>0,17,0) -> 0 | I78: 30 | J78: =+'Com R'!$H78+'Com R'!$I78 -> 30 | K78: ='Com R'!$H78+'Com R'!$I78-TODAY() -> -45566 | L78: =IF(K78<1,"VENCIDO","VIGENTE") -> VENCIDO
G79: =IF(H79>0,17,0) -> 0 | I79: 30 | J79: =+'Com R'!$H79+'Com R'!$I79 -> 30 | K79: ='Com R'!$H79+'Com R'!$I79-TODAY() -> -45566 | L79: =IF(K79<1,"VENCIDO","VIGENTE") -> VENCIDO
G80: =IF(H80>0,17,0) -> 0 | I80: 30 | J80: =+'Com R'!$H80+'Com R'!$I80 -> 30 | K80: ='Com R'!$H80+'Com R'!$I80-TODAY() -> -45566 | L80: =IF(K80<1,"VENCIDO","VIGENTE") -> VENCIDO
G81: =IF(H81>0,17,0) -> 0 | I81: 30 | J81: =+'Com R'!$H81+'Com R'!$I81 -> 30 | K81: ='Com R'!$H81+'Com R'!$I81-TODAY() -> -45566 | L81: =IF(K81<1,"VENCIDO","VIGENTE") -> VENCIDO
G82: =IF(H82>0,17,0) -> 0 | I82: 30 | J82: =+'Com R'!$H82+'Com R'!$I82 -> 30 | K82: ='Com R'!$H82+'Com R'!$I82-TODAY() -> -45566 | L82: =IF(K82<1,"VENCIDO","VIGENTE") -> VENCIDO
G83: =IF(H83>0,17,0) -> 0 | I83: 30 | J83: =+'Com R'!$H83+'Com R'!$I83 -> 30 | K83: ='Com R'!$H83+'Com R'!$I83-TODAY() -> -45566 | L83: =IF(K83<1,"VENCIDO","VIGENTE") -> VENCIDO
G84: =SUM(G71:G83) -> 0
B90: =TODAY() -> 45596
B91: CUENTA | C91: Contraseña | D91: CLAVE | E91: Facturacion | F91: PIN PERFIL | G91: PRECIO | H91: FECHA DE INICIO | I91: DIAS | J91: FECHA DE VENCIMIENTO | K91: ALARMA | L91: ESTADO
G92: =IF(H92>0,17,0) -> 0 | I92: 30 | J92: =+'Com R'!$H92+'Com R'!$I92 -> 30 | K92: ='Com R'!$H92+'Com R'!$I92-TODAY() -> -45566 | L92: =IF(K92<1,"VENCIDO","VIGENTE") -> VENCIDO
G93: =IF(H93>0,17,0) -> 0 | I93: 30 | J93: =+'Com R'!$H93+'Com R'!$I93 -> 30 | K93: ='Com R'!$H93+'Com R'!$I93-TODAY() -> -45566 | L93: =IF(K93<1,"VENCIDO","VIGENTE") -> VENCIDO
G94: =IF(H94>0,17,0) -> 0 | I94: 30 | J94: =+'Com R'!$H94+'Com R'!$I94 -> 30 | K94: ='Com R'!$H94+'Com R'!$I94-TODAY() -> -45566 | L94: =IF(K94<1,"VENCIDO","VIGENTE") -> VENCIDO
G95: =IF(H95>0,17,0) -> 0 | I95: 30 | J95: =+'Com R'!$H95+'Com R'!$I95 -> 30 | K95: ='Com R'!$H95+'Com R'!$I95-TODAY() -> -45566 | L95: =IF(K95<1,"VENCIDO","VIGENTE") -> VENCIDO
G96: =IF(H96>0,17,0) -> 0 | I96: 30 | J96: =+'Com R'!$H96+'Com R'!$I96 -> 30 | K96: ='Com R'!$H96+'Com R'!$I96-TODAY() -> -45566 | L96: =IF(K96<1,"VENCIDO","VIGENTE") -> VENCIDO
G97: =IF(H97>0,17,0) -> 0 | I97: 30 | J97: =+'Com R'!$H97+'Com R'!$I97 -> 30 | K97: ='Com R'!$H97+'Com R'!$I97-TODAY() -> -45566 | L97: =IF(K97<1,"VENCIDO","VIGENTE") -> VENCIDO
G98: =IF(H98>0,17,0) -> 0 | I98: 30 | J98: =+'Com R'!$H98+'Com R'!$I98 -> 30 | K98: ='Com R'!$H98+'Com R'!$I98-TODAY() -> -45566 | L98: =IF(K98<1,"VENCIDO","VIGENTE") -> VENCIDO
G99: =IF(H99>0,17,0) -> 0 | I99: 30 | J99: =+'Com R'!$H99+'Com R'!$I99 -> 30 | K99: ='Com R'!$H99+'Com R'!$I99-TODAY() -> -45566 | L99: =IF(K99<1,"VENCIDO","VIGENTE") -> VENCIDO
G100: =IF(H100>0,17,0) -> 0 | I100: 30 | J100: =+'Com R'!$H100+'Com R'!$I100 -> 30 | K100: ='Com R'!$H100+'Com R'!$I100-TODAY() -> -45566 | L100: =IF(K100<1,"VENCIDO","VIGENTE") -> VENCIDO
G101: =IF(H101>0,17,0) -> 0 | I101: 30 | J101: =+'Com R'!$H101+'Com R'!$I101 -> 30 | K101: ='Com R'!$H101+'Com R'!$I101-TODAY() -> -45566 | L101: =IF(K101<1,"VENCIDO","VIGENTE") -> VENCIDO
G102: =IF(H102>0,17,0) -> 0 | I102: 30 | J102: =+'Com R'!$H102+'Com R'!$I102 -> 30 | K102: ='Com R'!$H102+'Com R'!$I102-TODAY() -> -45566 | L102: =IF(K102<1,"VENCIDO","VIGENTE") -> VENCIDO
G103: =IF(H103>0,17,0) -> 0 | I103: 30 | J103: =+'Com R'!$H103+'Com R'!$I103 -> 30 | K103: ='Com R'!$H103+'Com R'!$I103-TODAY() -> -45566 | L103: =IF(K103<1,"VENCIDO","VIGENTE") -> VENCIDO
G104: =IF(H104>0,17,0) -> 0 | I104: 30 | J104: =+'Com R'!$H104+'Com R'!$I104 -> 30 | K104: ='Com R'!$H104+'Com R'!$I104-TODAY() -> -45566 | L104: =IF(K104<1,"VENCIDO","VIGENTE") -> VENCIDO
G105: =SUM(G92:G104) -> 0
B111: =TODAY() -> 45596
B112: CUENTA | C112: Contraseña | D112: CLAVE | E112: Facturacion | F112: PIN PERFIL | G112: PRECIO | H112: FECHA DE INICIO | I112: DIAS | J112: FECHA DE VENCIMIENTO | K112: ALARMA | L112: ESTADO
G113: =IF(H113>0,17,0) -> 0 | I113: 30 | J113: =+'Com R'!$H113+'Com R'!$I113 -> 30 | K113: ='Com R'!$H113+'Com R'!$I113-TODAY() -> -45566 | L113: =IF(K113<1,"VENCIDO","VIGENTE") -> VENCIDO
G114: =IF(H114>0,17,0) -> 0 | I114: 30 | J114: =+'Com R'!$H114+'Com R'!$I114 -> 30 | K114: ='Com R'!$H114+'Com R'!$I114-TODAY() -> -45566 | L114: =IF(K114<1,"VENCIDO","VIGENTE") -> VENCIDO
G115: =IF(H115>0,17,0) -> 0 | I115: 30 | J115: =+'Com R'!$H115+'Com R'!$I115 -> 30 | K115: ='Com R'!$H115+'Com R'!$I115-TODAY() -> -45566 | L115: =IF(K115<1,"VENCIDO","VIGENTE") -> VENCIDO
G116: =IF(H116>0,17,0) -> 0 | I116: 30 | J116: =+'Com R'!$H116+'Com R'!$I116 -> 30 | K116: ='Com R'!$H116+'Com R'!$I116-TODAY() -> -45566 | L116: =IF(K116<1,"VENCIDO","VIGENTE") -> VENCIDO
G117: =IF(H117>0,17,0) -> 0 | I117: 30 | J117: =+'Com R'!$H117+'Com R'!$I117 -> 30 | K117: ='Com R'!$H117+'Com R'!$I117-TODAY() -> -45566 | L117: =IF(K117<1,"VENCIDO","VIGENTE") -> VENCIDO
G118: =IF(H118>0,17,0) -> 0 | I118: 30 | J118: =+'Com R'!$H118+'Com R'!$I118 -> 30 | K118: ='Com R'!$H118+'Com R'!$I118-TODAY() -> -45566 | L118: =IF(K118<1,"VENCIDO","VIGENTE") -> VENCIDO
G119: =IF(H119>0,17,0) -> 0 | I119: 30 | J119: =+'Com R'!$H119+'Com R'!$I119 -> 30 | K119: ='Com R'!$H119+'Com R'!$I119-TODAY() -> -45566 | L119: =IF(K119<1,"VENCIDO","VIGENTE") -> VENCIDO
G120: =IF(H120>0,17,0) -> 0 | I120: 30 | J120: =+'Com R'!$H120+'Com R'!$I120 -> 30 | K120: ='Com R'!$H120+'Com R'!$I120-TODAY() -> -45566 | L120: =IF(K120<1,"VENCIDO","VIGENTE") -> VENCIDO
G121: =IF(H121>0,17,0) -> 0 | I121: 30 | J121: =+'Com R'!$H121+'Com R'!$I121 -> 30 | K121: ='Com R'!$H121+'Com R'!$I121-TODAY() -> -45566 | L121: =IF(K121<1,"VENCIDO","VIGENTE") -> VENCIDO
G122: =IF(H122>0,17,0) -> 0 | I122: 30 | J122: =+'Com R'!$H122+'Com R'!$I122 -> 30 | K122: ='Com R'!$H122+'Com R'!$I122-TODAY() -> -45566 | L122: =IF(K122<1,"VENCIDO","VIGENTE") -> VENCIDO
G123: =IF(H123>0,17,0) -> 0 | I123: 30 | J123: =+'Com R'!$H123+'Com R'!$I123 -> 30 | K123: ='Com R'!$H123+'Com R'!$I123-TODAY() -> -45566 | L123: =IF(K123<1,"VENCIDO","VIGENTE") -> VENCIDO
G124: =IF(H124>0,17,0) -> 0 | I124: 30 | J124: =+'Com R'!$H124+'Com R'!$I124 -> 30 | K124: ='Com R'!$H124+'Com R'!$I124-TODAY() -> -45566 | L124: =IF(K124<1,"VENCIDO","VIGENTE") -> VENCIDO
G125: =IF(H125>0,17,0) -> 0 | I125: 30 | J125: =+'Com R'!$H125+'Com R'!$I125 -> 30 | K125: ='Com R'!$H125+'Com R'!$I125-TODAY() -> -45566 | L125: =IF(K125<1,"VENCIDO","VIGENTE") -> VENCIDO
G126: =SUM(G113:G125) -> 0
B131: Hector Fast Streaming
...

Sheet Com F
B5: ALERTA DIAS
B6: =TODAY() -> 45596
B7: CUENTA | C7: NOMBRE | D7: CLAVE | E7: TELEFONO | F7: PIN PERFIL | G7: PRECIO | H7: FECHA DE INICIO | I7: DIAS | J7: FECHA DE VENCIMIENTO | K7: ALARMA | L7: ESTADO
G8: =IF(H8>0,7,0) -> 0 | I8: 30 | J8: =+'Com F'!$H8+'Com F'!$I8 -> 30 | K8: ='Com F'!$H8+'Com F'!$I8-TODAY() -> -45566 | L8: =IF(K8<1,"VENCIDO","VIGENTE") -> VENCIDO
G9: =IF(H9>0,7,0) -> 0 | I9: 30 | J9: =+'Com F'!$H9+'Com F'!$I9 -> 30 | K9: ='Com F'!$H9+'Com F'!$I9-TODAY() -> -45566 | L9: =IF(K9<1,"VENCIDO","VIGENTE") -> VENCIDO
G10: =IF(H10>0,7,0) -> 0 | I10: 30 | J10: =+'Com F'!$H10+'Com F'!$I10 -> 30 | K10: ='Com F'!$H10+'Com F'!$I10-TODAY() -> -45566 | L10: =IF(K10<1,"VENCIDO","VIGENTE") -> VENCIDO
G11: =IF(H11>0,7,0) -> 0 | I11: 30 | J11: =+'Com F'!$H11+'Com F'!$I11 -> 30 | K11: ='Com F'!$H11+'Com F'!$I11-TODAY() -> -45566 | L11: =IF(K11<1,"VENCIDO","VIGENTE") -> VENCIDO
G12: =IF(H12>0,7,0) -> 0 | I12: 30 | J12: =+'Com F'!$H12+'Com F'!$I12 -> 30 | K12: ='Com F'!$H12+'Com F'!$I12-TODAY() -> -45566 | L12: =IF(K12<1,"VENCIDO","VIGENTE") -> VENCIDO
G13: =IF(H13>0,7,0) -> 0 | I13: 30 | J13: =+'Com F'!$H13+'Com F'!$I13 -> 30 | K13: ='Com F'!$H13+'Com F'!$I13-TODAY() -> -45566 | L13: =IF(K13<1,"VENCIDO","VIGENTE") -> VENCIDO
G14: =IF(H14>0,7,0) -> 0 | I14: 90 | J14: =+'Com F'!$H14+'Com F'!$I14 -> 90 | K14: ='Com F'!$H14+'Com F'!$I14-TODAY() -> -45506 | L14: =IF(K14<1,"VENCIDO","VIGENTE") -> VENCIDO
C15: PERFILES : | F15: =SUM(F8:F14) -> 0 | G15: =SUM(G8:G14) -> 0
B20: =TODAY() -> 45596
B21: CUENTA | C21: NOMBRE | D21: CLAVE | E21: TELEFONO | F21: PIN PERFIL | G21: PRECIO | H21: FECHA DE INICIO | I21: DIAS | J21: FECHA DE VENCIMIENTO | K21: ALARMA | L21: ESTADO
C22: Moisrs76 | D22: dek57ner77 | E22: 51 986 430 133 | F22: 2633 | G22: =IF(H22>0,9,0) -> 9 | H22: 45570 | I22: 30 | J22: =+'Com F'!$H22+'Com F'!$I22 -> 45600 | K22: ='Com F'!$H22+'Com F'!$I22-TODAY() -> 4 | L22: =IF(K22<1,"VENCIDO","VIGENTE") -> VIGENTE
G23: =IF(H23>0,7,0) -> 0 | I23: 30 | J23: =+'Com F'!$H23+'Com F'!$I23 -> 30 | K23: ='Com F'!$H23+'Com F'!$I23-TODAY() -> -45566 | L23: =IF(K23<1,"VENCIDO","VIGENTE") -> VENCIDO
G24: =IF(H24>0,7,0) -> 0 | I24: 30 | J24: =+'Com F'!$H24+'Com F'!$I24 -> 30 | K24: ='Com F'!$H24+'Com F'!$I24-TODAY() -> -45566 | L24: =IF(K24<1,"VENCIDO","VIGENTE") -> VENCIDO
G25: =IF(H25>0,7,0) -> 0 | I25: 30 | J25: =+'Com F'!$H25+'Com F'!$I25 -> 30 | K25: ='Com F'!$H25+'Com F'!$I25-TODAY() -> -45566 | L25: =IF(K25<1,"VENCIDO","VIGENTE") -> VENCIDO
G26: =IF(H26>0,7,0) -> 0 | I26: 30 | J26: =+'Com F'!$H26+'Com F'!$I26 -> 30 | K26: ='Com F'!$H26+'Com F'!$I26-TODAY() -> -45566 | L26: =IF(K26<1,"VENCIDO","VIGENTE") -> VENCIDO
G27: =IF(H27>0,7,0) -> 0 | I27: 30 | J27: =+'Com F'!$H27+'Com F'!$I27 -> 30 | K27: ='Com F'!$H27+'Com F'!$I27-TODAY() -> -45566 | L27: =IF(K27<1,"VENCIDO","VIGENTE") -> VENCIDO
G28: =IF(H28>0,7,0) -> 0 | I28: 90 | J28: =+'Com F'!$H28+'Com F'!$I28 -> 90 | K28: ='Com F'!$H28+'Com F'!$I28-TODAY() -> -45506 | L28: =IF(K28<1,"VENCIDO","VIGENTE") -> VENCIDO
C29: PERFILES : | F29: =SUM(F22:F28) -> 2633 | G29: =SUM(G22:G28) -> 9
B34: =TODAY() -> 45596
B35: CUENTA | C35: NOMBRE | D35: CLAVE | E35: TELEFONO | F35: PIN PERFIL | G35: PRECIO | H35: FECHA DE INICIO | I35: DIAS | J35: FECHA DE VENCIMIENTO | K35: ALARMA | L35: ESTADO
G36: =IF(H36>0,7,0) -> 0 | I36: 30 | J36: =+'Com F'!$H36+'Com F'!$I36 -> 30 | K36: ='Com F'!$H36+'Com F'!$I36-TODAY() -> -45566 | L36: =IF(K36<1,"VENCIDO","VIGENTE") -> VENCIDO
G37: =IF(H37>0,7,0) -> 0 | I37: 30 | J37: =+'Com F'!$H37+'Com F'!$I37 -> 30 | K37: ='Com F'!$H37+'Com F'!$I37-TODAY() -> -45566 | L37: =IF(K37<1,"VENCIDO","VIGENTE") -> VENCIDO
G38: =IF(H38>0,7,0) -> 0 | I38: 30 | J38: =+'Com F'!$H38+'Com F'!$I38 -> 30 | K38: ='Com F'!$H38+'Com F'!$I38-TODAY() -> -45566 | L38: =IF(K38<1,"VENCIDO","VIGENTE") -> VENCIDO
G39: =IF(H39>0,7,0) -> 0 | I39: 30 | J39: =+'Com F'!$H39+'Com F'!$I39 -> 30 | K39: ='Com F'!$H39+'Com F'!$I39-TODAY() -> -45566 | L39: =IF(K39<1,"VENCIDO","VIGENTE") -> VENCIDO
G40: =IF(H40>0,7,0) -> 0 | I40: 30 | J40: =+'Com F'!$H40+'Com F'!$I40 -> 30 | K40: ='Com F'!$H40+'Com F'!$I40-TODAY() -> -45566 | L40: =IF(K40<1,"VENCIDO","VIGENTE") -> VENCIDO
G41: =IF(H41>0,7,0) -> 0 | I41: 30 | J41: =+'Com F'!$H41+'Com F'!$I41 -> 30 | K41: ='Com F'!$H41+'Com F'!$I41-TODAY() -> -45566 | L41: =IF(K41<1,"VENCIDO","VIGENTE") -> VENCIDO
G42: =IF(H42>0,7,0) -> 0 | I42: 90 | J42: =+'Com F'!$H42+'Com F'!$I42 -> 90 | K42: ='Com F'!$H42+'Com F'!$I42-TODAY() -> -45506 | L42: =IF(K42<1,"VENCIDO","VIGENTE") -> VENCIDO
C43: PERFILES : | F43: =SUM(F36:F42) -> 0 | G43: =SUM(G36:G42) -> 0
B48: =TODAY() -> 45596
B49: CUENTA | C49: NOMBRE | D49: CLAVE | E49: TELEFONO | F49: PIN PERFIL | G49: PRECIO | H49: FECHA DE INICIO | I49: DIAS | J49: FECHA DE VENCIMIENTO | K49: ALARMA | L49: ESTADO
G50: =IF(H50>0,7,0) -> 0 | I50: 30 | J50: =+'Com F'!$H50+'Com F'!$I50 -> 30 | K50: ='Com F'!$H50+'Com F'!$I50-TODAY() -> -45566 | L50: =IF(K50<1,"VENCIDO","VIGENTE") -> VENCIDO
G51: =IF(H51>0,7,0) -> 0 | I51: 30 | J51: =+'Com F'!$H51+'Com F'!$I51 -> 30 | K51: ='Com F'!$H51+'Com F'!$I51-TODAY() -> -45566 | L51: =IF(K51<1,"VENCIDO","VIGENTE") -> VENCIDO
G52: =IF(H52>0,7,0) -> 0 | I52: 30 | J52: =+'Com F'!$H52+'Com F'!$I52 -> 30 | K52: ='Com F'!$H52+'Com F'!$I52-TODAY() -> -45566 | L52: =IF(K52<1,"VENCIDO","VIGENTE") -> VENCIDO
G53: =IF(H53>0,7,0) -> 0 | I53: 30 | J53: =+'Com F'!$H53+'Com F'!$I53 -> 30 | K53: ='Com F'!$H53+'Com F'!$I53-TODAY() -> -45566 | L53: =IF(K53<1,"VENCIDO","VIGENTE") -> VENCIDO
G54: =IF(H54>0,7,0) -> 0 | I54: 30 | J54: =+'Com F'!$H54+'Com F'!$I54 -> 30 | K54: ='Com F'!$H54+'Com F'!$I54-TODAY() -> -45566 | L54: =IF(K54<1,"VENCIDO","VIGENTE") -> VENCIDO
G55: =IF(H55>0,7,0) -> 0 | I55: 30 | J55: =+'Com F'!$H55+'Com F'!$I55 -> 30 | K55: ='Com F'!$H55+'Com F'!$I55-TODAY() -> -45566 | L55: =IF(K55<1,"VENCIDO","VIGENTE") -> VENCIDO
G56: =IF(H56>0,7,0) -> 0 | I56: 90 | J56: =+'Com F'!$H56+'Com F'!$I56 -> 90 | K56: ='Com F'!$H56+'Com F'!$I56-TODAY() -> -45506 | L56: =IF(K56<1,"VENCIDO","VIGENTE") -> VENCIDO
C57: PERFILES : | F57: =SUM(F50:F56) -> 0 | G57: =SUM(G50:G56) -> 0
B62: =TODAY() -> 45596
B63: CUENTA | C63: NOMBRE | D63: CLAVE | E63: TELEFONO | F63: PIN PERFIL | G63: PRECIO | H63: FECHA DE INICIO | I63: DIAS | J63: FECHA DE VENCIMIENTO | K63: ALARMA | L63: ESTADO
G64: =IF(H64>0,7,0) -> 0 | I64: 30 | J64: =+'Com F'!$H64+'Com F'!$I64 -> 30 | K64: ='Com F'!$H64+'Com F'!$I64-TODAY() -> -45566 | L64: =IF(K64<1,"VENCIDO","VIGENTE") -> VENCIDO
G65: =IF(H65>0,7,0) -> 0 | I65: 30 | J65: =+'Com F'!$H65+'Com F'!$I65 -> 30 | K65: ='Com F'!$H65+'Com F'!$I65-TODAY() -> -45566 | L65: =IF(K65<1,"VENCIDO","VIGENTE") -> VENCIDO
G66: =IF(H66>0,7,0) -> 0 | I66: 30 | J66: =+'Com F'!$H66+'Com F'!$I66 -> 30 | K66: ='Com F'!$H66+'Com F'!$I66-TODAY() -> -45566 | L66: =IF(K66<1,"VENCIDO","VIGENTE") -> VENCIDO
G67: =IF(H67>0,7,0) -> 0 | I67: 30 | J67: =+'Com F'!$H67+'Com F'!$I67 -> 30 | K67: ='Com F'!$H67+'Com F'!$I67-TODAY() -> -45566 | L67: =IF(K67<1,"VENCIDO","VIGENTE") -> VENCIDO
G68: =IF(H68>0,7,0) -> 0 | I68: 30 | J68: =+'Com F'!$H68+'Com F'!$I68 -> 30 | K68: ='Com F'!$H68+'Com F'!$I68-TODAY() -> -45566 | L68: =IF(K68<1,"VENCIDO","VIGENTE") -> VENCIDO
G69: =IF(H69>0,7,0) -> 0 | I69: 30 | J69: =+'Com F'!$H69+'Com F'!$I69 -> 30 | K69: ='Com F'!$H69+'Com F'!$I69-TODAY() -> -45566 | L69: =IF(K69<1,"VENCIDO","VIGENTE") -> VENCIDO
G70: =IF(H70>0,7,0) -> 0 | I70: 90 | J70: =+'Com F'!$H70+'Com F'!$I70 -> 90 | K70: ='Com F'!$H70+'Com F'!$I70-TODAY() -> -45506 | L70: =IF(K70<1,"VENCIDO","VIGENTE") -> VENCIDO
C71: PERFILES : | F71: =SUM(F64:F70) -> 0 | G71: =SUM(G64:G70) -> 0
B76: =TODAY() -> 45596
B77: CUENTA | C77: NOMBRE | D77: CLAVE | E77: TELEFONO | F77: PIN PERFIL | G77: PRECIO | H77: FECHA DE INICIO | I77: DIAS | J77: FECHA DE VENCIMIENTO | K77: ALARMA | L77: ESTADO
G78: =IF(H78>0,7,0) -> 0 | I78: 30 | J78: =+'Com F'!$H78+'Com F'!$I78 -> 30 | K78: ='Com F'!$H78+'Com F'!$I78-TODAY() -> -45566 | L78: =IF(K78<1,"VENCIDO","VIGENTE") -> VENCIDO
G79: =IF(H79>0,7,0) -> 0 | I79: 30 | J79: =+'Com F'!$H79+'Com F'!$I79 -> 30 | K79: ='Com F'!$H79+'Com F'!$I79-TODAY() -> -45566 | L79: =IF(K79<1,"VENCIDO","VIGENTE") -> VENCIDO
G80: =IF(H80>0,7,0) -> 0 | I80: 30 | J80: =+'Com F'!$H80+'Com F'!$I80 -> 30 | K80: ='Com F'!$H80+'Com F'!$I80-TODAY() -> -45566 | L80: =IF(K80<1,"VENCIDO","VIGENTE") -> VENCIDO
G81: =IF(H81>0,7,0) -> 0 | I81: 30 | J81: =+'Com F'!$H81+'Com F'!$I81 -> 30 | K81: ='Com F'!$H81+'Com F'!$I81-TODAY() -> -45566 | L81: =IF(K81<1,"VENCIDO","VIGENTE") -> VENCIDO
G82: =IF(H82>0,7,0) -> 0 | I82: 30 | J82: =+'Com F'!$H82+'Com F'!$I82 -> 30 | K82: ='Com F'!$H82+'Com F'!$I82-TODAY() -> -45566 | L82: =IF(K82<1,"VENCIDO","VIGENTE") -> VENCIDO
G83: =IF(H83>0,7,0) -> 0 | I83: 30 | J83: =+'Com F'!$H83+'Com F'!$I83 -> 30 | K83: ='Com F'!$H83+'Com F'!$I83-TODAY() -> -45566 | L83: =IF(K83<1,"VENCIDO","VIGENTE") -> VENCIDO
G84: =IF(H84>0,7,0) -> 0 | I84: 90 | J84: =+'Com F'!$H84+'Com F'!$I84 -> 90 | K84: ='Com F'!$H84+'Com F'!$I84-TODAY() -> -45506 | L84: =IF(K84<1,"VENCIDO","VIGENTE") -> VENCIDO
C85: PERFILES : | F85: =SUM(F78:F84) -> 0 | G85: =SUM(G78:G84) -> 0
B90: =TODAY() -> 45596
B91: CUENTA | C91: NOMBRE | D91: CLAVE | E91: TELEFONO | F91: PIN PERFIL | G91: PRECIO | H91: FECHA DE INICIO | I91: DIAS | J91: FECHA DE VENCIMIENTO | K91: ALARMA | L91: ESTADO
G92: =IF(H92>0,7,0) -> 0 | I92: 30 | J92: =+'Com F'!$H92+'Com F'!$I92 -> 30 | K92: ='Com F'!$H92+'Com F'!$I92-TODAY() -> -45566 | L92: =IF(K92<1,"VENCIDO","VIGENTE") -> VENCIDO
G93: =IF(H93>0,7,0) -> 0 | I93: 30 | J93: =+'Com F'!$H93+'Com F'!$I93 -> 30 | K93: ='Com F'!$H93+'Com F'!$I93-TODAY() -> -45566 | L93: =IF(K93<1,"VENCIDO","VIGENTE") -> VENCIDO
G94: =IF(H94>0,7,0) -> 0 | I94: 30 | J94: =+'Com F'!$H94+'Com F'!$I94 -> 30 | K94: ='Com F'!$H94+'Com F'!$I94-TODAY() -> -45566 | L94: =IF(K94<1,"VENCIDO","VIGENTE") -> VENCIDO
G95: =IF(H95>0,7,0) -> 0 | I95: 30 | J95: =+'Com F'!$H95+'Com F'!$I95 -> 30 | K95: ='Com F'!$H95+'Com F'!$I95-TODAY() -> -45566 | L95: =IF(K95<1,"VENCIDO","VIGENTE") -> VENCIDO
G96: =IF(H96>0,7,0) -> 0 | I96: 30 | J96: =+'Com F'!$H96+'Com F'!$I96 -> 30 | K96: ='Com F'!$H96+'Com F'!$I96-TODAY() -> -45566 | L96: =IF(K96<1,"VENCIDO","VIGENTE") -> VENCIDO
G97: =IF(H97>0,7,0) -> 0 | I97: 30 | J97: =+'Com F'!$H97+'Com F'!$I97 -> 30 | K97: ='Com F'!$H97+'Com F'!$I97-TODAY() -> -45566 | L97: =IF(K97<1,"VENCIDO","VIGENTE") -> VENCIDO
G98: =IF(H98>0,7,0) -> 0 | I98: 90 | J98: =+'Com F'!$H98+'Com F'!$I98 -> 90 | K98: ='Com F'!$H98+'Com F'!$I98-TODAY() -> -45506 | L98: =IF(K98<1,"VENCIDO","VIGENTE") -> VENCIDO
C99: PERFILES : | F99: =SUM(F92:F98) -> 0 | G99: =SUM(G92:G98) -> 0
B104: =TODAY() -> 45596
B105: CUENTA | C105: NOMBRE | D105: CLAVE | E105: TELEFONO | F105: PIN PERFIL | G105: PRECIO | H105: FECHA DE INICIO | I105: DIAS | J105: FECHA DE VENCIMIENTO | K105: ALARMA | L105: ESTADO
G106: =IF(H106>0,7,0) -> 0 | I106: 30 | J106: =+'Com F'!$H106+'Com F'!$I106 -> 30 | K106: ='Com F'!$H106+'Com F'!$I106-TODAY() -> -45566 | L106: =IF(K106<1,"VENCIDO","VIGENTE") -> VENCIDO
G107: =IF(H107>0,7,0) -> 0 | I107: 30 | J107: =+'Com F'!$H107+'Com F'!$I107 -> 30 | K107: ='Com F'!$H107+'Com F'!$I107-TODAY() -> -45566 | L107: =IF(K107<1,"VENCIDO","VIGENTE") -> VENCIDO
G108: =IF(H108>0,7,0) -> 0 | I108: 30 | J108: =+'Com F'!$H108+'Com F'!$I108 -> 30 | K108: ='Com F'!$H108+'Com F'!$I108-TODAY() -> -45566 | L108: =IF(K108<1,"VENCIDO","VIGENTE") -> VENCIDO
G109: =IF(H109>0,7,0) -> 0 | I109: 30 | J109: =+'Com F'!$H109+'Com F'!$I109 -> 30 | K109: ='Com F'!$H109+'Com F'!$I109-TODAY() -> -45566 | L109: =IF(K109<1,"VENCIDO","VIGENTE") -> VENCIDO
G110: =IF(H110>0,7,0) -> 0 | I110: 30 | J110: =+'Com F'!$H110+'Com F'!$I110 -> 30 | K110: ='Com F'!$H110+'Com F'!$I110-TODAY() -> -45566 | L110: =IF(K110<1,"VENCIDO","VIGENTE") -> VENCIDO
G111: =IF(H111>0,7,0) -> 0 | I111: 30 | J111: =+'Com F'!$H111+'Com F'!$I111 -> 30 | K111: ='Com F'!$H111+'Com F'!$I111-TODAY() -> -45566 | L111: =IF(K111<1,"VENCIDO","VIGENTE") -> VENCIDO
G112: =IF(H112>0,7,0) -> 0 | I112: 90 | J112: =+'Com F'!$H112+'Com F'!$I112 -> 90 | K112: ='Com F'!$H112+'Com F'!$I112-TODAY() -> -45506 | L112: =IF(K112<1,"VENCIDO","VIGENTE") -> VENCIDO
C113: PERFILES : | F113: =SUM(F106:F112) -> 0 | G113: =SUM(G106:G112) -> 0

Sheet HBO F
B5: ALERTA DIAS
B6: =TODAY() -> 45596
B7: CUENTA | C7: NOMBRE | D7: CLAVE | E7: TELEFONO | F7: PIN PERFIL | G7: PRECIO | H7: FECHA DE INICIO | I7: DIAS | J7: FECHA DE VENCIMIENTO | K7: ALARMA | L7: ESTADO
B8: Correo: ctisfer465@gmail.com Contraseña: Dmer32deku | G8: =IF(H8>0,8,0) -> 0 | I8: 30 | J8: =+'HBO F'!$H8+'HBO F'!$I8 -> 30 | K8: ='HBO F'!$H8+'HBO F'!$I8-TODAY() -> -45566 | L8: =IF(K8<1,"VENCIDO","VIGENTE") -> VENCIDO
G9: =IF(H9>0,8,0) -> 0 | I9: 30 | J9: =+'HBO F'!$H9+'HBO F'!$I9 -> 30 | K9: ='HBO F'!$H9+'HBO F'!$I9-TODAY() -> -45566 | L9: =IF(K9<1,"VENCIDO","VIGENTE") -> VENCIDO
G10: =IF(H10>0,8,0) -> 0 | I10: 30 | J10: =+'HBO F'!$H10+'HBO F'!$I10 -> 30 | K10: ='HBO F'!$H10+'HBO F'!$I10-TODAY() -> -45566 | L10: =IF(K10<1,"VENCIDO","VIGENTE") -> VENCIDO
G11: =IF(H11>0,8,0) -> 0 | I11: 30 | J11: =+'HBO F'!$H11+'HBO F'!$I11 -> 30 | K11: ='HBO F'!$H11+'HBO F'!$I11-TODAY() -> -45566 | L11: =IF(K11<1,"VENCIDO","VIGENTE") -> VENCIDO
G12: =IF(H12>0,8,0) -> 0 | I12: 30 | J12: =+'HBO F'!$H12+'HBO F'!$I12 -> 30 | K12: ='HBO F'!$H12+'HBO F'!$I12-TODAY() -> -45566 | L12: =IF(K12<1,"VENCIDO","VIGENTE") -> VENCIDO
C13: PERFILES : | F13: =SUM(F8:F12) -> 0 | G13: =SUM(G8:G12) -> 0
B18: ALERTA DIAS | C18: Renovar
B19: =TODAY() -> 45596
B20: CUENTA | C20: NOMBRE | D20: CLAVE | E20: TELEFONO | F20: PIN PERFIL | G20: PRECIO | H20: FECHA DE INICIO | I20: DIAS | J20: FECHA DE VENCIMIENTO | K20: ALARMA | L20: ESTADO
B21: correo:filtroperu123+begrenzter@gmail.com contraseña_: campeonato99 | C21: Deereck92 | D21: campeonato99 | E21: 51 963 840 072 | F21: 9177 | G21: =IF(H21>0,5,0) -> 5 | H21: 45568 | I21: 30 | J21: =+'HBO F'!$H21+'HBO F'!$I21 -> 45598 | K21: ='HBO F'!$H21+'HBO F'!$I21-TODAY() -> 2 | L21: =IF(K21<1,"VENCIDO","VIGENTE") -> VIGENTE
C22: Remylag933 | E22: 51 926 665 678 | F22: 6333 | G22: =IF(H22>0,5,0) -> 5 | H22: 45565 | I22: 30 | J22: =+'HBO F'!$H22+'HBO F'!$I22 -> 45595 | K22: ='HBO F'!$H22+'HBO F'!$I22-TODAY() -> -1 | L22: =IF(K22<1,"VENCIDO","VIGENTE") -> VENCIDO
C23: Geraldine528 | E23: 51 946 579 911 | F23: 4288 | G23: =IF(H23>0,4,0) -> 4 | H23: 45543 | I23: 30 | J23: =+'HBO F'!$H23+'HBO F'!$I23 -> 45573 | K23: ='HBO F'!$H23+'HBO F'!$I23-TODAY() -> -23 | L23: =IF(K23<1,"VENCIDO","VIGENTE") -> VENCIDO
C24: Criss02 | E24: 51 946 579 911 | F24: 5534 | G24: =IF(H24>0,4,0) -> 4 | H24: 45536 | I24: 30 | J24: =+'HBO F'!$H24+'HBO F'!$I24 -> 45566 | K24: ='HBO F'!$H24+'HBO F'!$I24-TODAY() -> -30 | L24: =IF(K24<1,"VENCIDO","VIGENTE") -> VENCIDO
G25: =IF(H25>0,8,0) -> 0 | I25: 30 | J25: =+'HBO F'!$H25+'HBO F'!$I25 -> 30 | K25: ='HBO F'!$H25+'HBO F'!$I25-TODAY() -> -45566 | L25: =IF(K25<1,"VENCIDO","VIGENTE") -> VENCIDO
C26: PERFILES : | F26: =SUM(F21:F25) -> 25332 | G26: =SUM(G21:G25) -> 18
B31: ALERTA DIAS
B32: =TODAY() -> 45596
B33: CUENTA | C33: NOMBRE | D33: CLAVE | E33: TELEFONO | F33: PIN PERFIL | G33: PRECIO | H33: FECHA DE INICIO | I33: DIAS | J33: FECHA DE VENCIMIENTO | K33: ALARMA | L33: ESTADO
B34: Correo: lukcris961@gmail.com Contraseña: gerta54$ | G34: =IF(H34>0,8,0) -> 0 | I34: 30 | J34: =+'HBO F'!$H34+'HBO F'!$I34 -> 30 | K34: ='HBO F'!$H34+'HBO F'!$I34-TODAY() -> -45566 | L34: =IF(K34<1,"VENCIDO","VIGENTE") -> VENCIDO
G35: =IF(H35>0,8,0) -> 0 | I35: 30 | J35: =+'HBO F'!$H35+'HBO F'!$I35 -> 30 | K35: ='HBO F'!$H35+'HBO F'!$I35-TODAY() -> -45566 | L35: =IF(K35<1,"VENCIDO","VIGENTE") -> VENCIDO
G36: =IF(H36>0,8,0) -> 0 | I36: 60 | J36: =+'HBO F'!$H36+'HBO F'!$I36 -> 60 | K36: ='HBO F'!$H36+'HBO F'!$I36-TODAY() -> -45536 | L36: =IF(K36<1,"VENCIDO","VIGENTE") -> VENCIDO
G37: =IF(H37>0,8,0) -> 0 | I37: 180 | J37: =+'HBO F'!$H37+'HBO F'!$I37 -> 180 | K37: ='HBO F'!$H37+'HBO F'!$I37-TODAY() -> -45416 | L37: =IF(K37<1,"VENCIDO","VIGENTE") -> VENCIDO
G38: =IF(H38>0,8,0) -> 0 | I38: 30 | J38: =+'HBO F'!$H38+'HBO F'!$I38 -> 30 | K38: ='HBO F'!$H38+'HBO F'!$I38-TODAY() -> -45566 | L38: =IF(K38<1,"VENCIDO","VIGENTE") -> VENCIDO
C39: PERFILES : | F39: =SUM(F34:F38) -> 0 | G39: =SUM(G34:G38) -> 0
B44: ALERTA DIAS
B45: =TODAY() -> 45596
B46: CUENTA | C46: NOMBRE | D46: CLAVE | E46: TELEFONO | F46: PIN PERFIL | G46: PRECIO | H46: FECHA DE INICIO | I46: DIAS | J46: FECHA DE VENCIMIENTO | K46: ALARMA | L46: ESTADO
B47: Correo: servicioso02991@gmail.com Contraseña: cp1dekig | C47: diego9 | G47: 4.5 | H47: 45252 | I47: 30 | J47: =+'HBO F'!$H47+'HBO F'!$I47 -> 45282 | K47: ='HBO F'!$H47+'HBO F'!$I47-TODAY() -> -314 | L47: =IF(K47<1,"VENCIDO","VIGENTE") -> VENCIDO
C48: dany e | G48: 4.5 | H48: 45230 | I48: 30 | J48: =+'HBO F'!$H48+'HBO F'!$I48 -> 45260 | K48: ='HBO F'!$H48+'HBO F'!$I48-TODAY() -> -336 | L48: =IF(K48<1,"VENCIDO","VIGENTE") -> VENCIDO
C49: moises | G49: 4.5 | H49: 45232 | I49: 30 | J49: =+'HBO F'!$H49+'HBO F'!$I49 -> 45262 | K49: ='HBO F'!$H49+'HBO F'!$I49-TODAY() -> -334 | L49: =IF(K49<1,"VENCIDO","VIGENTE") -> VENCIDO
C50: miguel | G50: 4.5 | H50: 45211 | I50: 30 | J50: =+'HBO F'!$H50+'HBO F'!$I50 -> 45241 | K50: ='HBO F'!$H50+'HBO F'!$I50-TODAY() -> -355 | L50: =IF(K50<1,"VENCIDO","VIGENTE") -> VENCIDO
C51: noemi | G51: 4.5 | I51: 30 | J51: =+'HBO F'!$H51+'HBO F'!$I51 -> 30 | K51: ='HBO F'!$H51+'HBO F'!$I51-TODAY() -> -45566 | L51: =IF(K51<1,"VENCIDO","VIGENTE") -> VENCIDO
C52: PERFILES : | F52: =SUM(F47:F51) -> 0 | G52: =SUM(G47:G51) -> 22.5
B57: ALERTA DIAS
B58: =TODAY() -> 45596
B59: CUENTA | C59: NOMBRE | D59: CLAVE | E59: TELEFONO | F59: PIN PERFIL | G59: PRECIO | H59: FECHA DE INICIO | I59: DIAS | J59: FECHA DE VENCIMIENTO | K59: ALARMA | L59: ESTADO
B60: kills269@lownice.com | G60: =IF(H60>0,8,0) -> 0 | I60: 30 | J60: =+'HBO F'!$H60+'HBO F'!$I60 -> 30 | K60: ='HBO F'!$H60+'HBO F'!$I60-TODAY() -> -45566 | L60: =IF(K60<1,"VENCIDO","VIGENTE") -> VENCIDO
G61: =IF(H61>0,8,0) -> 0 | I61: 30 | J61: =+'HBO F'!$H61+'HBO F'!$I61 -> 30 | K61: ='HBO F'!$H61+'HBO F'!$I61-TODAY() -> -45566 | L61: =IF(K61<1,"VENCIDO","VIGENTE") -> VENCIDO
G62: =IF(H62>0,8,0) -> 0 | I62: 30 | J62: =+'HBO F'!$H62+'HBO F'!$I62 -> 30 | K62: ='HBO F'!$H62+'HBO F'!$I62-TODAY() -> -45566 | L62: =IF(K62<1,"VENCIDO","VIGENTE") -> VENCIDO
G63: =IF(H63>0,8,0) -> 0 | I63: 30 | J63: =+'HBO F'!$H63+'HBO F'!$I63 -> 30 | K63: ='HBO F'!$H63+'HBO F'!$I63-TODAY() -> -45566 | L63: =IF(K63<1,"VENCIDO","VIGENTE") -> VENCIDO
G64: =IF(H64>0,8,0) -> 0 | I64: 30 | J64: =+'HBO F'!$H64+'HBO F'!$I64 -> 30 | K64: ='HBO F'!$H64+'HBO F'!$I64-TODAY() -> -45566 | L64: =IF(K64<1,"VENCIDO","VIGENTE") -> VENCIDO
C65: PERFILES : | F65: =SUM(F60:F64) -> 0 | G65: =SUM(G60:G64) -> 0
B70: ALERTA DIAS
B71: =TODAY() -> 45596
B72: CUENTA | C72: NOMBRE | D72: CLAVE | E72: TELEFONO | F72: PIN PERFIL | G72: PRECIO | H72: FECHA DE INICIO | I72: DIAS | J72: FECHA DE VENCIMIENTO | K72: ALARMA | L72: ESTADO
G73: =IF(H73>0,8,0) -> 0 | I73: 30 | J73: =+'HBO F'!$H73+'HBO F'!$I73 -> 30 | K73: ='HBO F'!$H73+'HBO F'!$I73-TODAY() -> -45566 | L73: =IF(K73<1,"VENCIDO","VIGENTE") -> VENCIDO
G74: =IF(H74>0,8,0) -> 0 | I74: 30 | J74: =+'HBO F'!$H74+'HBO F'!$I74 -> 30 | K74: ='HBO F'!$H74+'HBO F'!$I74-TODAY() -> -45566 | L74: =IF(K74<1,"VENCIDO","VIGENTE") -> VENCIDO
G75: =IF(H75>0,8,0) -> 0 | I75: 30 | J75: =+'HBO F'!$H75+'HBO F'!$I75 -> 30 | K75: ='HBO F'!$H75+'HBO F'!$I75-TODAY() -> -45566 | L75: =IF(K75<1,"VENCIDO","VIGENTE") -> VENCIDO
G76: =IF(H76>0,8,0) -> 0 | I76: 30 | J76: =+'HBO F'!$H76+'HBO F'!$I76 -> 30 | K76: ='HBO F'!$H76+'HBO F'!$I76-TODAY() -> -45566 | L76: =IF(K76<1,"VENCIDO","VIGENTE") -> VENCIDO
G77: =IF(H77>0,8,0) -> 0 | I77: 30 | J77: =+'HBO F'!$H77+'HBO F'!$I77 -> 30 | K77: ='HBO F'!$H77+'HBO F'!$I77-TODAY() -> -45566 | L77: =IF(K77<1,"VENCIDO","VIGENTE") -> VENCIDO
C78: PERFILES : | F78: =SUM(F73:F77) -> 0 | G78: =SUM(G73:G77) -> 0
B83: ALERTA DIAS
B84: =TODAY() -> 45596
B85: CUENTA | C85: NOMBRE | D85: CLAVE | E85: TELEFONO | F85: PIN PERFIL | G85: PRECIO | H85: FECHA DE INICIO | I85: DIAS | J85: FECHA DE VENCIMIENTO | K85: ALARMA | L85: ESTADO
G86: =IF(H86>0,8,0) -> 0 | I86: 30 | J86: =+'HBO F'!$H86+'HBO F'!$I86 -> 30 | K86: ='HBO F'!$H86+'HBO F'!$I86-TODAY() -> -45566 | L86: =IF(K86<1,"VENCIDO","VIGENTE") -> VENCIDO
G87: =IF(H87>0,8,0) -> 0 | I87: 30 | J87: =+'HBO F'!$H87+'HBO F'!$I87 -> 30 | K87: ='HBO F'!$H87+'HBO F'!$I87-TODAY() -> -45566 | L87: =IF(K87<1,"VENCIDO","VIGENTE") -> VENCIDO
G88: =IF(H88>0,8,0) -> 0 | I88: 30 | J88: =+'HBO F'!$H88+'HBO F'!$I88 -> 30 | K88: ='HBO F'!$H88+'HBO F'!$I88-TODAY() -> -45566 | L88: =IF(K88<1,"VENCIDO","VIGENTE") -> VENCIDO
G89: =IF(H89>0,8,0) -> 0 | I89: 30 | J89: =+'HBO F'!$H89+'HBO F'!$I89 -> 30 | K89: ='HBO F'!$H89+'HBO F'!$I89-TODAY() -> -45566 | L89: =IF(K89<1,"VENCIDO","VIGENTE") -> VENCIDO
G90: =IF(H90>0,8,0) -> 0 | I90: 30 | J90: =+'HBO F'!$H90+'HBO F'!$I90 -> 30 | K90: ='HBO F'!$H90+'HBO F'!$I90-TODAY() -> -45566 | L90: =IF(K90<1,"VENCIDO","VIGENTE") -> VENCIDO
C91: PERFILES : | F91: =SUM(F86:F90) -> 0 | G91: =SUM(G86:G90) -> 0

Sheet Amazon F
B5: ALERTA DIAS
B6: =TODAY() -> 45596
B7: CUENTA | C7: NOMBRE | D7: CLAVE | E7: TELEFONO | F7: PIN PERFIL | G7: PRECIO | H7: FECHA DE INICIO | I7: DIAS | J7: FECHA DE VENCIMIENTO | K7: ALARMA | L7: ESTADO
C8: Diana477 | D8: de52kve12 | F8: 38777 | G8: =IF('Amazon F'!$H8>0,6,0) -> 6 | H8: 45502 | I8: 30 | J8: =+'Amazon F'!$H8+'Amazon F'!$I8 -> 45532 | K8: ='Amazon F'!$H8+'Amazon F'!$I8-TODAY() -> -64 | L8: =IF(K8<1,"VENCIDO","VIGENTE") -> VENCIDO
G9: =IF('Amazon F'!$H9>0,6,0) -> 0 | I9: 30 | J9: =+'Amazon F'!$H9+'Amazon F'!$I9 -> 30 | K9: ='Amazon F'!$H9+'Amazon F'!$I9-TODAY() -> -45566 | L9: =IF(K9<1,"VENCIDO","VIGENTE") -> VENCIDO
G10: =IF('Amazon F'!$H10>0,6,0) -> 0 | I10: 30 | J10: =+'Amazon F'!$H10+'Amazon F'!$I10 -> 30 | K10: ='Amazon F'!$H10+'Amazon F'!$I10-TODAY() -> -45566 | L10: =IF(K10<1,"VENCIDO","VIGENTE") -> VENCIDO
G11: =IF('Amazon F'!$H11>0,6,0) -> 0 | I11: 30 | J11: =+'Amazon F'!$H11+'Amazon F'!$I11 -> 30 | K11: ='Amazon F'!$H11+'Amazon F'!$I11-TODAY() -> -45566 | L11: =IF(K11<1,"VENCIDO","VIGENTE") -> VENCIDO
D12: 15121 | G12: =IF('Amazon F'!$H12>0,6,0) -> 0 | I12: 30 | J12: =+'Amazon F'!$H12+'Amazon F'!$I12 -> 30 | K12: ='Amazon F'!$H12+'Amazon F'!$I12-TODAY() -> -45566 | L12: =IF(K12<1,"VENCIDO","VIGENTE") -> VENCIDO
G13: =IF('Amazon F'!$H13>0,6,0) -> 0 | I13: 30 | J13: =+'Amazon F'!$H13+'Amazon F'!$I13 -> 30 | K13: ='Amazon F'!$H13+'Amazon F'!$I13-TODAY() -> -45566 | L13: =IF(K13<1,"VENCIDO","VIGENTE") -> VENCIDO
C14: PERFILES : | F14: =SUM(F9:F13) -> 0 | G14: =SUM(G9:G13) -> 0 | L14: =IF(K14<1,"VENCIDO","VIGENTE") -> VENCIDO
B19: ALERTA DIAS
B20: =TODAY() -> 45596
B21: CUENTA | C21: NOMBRE | D21: CLAVE | E21: TELEFONO | F21: PIN PERFIL | G21: PRECIO | H21: FECHA DE INICIO | I21: DIAS | J21: FECHA DE VENCIMIENTO | K21: ALARMA | L21: ESTADO
B22: Correo : dekumoood@gmail.com Contraseña : de233ku525 | C22: Giamyle826 | E22: 51 978 649 494 | F22: 62733 | G22: =IF('Amazon F'!$H22>0,4.5,0) -> 4.5 | H22: 45573 | I22: 30 | J22: =+'Amazon F'!$H22+'Amazon F'!$I22 -> 45603 | K22: ='Amazon F'!$H22+'Amazon F'!$I22-TODAY() -> 7 | L22: =IF(K22<1,"VENCIDO","VIGENTE") -> VIGENTE
C23: akemi34 | E23: 51 963 931 721 | F23: 9239 | G23: =IF('Amazon F'!$H23>0,6,0) -> 0 | I23: 30 | J23: =+'Amazon F'!$H23+'Amazon F'!$I23 -> 30 | K23: ='Amazon F'!$H23+'Amazon F'!$I23-TODAY() -> -45566 | L23: =IF(K23<1,"VENCIDO","VIGENTE") -> VENCIDO
C24: babas21 | E24: 51 951 821 138 | F24: 1122 | G24: =IF('Amazon F'!$H24>0,28,0) -> 28 | H24: 45574 | I24: 30 | J24: =+'Amazon F'!$H24+'Amazon F'!$I24 -> 45604 | K24: ='Amazon F'!$H24+'Amazon F'!$I24-TODAY() -> 8 | L24: =IF(K24<1,"VENCIDO","VIGENTE") -> VIGENTE
C25: Kuffo837 | E25: 593 98 946 6031 | F25: 41222 | G25: =IF('Amazon F'!$H25>0,1.8,0) -> 1.8 | H25: 45548 | I25: 30 | J25: =+'Amazon F'!$H25+'Amazon F'!$I25 -> 45578 | K25: ='Amazon F'!$H25+'Amazon F'!$I25-TODAY() -> -18 | L25: =IF(K25<1,"VENCIDO","VIGENTE") -> VENCIDO
C26: Javier932 | E26: 51 924 623 553 | F26: 22336 | G26: =IF('Amazon F'!$H26>0,6,0) -> 0 | I26: 30 | J26: =+'Amazon F'!$H26+'Amazon F'!$I26 -> 30 | K26: ='Amazon F'!$H26+'Amazon F'!$I26-TODAY() -> -45566 | L26: =IF(K26<1,"VENCIDO","VIGENTE") -> VENCIDO
C27: Giamyle826 | E27: 51 978 649 494 | F27: 62733 | G27: =IF('Amazon F'!$H27>0,4.5,0) -> 4.5 | H27: 45573 | I27: 30 | J27: =+'Amazon F'!$H27+'Amazon F'!$I27 -> 45603 | K27: ='Amazon F'!$H27+'Amazon F'!$I27-TODAY() -> 7 | L27: =IF(K27<1,"VENCIDO","VIGENTE") -> VIGENTE
C28: PERFILES : | F28: =SUM(F23:F27) -> 136652 | G28: =SUM(G23:G27) -> 34.3 | L28: =IF(K28<1,"VENCIDO","VIGENTE") -> VENCIDO
B33: ALERTA DIAS
B34: =TODAY() -> 45596
B35: CUENTA | C35: NOMBRE | D35: CLAVE | E35: TELEFONO | F35: PIN PERFIL | G35: PRECIO | H35: FECHA DE INICIO | I35: DIAS | J35: FECHA DE VENCIMIENTO | K35: ALARMA | L35: ESTADO
G36: =IF('Amazon F'!$H36>0,6,0) -> 0 | I36: 90 | J36: =+'Amazon F'!$H36+'Amazon F'!$I36 -> 90 | K36: ='Amazon F'!$H36+'Amazon F'!$I36-TODAY() -> -45506 | L36: =IF(K36<1,"VENCIDO","VIGENTE") -> VENCIDO
G37: =IF('Amazon F'!$H37>0,6,0) -> 0 | I37: 90 | J37: =+'Amazon F'!$H37+'Amazon F'!$I37 -> 90 | K37: ='Amazon F'!$H37+'Amazon F'!$I37-TODAY() -> -45506 | L37: =IF(K37<1,"VENCIDO","VIGENTE") -> VENCIDO
G38: =IF('Amazon F'!$H38>0,6,0) -> 0 | I38: 90 | J38: =+'Amazon F'!$H38+'Amazon F'!$I38 -> 90 | K38: ='Amazon F'!$H38+'Amazon F'!$I38-TODAY() -> -45506 | L38: =IF(K38<1,"VENCIDO","VIGENTE") -> VENCIDO
G39: =IF('Amazon F'!$H39>0,6,0) -> 0 | I39: 90 | J39: =+'Amazon F'!$H39+'Amazon F'!$I39 -> 90 | K39: ='Amazon F'!$H39+'Amazon F'!$I39-TODAY() -> -45506 | L39: =IF(K39<1,"VENCIDO","VIGENTE") -> VENCIDO
G40: =IF('Amazon F'!$H40>0,6,0) -> 0 | I40: 90 | J40: =+'Amazon F'!$H40+'Amazon F'!$I40 -> 90 | K40: ='Amazon F'!$H40+'Amazon F'!$I40-TODAY() -> -45506 | L40: =IF(K40<1,"VENCIDO","VIGENTE") -> VENCIDO
G41: =IF('Amazon F'!$H41>0,6,0) -> 0 | I41: 90 | J41: =+'Amazon F'!$H41+'Amazon F'!$I41 -> 90 | K41: ='Amazon F'!$H41+'Amazon F'!$I41-TODAY() -> -45506 | L41: =IF(K41<1,"VENCIDO","VIGENTE") -> VENCIDO
C42: PERFILES : | F42: =SUM(F37:F41) -> 0 | G42: =SUM(G37:G41) -> 0 | L42: =IF(K42<1,"VENCIDO","VIGENTE") -> VENCIDO
B47: ALERTA DIAS
B48: =TODAY() -> 45596
B49: CUENTA | C49: NOMBRE | D49: CLAVE | E49: TELEFONO | F49: PIN PERFIL | G49: PRECIO | H49: FECHA DE INICIO | I49: DIAS | J49: FECHA DE VENCIMIENTO | K49: ALARMA | L49: ESTADO
G50: =IF('Amazon F'!$H50>0,6,) -> 0 | I50: 90 | J50: =+'Amazon F'!$H50+'Amazon F'!$I50 -> 90 | K50: ='Amazon F'!$H50+'Amazon F'!$I50-TODAY() -> -45506 | L50: =IF(K50<1,"VENCIDO","VIGENTE") -> VENCIDO
G51: =IF('Amazon F'!$H51>0,6,) -> 0 | I51: 90 | J51: =+'Amazon F'!$H51+'Amazon F'!$I51 -> 90 | K51: ='Amazon F'!$H51+'Amazon F'!$I51-TODAY() -> -45506 | L51: =IF(K51<1,"VENCIDO","VIGENTE") -> VENCIDO
G52: =IF('Amazon F'!$H52>0,6,) -> 0 | I52: 90 | J52: =+'Amazon F'!$H52+'Amazon F'!$I52 -> 90 | K52: ='Amazon F'!$H52+'Amazon F'!$I52-TODAY() -> -45506 | L52: =IF(K52<1,"VENCIDO","VIGENTE") -> VENCIDO
G53: =IF('Amazon F'!$H53>0,6,) -> 0 | I53: 90 | J53: =+'Amazon F'!$H53+'Amazon F'!$I53 -> 90 | K53: ='Amazon F'!$H53+'Amazon F'!$I53-TODAY() -> -45506 | L53: =IF(K53<1,"VENCIDO","VIGENTE") -> VENCIDO
G54: =IF('Amazon F'!$H54>0,6,) -> 0 | I54: 90 | J54: =+'Amazon F'!$H54+'Amazon F'!$I54 -> 90 | K54: ='Amazon F'!$H54+'Amazon F'!$I54-TODAY() -> -45506 | L54: =IF(K54<1,"VENCIDO","VIGENTE") -> VENCIDO
G55: =IF('Amazon F'!$H55>0,6,) -> 0 | I55: 90 | J55: =+'Amazon F'!$H55+'Amazon F'!$I55 -> 90 | K55: ='Amazon F'!$H55+'Amazon F'!$I55-TODAY() -> -45506 | L55: =IF(K55<1,"VENCIDO","VIGENTE") -> VENCIDO
C56: PERFILES : | F56: =SUM(F51:F55) -> 0 | G56: =SUM(G51:G55) -> 0 | L56: =IF(K56<1,"VENCIDO","VIGENTE") -> VENCIDO
B61: ALERTA DIAS
B62: =TODAY() -> 45596
B63: CUENTA | C63: NOMBRE | D63: CLAVE | E63: TELEFONO | F63: PIN PERFIL | G63: PRECIO | H63: FECHA DE INICIO | I63: DIAS | J63: FECHA DE VENCIMIENTO | K63: ALARMA | L63: ESTADO
G64: =IF('Amazon F'!$H64>0,6,0) -> 0 | I64: 90 | J64: =+'Amazon F'!$H64+'Amazon F'!$I64 -> 90 | K64: ='Amazon F'!$H64+'Amazon F'!$I64-TODAY() -> -45506 | L64: =IF(K64<1,"VENCIDO","VIGENTE") -> VENCIDO
G65: =IF('Amazon F'!$H65>0,6,0) -> 0 | I65: 90 | J65: =+'Amazon F'!$H65+'Amazon F'!$I65 -> 90 | K65: ='Amazon F'!$H65+'Amazon F'!$I65-TODAY() -> -45506 | L65: =IF(K65<1,"VENCIDO","VIGENTE") -> VENCIDO
G66: =IF('Amazon F'!$H66>0,6,0) -> 0 | I66: 90 | J66: =+'Amazon F'!$H66+'Amazon F'!$I66 -> 90 | K66: ='Amazon F'!$H66+'Amazon F'!$I66-TODAY() -> -45506 | L66: =IF(K66<1,"VENCIDO","VIGENTE") -> VENCIDO
G67: =IF('Amazon F'!$H67>0,6,0) -> 0 | I67: 90 | J67: =+'Amazon F'!$H67+'Amazon F'!$I67 -> 90 | K67: ='Amazon F'!$H67+'Amazon F'!$I67-TODAY() -> -45506 | L67: =IF(K67<1,"VENCIDO","VIGENTE") -> VENCIDO
G68: =IF('Amazon F'!$H68>0,6,0) -> 0 | I68: 90 | J68: =+'Amazon F'!$H68+'Amazon F'!$I68 -> 90 | K68: ='Amazon F'!$H68+'Amazon F'!$I68-TODAY() -> -45506 | L68: =IF(K68<1,"VENCIDO","VIGENTE") -> VENCIDO
G69: =IF('Amazon F'!$H69>0,6,0) -> 0 | I69: 90 | J69: =+'Amazon F'!$H69+'Amazon F'!$I69 -> 90 | K69: ='Amazon F'!$H69+'Amazon F'!$I69-TODAY() -> -45506 | L69: =IF(K69<1,"VENCIDO","VIGENTE") -> VENCIDO
C70: PERFILES : | F70: =SUM(F65:F69) -> 0 | G70: =SUM(G65:G69) -> 0 | L70: =IF(K70<1,"VENCIDO","VIGENTE") -> VENCIDO
B75: ALERTA DIAS
B76: =TODAY() -> 45596
B77: CUENTA | C77: NOMBRE | D77: CLAVE | E77: TELEFONO | F77: PIN PERFIL | G77: PRECIO | H77: FECHA DE INICIO | I77: DIAS | J77: FECHA DE VENCIMIENTO | K77: ALARMA | L77: ESTADO
G78: =IF('Amazon F'!$H78>0,6,0) -> 0 | I78: 90 | J78: =+'Amazon F'!$H78+'Amazon F'!$I78 -> 90 | K78: ='Amazon F'!$H78+'Amazon F'!$I78-TODAY() -> -45506 | L78: =IF(K78<1,"VENCIDO","VIGENTE") -> VENCIDO
G79: =IF('Amazon F'!$H79>0,6,0) -> 0 | I79: 90 | J79: =+'Amazon F'!$H79+'Amazon F'!$I79 -> 90 | K79: ='Amazon F'!$H79+'Amazon F'!$I79-TODAY() -> -45506 | L79: =IF(K79<1,"VENCIDO","VIGENTE") -> VENCIDO
G80: =IF('Amazon F'!$H80>0,6,0) -> 0 | I80: 90 | J80: =+'Amazon F'!$H80+'Amazon F'!$I80 -> 90 | K80: ='Amazon F'!$H80+'Amazon F'!$I80-TODAY() -> -45506 | L80: =IF(K80<1,"VENCIDO","VIGENTE") -> VENCIDO
G81: =IF('Amazon F'!$H81>0,6,0) -> 0 | I81: 90 | J81: =+'Amazon F'!$H81+'Amazon F'!$I81 -> 90 | K81: ='Amazon F'!$H81+'Amazon F'!$I81-TODAY() -> -45506 | L81: =IF(K81<1,"VENCIDO","VIGENTE") -> VENCIDO
G82: =IF('Amazon F'!$H82>0,6,0) -> 0 | I82: 90 | J82: =+'Amazon F'!$H82+'Amazon F'!$I82 -> 90 | K82: ='Amazon F'!$H82+'Amazon F'!$I82-TODAY() -> -45506 | L82: =IF(K82<1,"VENCIDO","VIGENTE") -> VENCIDO
G83: =IF('Amazon F'!$H83>0,6,0) -> 0 | I83: 90 | J83: =+'Amazon F'!$H83+'Amazon F'!$I83 -> 90 | K83: ='Amazon F'!$H83+'Amazon F'!$I83-TODAY() -> -45506 | L83: =IF(K83<1,"VENCIDO","VIGENTE") -> VENCIDO
C84: PERFILES : | F84: =SUM(F79:F83) -> 0 | G84: =SUM(G79:G83) -> 0 | L84: =IF(K84<1,"VENCIDO","VIGENTE") -> VENCIDO
B89: ALERTA DIAS
B90: =TODAY() -> 45596
B91: CUENTA | C91: NOMBRE | D91: CLAVE | E91: TELEFONO | F91: PIN PERFIL | G91: PRECIO | H91: FECHA DE INICIO | I91: DIAS | J91: FECHA DE VENCIMIENTO | K91: ALARMA | L91: ESTADO
G92: =IF('Amazon F'!$H92>0,6,0) -> 0 | I92: 90 | J92: =+'Amazon F'!$H92+'Amazon F'!$I92 -> 90 | K92: ='Amazon F'!$H92+'Amazon F'!$I92-TODAY() -> -45506 | L92: =IF(K92<1,"VENCIDO","VIGENTE") -> VENCIDO
G93: =IF('Amazon F'!$H93>0,6,0) -> 0 | I93: 90 | J93: =+'Amazon F'!$H93+'Amazon F'!$I93 -> 90 | K93: ='Amazon F'!$H93+'Amazon F'!$I93-TODAY() -> -45506 | L93: =IF(K93<1,"VENCIDO","VIGENTE") -> VENCIDO
G94: =IF('Amazon F'!$H94>0,6,0) -> 0 | I94: 90 | J94: =+'Amazon F'!$H94+'Amazon F'!$I94 -> 90 | K94: ='Amazon F'!$H94+'Amazon F'!$I94-TODAY() -> -45506 | L94: =IF(K94<1,"VENCIDO","VIGENTE") -> VENCIDO
G95: =IF('Amazon F'!$H95>0,6,0) -> 0 | I95: 90 | J95: =+'Amazon F'!$H95+'Amazon F'!$I95 -> 90 | K95: ='Amazon F'!$H95+'Amazon F'!$I95-TODAY() -> -45506 | L95: =IF(K95<1,"VENCIDO","VIGENTE") -> VENCIDO
G96: =IF('Amazon F'!$H96>0,6,0) -> 0 | I96: 90 | J96: =+'Amazon F'!$H96+'Amazon F'!$I96 -> 90 | K96: ='Amazon F'!$H96+'Amazon F'!$I96-TODAY() -> -45506 | L96: =IF(K96<1,"VENCIDO","VIGENTE") -> VENCIDO
G97: =IF('Amazon F'!$H97>0,6,0) -> 0 | I97: 90 | J97: =+'Amazon F'!$H97+'Amazon F'!$I97 -> 90 | K97: ='Amazon F'!$H97+'Amazon F'!$I97-TODAY() -> -45506 | L97: =IF(K97<1,"VENCIDO","VIGENTE") -> VENCIDO
C98: PERFILES : | F98: =SUM(F93:F97) -> 0 | G98: =SUM(G93:G97) -> 0 | L98: =IF(K98<1,"VENCIDO","VIGENTE") -> VENCIDO

Sheet Spotify
H4: SI(H218>0;30;0)
B5: ALERTA DIAS
B6: =TODAY() -> 45596
B7: CUENTA | C7: NOMBRE | D7: CLAVE | E7: TELEFONO | F7: PIN PERFIL | G7: PRECIO | H7: FECHA DE INICIO | I7: DIAS | J7: FECHA DE VENCIMIENTO | K7: ALARMA | L7: ESTADO
F8: x | G8: =IF(Spotify!$H8>0,8,0) -> 0 | I8: 30 | J8: =+Spotify!$H8+Spotify!$I8 -> 30 | K8: =Spotify!$H8+Spotify!$I8-TODAY() -> -45566 | L8: =IF(K8<1,"VENCIDO","VIGENTE") -> VENCIDO
G9: =IF(Spotify!$H9>0,20,0) -> 0 | I9: 90 | J9: =+Spotify!$H9+Spotify!$I9 -> 90 | K9: =Spotify!$H9+Spotify!$I9-TODAY() -> -45506 | L9: =IF(K9<1,"VENCIDO","VIGENTE") -> VENCIDO
G10: =IF(Spotify!$H10>0,20,0) -> 0 | I10: 90 | J10: =+Spotify!$H10+Spotify!$I10 -> 90 | K10: =Spotify!$H10+Spotify!$I10-TODAY() -> -45506 | L10: =IF(K10<1,"VENCIDO","VIGENTE") -> VENCIDO
G11: =IF(Spotify!$H11>0,8,0) -> 0 | I11: 30 | J11: =+Spotify!$H11+Spotify!$I11 -> 30 | K11: =Spotify!$H11+Spotify!$I11-TODAY() -> -45566 | L11: =IF(K11<1,"VENCIDO","VIGENTE") -> VENCIDO
G12: =IF(Spotify!$H12>0,20,0) -> 0 | I12: 90 | J12: =+Spotify!$H12+Spotify!$I12 -> 90 | K12: =Spotify!$H12+Spotify!$I12-TODAY() -> -45506 | L12: =IF(K12<1,"VENCIDO","VIGENTE") -> VENCIDO
G13: =IF(Spotify!$H13>0,8,0) -> 0 | I13: 30 | J13: =+Spotify!$H13+Spotify!$I13 -> 30 | K13: =Spotify!$H13+Spotify!$I13-TODAY() -> -45566 | L13: =IF(K13<1,"VENCIDO","VIGENTE") -> VENCIDO
C14: PERFILES : | F14: =SUM(F9:F13) -> 0 | G14: =SUM(G9:G13) -> 0 | L14: =IF(K14<1,"VENCIDO","VIGENTE") -> VENCIDO
B19: ALERTA DIAS
B20: =TODAY() -> 45596
B21: CUENTA | C21: NOMBRE | D21: CLAVE | E21: TELEFONO | F21: PIN PERFIL | G21: PRECIO | H21: FECHA DE INICIO | I21: DIAS | J21: FECHA DE VENCIMIENTO | K21: ALARMA | L21: ESTADO
G22: =IF(Spotify!$H22>0,20,0) -> 0 | I22: 60 | J22: =+Spotify!$H22+Spotify!$I22 -> 60 | K22: =Spotify!$H22+Spotify!$I22-TODAY() -> -45536 | L22: =IF(K22<1,"VENCIDO","VIGENTE") -> VENCIDO
G23: =IF(Spotify!$H23>0,20,0) -> 0 | I23: 90 | J23: =+Spotify!$H23+Spotify!$I23 -> 90 | K23: =Spotify!$H23+Spotify!$I23-TODAY() -> -45506 | L23: =IF(K23<1,"VENCIDO","VIGENTE") -> VENCIDO
G24: =IF(Spotify!$H24>0,8,0) -> 0 | I24: 30 | J24: =+Spotify!$H24+Spotify!$I24 -> 30 | K24: =Spotify!$H24+Spotify!$I24-TODAY() -> -45566 | L24: =IF(K24<1,"VENCIDO","VIGENTE") -> VENCIDO
G25: =IF(Spotify!$H25>0,20,0) -> 0 | I25: 90 | J25: =+Spotify!$H25+Spotify!$I25 -> 90 | K25: =Spotify!$H25+Spotify!$I25-TODAY() -> -45506 | L25: =IF(K25<1,"VENCIDO","VIGENTE") -> VENCIDO
G26: =IF(Spotify!$H26>0,8,0) -> 0 | I26: 90 | J26: =+Spotify!$H26+Spotify!$I26 -> 90 | K26: =Spotify!$H26+Spotify!$I26-TODAY() -> -45506 | L26: =IF(K26<1,"VENCIDO","VIGENTE") -> VENCIDO
G27: =IF(Spotify!$H27>0,8,0) -> 0 | I27: 30 | J27: =+Spotify!$H27+Spotify!$I27 -> 30 | K27: =Spotify!$H27+Spotify!$I27-TODAY() -> -45566 | L27: =IF(K27<1,"VENCIDO","VIGENTE") -> VENCIDO
C28: PERFILES : | F28: =SUM(F23:F27) -> 0 | G28: =SUM(G23:G27) -> 0 | L28: =IF(K28<1,"VENCIDO","VIGENTE") -> VENCIDO
B33: ALERTA DIAS
B34: =TODAY() -> 45596
B35: CUENTA | C35: NOMBRE | D35: CLAVE | E35: TELEFONO | F35: PIN PERFIL | G35: PRECIO | H35: FECHA DE INICIO | I35: DIAS | J35: FECHA DE VENCIMIENTO | K35: ALARMA | L35: ESTADO
G36: =IF(Spotify!$H36>0,20,0) -> 0 | I36: 90 | J36: =+Spotify!$H36+Spotify!$I36 -> 90 | K36: =Spotify!$H36+Spotify!$I36-TODAY() -> -45506 | L36: =IF(K36<1,"VENCIDO","VIGENTE") -> VENCIDO
G37: =IF(Spotify!$H37>0,20,0) -> 0 | I37: 90 | J37: =+Spotify!$H37+Spotify!$I37 -> 90 | K37: =Spotify!$H37+Spotify!$I37-TODAY() -> -45506 | L37: =IF(K37<1,"VENCIDO","VIGENTE") -> VENCIDO
G38: =IF(Spotify!$H38>0,20,0) -> 0 | I38: 90 | J38: =+Spotify!$H38+Spotify!$I38 -> 90 | K38: =Spotify!$H38+Spotify!$I38-TODAY() -> -45506 | L38: =IF(K38<1,"VENCIDO","VIGENTE") -> VENCIDO
G39: =IF(Spotify!$H39>0,20,0) -> 0 | I39: 90 | J39: =+Spotify!$H39+Spotify!$I39 -> 90 | K39: =Spotify!$H39+Spotify!$I39-TODAY() -> -45506 | L39: =IF(K39<1,"VENCIDO","VIGENTE") -> VENCIDO
G40: =IF(Spotify!$H40>0,20,0) -> 0 | I40: 90 | J40: =+Spotify!$H40+Spotify!$I40 -> 90 | K40: =Spotify!$H40+Spotify!$I40-TODAY() -> -45506 | L40: =IF(K40<1,"VENCIDO","VIGENTE") -> VENCIDO
G41: =IF(Spotify!$H41>0,20,0) -> 0 | I41: 90 | J41: =+Spotify!$H41+Spotify!$I41 -> 90 | K41: =Spotify!$H41+Spotify!$I41-TODAY() -> -45506 | L41: =IF(K41<1,"VENCIDO","VIGENTE") -> VENCIDO
C42: PERFILES : | F42: =SUM(F37:F41) -> 0 | G42: =SUM(G37:G41) -> 0 | L42: =IF(K42<1,"VENCIDO","VIGENTE") -> VENCIDO
B47: ALERTA DIAS
B48: =TODAY() -> 45596
B49: CUENTA | C49: NOMBRE | D49: CLAVE | E49: TELEFONO | F49: PIN PERFIL | G49: PRECIO | H49: FECHA DE INICIO | I49: DIAS | J49: FECHA DE VENCIMIENTO | K49: ALARMA | L49: ESTADO
A50: no sale pago | B50: Correo : dek19se183cek@hotmail.com Contraseña: T!1X9tpUB$szhJe&t0#T | C50: luis usa ns | G50: =IF(Spotify!$H50>0,20,0) -> 0 | I50: 90 | J50: =+Spotify!$H50+Spotify!$I50 -> 90 | K50: =Spotify!$H50+Spotify!$I50-TODAY() -> -45506 | L50: =IF(K50<1,"VENCIDO","VIGENTE") -> VENCIDO
G51: =IF(Spotify!$H51>0,20,0) -> 0 | I51: 90 | J51: =+Spotify!$H51+Spotify!$I51 -> 90 | K51: =Spotify!$H51+Spotify!$I51-TODAY() -> -45506 | L51: =IF(K51<1,"VENCIDO","VIGENTE") -> VENCIDO
G52: =IF(Spotify!$H52>0,20,0) -> 0 | I52: 90 | J52: =+Spotify!$H52+Spotify!$I52 -> 90 | K52: =Spotify!$H52+Spotify!$I52-TODAY() -> -45506 | L52: =IF(K52<1,"VENCIDO","VIGENTE") -> VENCIDO
G53: =IF(Spotify!$H53>0,20,0) -> 0 | I53: 90 | J53: =+Spotify!$H53+Spotify!$I53 -> 90 | K53: =Spotify!$H53+Spotify!$I53-TODAY() -> -45506 | L53: =IF(K53<1,"VENCIDO","VIGENTE") -> VENCIDO
G54: =IF(Spotify!$H54>0,20,0) -> 0 | I54: 90 | J54: =+Spotify!$H54+Spotify!$I54 -> 90 | K54: =Spotify!$H54+Spotify!$I54-TODAY() -> -45506 | L54: =IF(K54<1,"VENCIDO","VIGENTE") -> VENCIDO
G55: =IF(Spotify!$H55>0,20,0) -> 0 | I55: 90 | J55: =+Spotify!$H55+Spotify!$I55 -> 90 | K55: =Spotify!$H55+Spotify!$I55-TODAY() -> -45506 | L55: =IF(K55<1,"VENCIDO","VIGENTE") -> VENCIDO
C56: PERFILES : | F56: =SUM(F51:F55) -> 0 | G56: =SUM(G51:G55) -> 0 | L56: =IF(K56<1,"VENCIDO","VIGENTE") -> VENCIDO
B61: ALERTA DIAS
B62: =TODAY() -> 45596
B63: CUENTA | C63: NOMBRE | D63: CLAVE | E63: TELEFONO | F63: PIN PERFIL | G63: PRECIO | H63: FECHA DE INICIO | I63: DIAS | J63: FECHA DE VENCIMIENTO | K63: ALARMA | L63: ESTADO
B64: CORREO: dek35bedeku@gmail.com CONTRASEÑA: dekk45ner2 | C64: abraham el papi | E64: 51 942 257 254 | G64: =IF(Spotify!$H64>0,35,0) -> 35 | H64: 45528 | I64: 180 | J64: =+Spotify!$H64+Spotify!$I64 -> 45708 | K64: =Spotify!$H64+Spotify!$I64-TODAY() -> 112 | L64: =IF(K64<1,"VENCIDO","VIGENTE") -> VIGENTE
G65: =IF(Spotify!$H65>0,20,0) -> 0 | I65: 90 | J65: =+Spotify!$H65+Spotify!$I65 -> 90 | K65: =Spotify!$H65+Spotify!$I65-TODAY() -> -45506 | L65: =IF(K65<1,"VENCIDO","VIGENTE") -> VENCIDO
G66: =IF(Spotify!$H66>0,20,0) -> 0 | I66: 90 | J66: =+Spotify!$H66+Spotify!$I66 -> 90 | K66: =Spotify!$H66+Spotify!$I66-TODAY() -> -45506 | L66: =IF(K66<1,"VENCIDO","VIGENTE") -> VENCIDO
G67: =IF(Spotify!$H67>0,20,0) -> 0 | I67: 90 | J67: =+Spotify!$H67+Spotify!$I67 -> 90 | K67: =Spotify!$H67+Spotify!$I67-TODAY() -> -45506 | L67: =IF(K67<1,"VENCIDO","VIGENTE") -> VENCIDO
G68: =IF(Spotify!$H68>0,20,0) -> 0 | I68: 90 | J68: =+Spotify!$H68+Spotify!$I68 -> 90 | K68: =Spotify!$H68+Spotify!$I68-TODAY() -> -45506 | L68: =IF(K68<1,"VENCIDO","VIGENTE") -> VENCIDO
G69: =IF(Spotify!$H69>0,20,0) -> 0 | I69: 90 | J69: =+Spotify!$H69+Spotify!$I69 -> 90 | K69: =Spotify!$H69+Spotify!$I69-TODAY() -> -45506 | L69: =IF(K69<1,"VENCIDO","VIGENTE") -> VENCIDO
C70: PERFILES : | F70: =SUM(F65:F69) -> 0 | G70: =SUM(G65:G69) -> 0 | L70: =IF(K70<1,"VENCIDO","VIGENTE") -> VENCIDO
B75: ALERTA DIAS
B76: =TODAY() -> 45596
B77: CUENTA | C77: NOMBRE | D77: CLAVE | E77: TELEFONO | F77: PIN PERFIL | G77: precio US | H77: PRECIO | I77: FECHA DE INICIO | J77: DIAS | K77: FECHA DE VENCIMIENTO | L77: ALARMA | M77: ESTADO
B78: CORREO: spotify20249586102@prc.cx CONTRASEÑA: spot20245478 | C78: alexanderrr | E78: 51 973 042 635 | G78: $3.5 | H78: =IF(Spotify!$I78>0,20,0) -> 20 | I78: 45540 | J78: 100 | K78: =+Spotify!$I78+Spotify!$J78 -> 45640 | L78: =Spotify!$I78+Spotify!$J78-TODAY() -> 44 | M78: =IF(L78<1,"VENCIDO","VIGENTE") -> VIGENTE
H79: =IF(Spotify!$I79>0,20,0) -> 0 | J79: 90 | K79: =+Spotify!$I79+Spotify!$J79 -> 90 | L79: =Spotify!$I79+Spotify!$J79-TODAY() -> -45506 | M79: =IF(L79<1,"VENCIDO","VIGENTE") -> VENCIDO
H80: =IF(Spotify!$I80>0,20,0) -> 0 | J80: 90 | K80: =+Spotify!$I80+Spotify!$J80 -> 90 | L80: =Spotify!$I80+Spotify!$J80-TODAY() -> -45506 | M80: =IF(L80<1,"VENCIDO","VIGENTE") -> VENCIDO
H81: =IF(Spotify!$I81>0,20,0) -> 0 | J81: 90 | K81: =+Spotify!$I81+Spotify!$J81 -> 90 | L81: =Spotify!$I81+Spotify!$J81-TODAY() -> -45506 | M81: =IF(L81<1,"VENCIDO","VIGENTE") -> VENCIDO
H82: =IF(Spotify!$I82>0,20,0) -> 0 | J82: 90 | K82: =+Spotify!$I82+Spotify!$J82 -> 90 | L82: =Spotify!$I82+Spotify!$J82-TODAY() -> -45506 | M82: =IF(L82<1,"VENCIDO","VIGENTE") -> VENCIDO
H83: =IF(Spotify!$I83>0,20,0) -> 0 | J83: 90 | K83: =+Spotify!$I83+Spotify!$J83 -> 90 | L83: =Spotify!$I83+Spotify!$J83-TODAY() -> -45506 | M83: =IF(L83<1,"VENCIDO","VIGENTE") -> VENCIDO
C84: PERFILES : | F84: =SUM(F79:F83) -> 0 | H84: =SUM(H79:H83) -> 0 | M84: =IF(L84<1,"VENCIDO","VIGENTE") -> VENCIDO
B89: ALERTA DIAS
B90: =TODAY() -> 45596
B91: CUENTA | C91: NOMBRE | D91: CLAVE | E91: TELEFONO | F91: PIN PERFIL | G91: PRECIO | H91: FECHA DE INICIO | I91: DIAS | J91: FECHA DE VENCIMIENTO | K91: ALARMA | L91: ESTADO
B92: CORREO: spotify154527@prc.cx 🔑 CONTRASEÑA: dekju436ber3 | C92: C##000187 Babas | E92: +51 951 821 138 | G92: =IF(Spotify!$H92>0,20,0) -> 20 | H92: 45573 | I92: 30 | J92: =+Spotify!$H92+Spotify!$I92 -> 45603 | K92: =Spotify!$H92+Spotify!$I92-TODAY() -> 7 | L92: =IF(K92<1,"VENCIDO","VIGENTE") -> VIGENTE
G93: =IF(Spotify!$H93>0,20,0) -> 0 | I93: 90 | J93: =+Spotify!$H93+Spotify!$I93 -> 90 | K93: =Spotify!$H93+Spotify!$I93-TODAY() -> -45506 | L93: =IF(K93<1,"VENCIDO","VIGENTE") -> VENCIDO
G94: =IF(Spotify!$H94>0,20,0) -> 0 | I94: 90 | J94: =+Spotify!$H94+Spotify!$I94 -> 90 | K94: =Spotify!$H94+Spotify!$I94-TODAY() -> -45506 | L94: =IF(K94<1,"VENCIDO","VIGENTE") -> VENCIDO
G95: =IF(Spotify!$H95>0,20,0) -> 0 | I95: 90 | J95: =+Spotify!$H95+Spotify!$I95 -> 90 | K95: =Spotify!$H95+Spotify!$I95-TODAY() -> -45506 | L95: =IF(K95<1,"VENCIDO","VIGENTE") -> VENCIDO
G96: =IF(Spotify!$H96>0,20,0) -> 0 | I96: 90 | J96: =+Spotify!$H96+Spotify!$I96 -> 90 | K96: =Spotify!$H96+Spotify!$I96-TODAY() -> -45506 | L96: =IF(K96<1,"VENCIDO","VIGENTE") -> VENCIDO
G97: =IF(Spotify!$H97>0,20,0) -> 0 | I97: 90 | J97: =+Spotify!$H97+Spotify!$I97 -> 90 | K97: =Spotify!$H97+Spotify!$I97-TODAY() -> -45506 | L97: =IF(K97<1,"VENCIDO","VIGENTE") -> VENCIDO
C98: PERFILES : | F98: =SUM(F93:F97) -> 0 | G98: =SUM(G93:G97) -> 0

Sheet Crunchyroll
A2: ALERTA DIAS
A3: =TODAY() -> 45596
A4: CUENTA | B4: NOMBRE | C4: CLAVE | D4: TELEFONO | E4: PIN PERFIL | F4: PRECIO USD | G4: PRECIO | H4: FECHA DE INICIO | I4: DIAS | J4: FECHA DE VENCIMIENTO | K4: ALARMA | L4: ESTADO
A5: CORREO: deku73773de@tapi.re CONTRASEÑA: Deku##rw426 | B5: Luis349 | D5: 593 93 929 3826 | F5: $1.8 | G5: =IF(H5>0,7,0) -> 7 | H5: 45575 | I5: 30 | J5: =+Table_7836[[#This Row],[FECHA DE INICIO]]+Table_7836[[#This Row],[DIAS]] -> 45605 | K5: =+Table_7836[[#This Row],[FECHA DE INICIO]]+Table_7836[[#This Row],[DIAS]]-TODAY() -> 9 | L5: =IF(K5<1,"VENCIDO","VIGENTE") -> VIGENTE
B6: Babas334 | D6: 51 951 821 138 | G6: =IF(H6>0,5,0) -> 5 | H6: 45573 | I6: 30 | J6: =+Table_7836[[#This Row],[FECHA DE INICIO]]+Table_7836[[#This Row],[DIAS]] -> 45603 | K6: =+Table_7836[[#This Row],[FECHA DE INICIO]]+Table_7836[[#This Row],[DIAS]]-TODAY() -> 7 | L6: =IF(K6<1,"VENCIDO","VIGENTE") -> VIGENTE
B7: Alexander922 | D7: 51 973 042 635 | G7: =IF(H7>0,5,0) -> 5 | H7: 45577 | I7: 30 | J7: =+Table_7836[[#This Row],[FECHA DE INICIO]]+Table_7836[[#This Row],[DIAS]] -> 45607 | K7: =+Table_7836[[#This Row],[FECHA DE INICIO]]+Table_7836[[#This Row],[DIAS]]-TODAY() -> 11 | L7: =IF(K7<1,"VENCIDO","VIGENTE") -> VIGENTE
B8: Sebas361 | D8: 51 951 821 138 | G8: 5 | H8: 45573 | I8: 30 | J8: =+Table_7836[[#This Row],[FECHA DE INICIO]]+Table_7836[[#This Row],[DIAS]] -> 45603 | K8: =+Table_7836[[#This Row],[FECHA DE INICIO]]+Table_7836[[#This Row],[DIAS]]-TODAY() -> 7 | L8: =IF(K8<1,"VENCIDO","VIGENTE") -> VIGENTE
I9: 30 | J9: =+Table_7836[[#This Row],[FECHA DE INICIO]]+Table_7836[[#This Row],[DIAS]] -> 30 | K9: =+Table_7836[[#This Row],[FECHA DE INICIO]]+Table_7836[[#This Row],[DIAS]]-TODAY() -> -45566 | L9: =IF(K9<1,"VENCIDO","VIGENTE") -> VENCIDO
B10: PERFILES : | E10: =SUM(E5:E9) -> 0 | G10: =SUM(G5:G9) -> 22 | I10: 30 | J10: =+Table_7836[[#This Row],[FECHA DE INICIO]]+Table_7836[[#This Row],[DIAS]] -> 30 | K10: =+Table_7836[[#This Row],[FECHA DE INICIO]]+Table_7836[[#This Row],[DIAS]]-TODAY() -> -45566
A14: ALERTA DIAS
A15: =TODAY() -> 45596
A16: CUENTA | B16: NOMBRE | C16: CLAVE | D16: TELEFONO | E16: PIN PERFIL | F16: PRECIO USD | G16: PRECIO | H16: FECHA DE INICIO | I16: DIAS | J16: FECHA DE VENCIMIENTO | K16: ALARMA | L16: ESTADO
A17: CORREO: deku924crunc@haren.uk CONTRASEÑA: Deku1836$$ | B17: Sebas361 | D17: 593 98 372 8976 | G17: =IF(H17>0,7,0) -> 7 | H17: 45532 | I17: 30 | J17: =+Table_783617[[#This Row],[FECHA DE INICIO]]+Table_783617[[#This Row],[DIAS]] -> 45562 | K17: =+Table_783617[[#This Row],[FECHA DE INICIO]]+Table_783617[[#This Row],[DIAS]]-TODAY() -> -34 | L17: =IF(K17<1,"VENCIDO","VIGENTE") -> VENCIDO
B18: Jhonatan35 | D18: 593 99 803 3836 | F18: $17 | G18: =IF(H18>0,0,0) -> 0 | H18: 45510 | I18: 360 | J18: =+Table_783617[[#This Row],[FECHA DE INICIO]]+Table_783617[[#This Row],[DIAS]] -> 45870 | K18: =+Table_783617[[#This Row],[FECHA DE INICIO]]+Table_783617[[#This Row],[DIAS]]-TODAY() -> 274 | L18: =IF(K18<1,"VENCIDO","VIGENTE") -> VIGENTE
B19: Remy847 | D19: 51 926 665 678 | G19: =IF(H19>0,5,0) -> 5 | H19: 45552 | I19: 30 | J19: =+Table_783617[[#This Row],[FECHA DE INICIO]]+Table_783617[[#This Row],[DIAS]] -> 45582 | K19: =+Table_783617[[#This Row],[FECHA DE INICIO]]+Table_783617[[#This Row],[DIAS]]-TODAY() -> -14 | L19: =IF(K19<1,"VENCIDO","VIGENTE") -> VENCIDO
B20: Marlon349 | F20: $1.5 | G20: =IF(H20>0,7,0) -> 7 | H20: 45546 | I20: 30 | J20: =+Table_783617[[#This Row],[FECHA DE INICIO]]+Table_783617[[#This Row],[DIAS]] -> 45576 | K20: =+Table_783617[[#This Row],[FECHA DE INICIO]]+Table_783617[[#This Row],[DIAS]]-TODAY() -> -20 | L20: =IF(K20<1,"VENCIDO","VIGENTE") -> VENCIDO
B21: Criswell Ostaiza | D21: 593 96 178 8067 | F21: $1.8 | G21: =IF(H21>0,7,0) -> 7 | H21: 45579 | I21: 30 | J21: =+Table_783617[[#This Row],[FECHA DE INICIO]]+Table_783617[[#This Row],[DIAS]] -> 45609 | K21: =+Table_783617[[#This Row],[FECHA DE INICIO]]+Table_783617[[#This Row],[DIAS]]-TODAY() -> 13 | L21: =IF(K21<1,"VENCIDO","VIGENTE") -> VIGENTE
B22: PERFILES : | E22: =SUM(E17:E21) -> 0 | G22: =SUM(G17:G21) -> 26 | I22: 30 | J22: =+Table_783617[[#This Row],[FECHA DE INICIO]]+Table_783617[[#This Row],[DIAS]] -> 30 | K22: =+Table_783617[[#This Row],[FECHA DE INICIO]]+Table_783617[[#This Row],[DIAS]]-TODAY() -> -45566
A27: ALERTA DIAS
A28: =TODAY() -> 45596
A29: CUENTA | B29: NOMBRE | C29: CLAVE | D29: TELEFONO | E29: PIN PERFIL | F29: PRECIO USD | G29: PRECIO | H29: FECHA DE INICIO | I29: DIAS | J29: FECHA DE VENCIMIENTO | K29: ALARMA | L29: ESTADO
A30: Correo: deku258@ichigo.me Contraseña: deku25ver265 | G30: =IF(H30>0,7,0) -> 0 | I30: 30 | J30: =+Table_78361718[[#This Row],[FECHA DE INICIO]]+Table_78361718[[#This Row],[DIAS]] -> 30 | K30: =+Table_78361718[[#This Row],[FECHA DE INICIO]]+Table_78361718[[#This Row],[DIAS]]-TODAY() -> -45566 | L30: =IF(K30<1,"VENCIDO","VIGENTE") -> VENCIDO
G31: =IF(H31>0,0,0) -> 0 | I31: 360 | J31: =+Table_78361718[[#This Row],[FECHA DE INICIO]]+Table_78361718[[#This Row],[DIAS]] -> 360 | K31: =+Table_78361718[[#This Row],[FECHA DE INICIO]]+Table_78361718[[#This Row],[DIAS]]-TODAY() -> -45236 | L31: =IF(K31<1,"VENCIDO","VIGENTE") -> VENCIDO
G32: =IF(H32>0,5,0) -> 0 | I32: 30 | J32: =+Table_78361718[[#This Row],[FECHA DE INICIO]]+Table_78361718[[#This Row],[DIAS]] -> 30 | K32: =+Table_78361718[[#This Row],[FECHA DE INICIO]]+Table_78361718[[#This Row],[DIAS]]-TODAY() -> -45566 | L32: =IF(K32<1,"VENCIDO","VIGENTE") -> VENCIDO
G33: =IF(H33>0,7,0) -> 0 | I33: 30 | J33: =+Table_78361718[[#This Row],[FECHA DE INICIO]]+Table_78361718[[#This Row],[DIAS]] -> 30 | K33: =+Table_78361718[[#This Row],[FECHA DE INICIO]]+Table_78361718[[#This Row],[DIAS]]-TODAY() -> -45566 | L33: =IF(K33<1,"VENCIDO","VIGENTE") -> VENCIDO
G34: =IF(H34>0,7,0) -> 0 | I34: 30 | J34: =+Table_78361718[[#This Row],[FECHA DE INICIO]]+Table_78361718[[#This Row],[DIAS]] -> 30 | K34: =+Table_78361718[[#This Row],[FECHA DE INICIO]]+Table_78361718[[#This Row],[DIAS]]-TODAY() -> -45566 | L34: =IF(K34<1,"VENCIDO","VIGENTE") -> VENCIDO
B35: PERFILES : | E35: =SUM(E30:E34) -> 0 | G35: =SUM(G30:G34) -> 0 | I35: 30 | J35: =+Table_78361718[[#This Row],[FECHA DE INICIO]]+Table_78361718[[#This Row],[DIAS]] -> 30 | K35: =+Table_78361718[[#This Row],[FECHA DE INICIO]]+Table_78361718[[#This Row],[DIAS]]-TODAY() -> -45566

Sheet Hoja3

Sheet Presupuesto
C6: Netflix F | D6: Netflix R | E6: Disnet F | F6: Disney R | G6: Combo F | H6: Combo R | I6: HBO F | J6: Amazon F | K6: Spotify
C8: ='Net F'!H14 -> 10 | D8: ='Net R'!G21 -> 30 | E8: ='Dis F'!G15 -> 24.5 | F8: ='Dis R'!G21 -> 5 | G8: ='Com F'!G15 -> 0 | H8: ='Com R'!G21 -> 0 | I8: ='HBO F'!G13 -> 0 | J8: ='Amazon F'!G14 -> 0 | K8: =Spotify!G14 -> 0
C9: ='Net F'!#REF! -> #REF! | D9: ='Net R'!G42 -> 0 | E9: ='Dis F'!#REF! -> #REF! | F9: ='Dis R'!G42 -> 6.5 | G9: ='Com F'!G29 -> 9 | H9: ='Com R'!G42 -> 0 | I9: ='HBO F'!G26 -> 18 | J9: ='Amazon F'!G28 -> 34.3 | K9: =Spotify!G28 -> 0
C10: ='Net F'!#REF! -> #REF! | D10: ='Net R'!G63 -> 0 | E10: ='Dis F'!#REF! -> #REF! | F10: ='Dis R'!G63 -> 0 | G10: ='Com F'!G43 -> 0 | H10: ='Com R'!G63 -> 0 | I10: ='HBO F'!G39 -> 0 | J10: ='Amazon F'!G42 -> 0 | K10: =Spotify!G42 -> 0
C11: ='Net F'!#REF! -> #REF! | D11: ='Net R'!G84 -> 0 | E11: ='Dis F'!#REF! -> #REF! | F11: ='Dis R'!G84 -> 0 | G11: ='Com F'!G57 -> 0 | H11: ='Com R'!G84 -> 0 | I11: ='HBO F'!G52 -> 22.5 | J11: ='Amazon F'!G56 -> 0 | K11: =Spotify!G56 -> 0
C12: ='Net F'!#REF! -> #REF! | D12: ='Net R'!G105 -> 0 | E12: ='Dis F'!#REF! -> #REF! | F12: ='Dis R'!G105 -> 0 | G12: ='Com F'!G71 -> 0 | H12: ='Com R'!G105 -> 0 | I12: ='HBO F'!G65 -> 0 | J12: ='Amazon F'!G70 -> 0 | K12: =Spotify!G70 -> 0
C13: ='Net F'!#REF! -> #REF! | D13: ='Net R'!G126 -> 0 | E13: ='Dis F'!#REF! -> #REF! | F13: ='Dis R'!G126 -> 0 | G13: ='Com F'!G85 -> 0 | H13: ='Com R'!G126 -> 0 | I13: ='HBO F'!G78 -> 0 | J13: ='Amazon F'!G84 -> 0 | K13: =Spotify!H84 -> 0
C14: ='Net F'!#REF! -> #REF! | D14: ='Net R'!G147 -> 0 | E14: ='Dis F'!#REF! -> #REF! | F14: ='Dis R'!G147 -> 0 | G14: ='Com F'!G99 -> 0 | H14: ='Com R'!G147 -> 0 | I14: ='HBO F'!G91 -> 0 | J14: ='Amazon F'!G98 -> 0 | K14: =Spotify!G98 -> 0
C15: ='Net F'!#REF! -> #REF! | D15: ='Net R'!G168 -> 0 | E15: ='Dis F'!#REF! -> #REF! | F15: ='Dis R'!G168 -> 0 | G15: ='Com F'!G113 -> 0 | H15: ='Com R'!G168 -> 0
C16: ='Net F'!#REF! -> #REF! | D16: ='Net R'!G189 -> 0 | F16: ='Dis R'!G189 -> 0 | H16: ='Com R'!G189 -> 0
C17: ='Net F'!#REF! -> #REF! | D17: ='Net R'!G210 -> 0 | F17: ='Dis R'!G210 -> 0 | H17: ='Com R'!G210 -> 0
C18: ='Net F'!#REF! -> #REF! | D18: ='Net R'!G231 -> 0 | F18: ='Dis R'!G231 -> 0 | H18: ='Com R'!G231 -> 0
C19: ='Net F'!#REF! -> #REF! | D19: ='Net R'!G252 -> 0 | F19: ='Dis R'!G252 -> 0 | H19: ='Com R'!G252 -> 0
C20: ='Net F'!#REF! -> #REF! | D20: ='Net R'!G273 -> 0 | H20: ='Com R'!G273 -> 0
C21: ='Net F'!#REF! -> #REF! | D21: ='Net R'!G294 -> 0 | H21: ='Com R'!G294 -> 0
C22: ='Net F'!#REF! -> #REF! | D22: ='Net R'!G315 -> 0 | H22: ='Com R'!G315 -> 0
C23: ='Net F'!#REF! -> #REF! | D23: ='Net R'!G336 -> 0 | H23: ='Com R'!G336 -> 0
C24: ='Net F'!#REF! -> #REF! | D24: ='Net R'!G357 -> 0 | H24: ='Com R'!G357 -> 0
C25: ='Net F'!#REF! -> #REF! | D25: ='Net R'!G378 -> 0 | H25: ='Com R'!G378 -> 0
C26: ='Net F'!#REF! -> #REF! | D26: ='Net R'!G399 -> 0
C27: ='Net F'!#REF! -> #REF! | D27: ='Net R'!G420 -> 0
C28: ='Net F'!#REF! -> #REF! | D28: ='Net R'!G441 -> 0
C29: ='Net F'!#REF! -> #REF! | D29: ='Net R'!G463 -> 0
C30: ='Net F'!#REF! -> #REF! | D30: ='Net R'!G484 -> 0
C31: =#REF! -> #REF! | D31: ='Net R'!G505 -> 0
C32: ='Net F'!#REF! -> #REF! | D32: ='Net R'!G526 -> 0
D33: ='Net R'!G547 -> 0
D34: ='Net R'!G568 -> 0
D35: ='Net R'!G589 -> 0
D36: ='Net R'!G610 -> 0
C38: =SUM(C8:C37) -> #REF! | D38: =SUM(D8:D37) -> 30 | E38: =SUM(E8:E37) -> #REF! | F38: =SUM(F8:F37) -> 11.5 | G38: =SUM(G8:G37) -> 9 | H38: =SUM(H8:H37) -> 0 | I38: =SUM(I8:I37) -> 40.5 | J38: =SUM(J8:J37) -> 34.3 | K38: {=SUM((K8:K37)/3)} -> 0 | L38: =SUM(C38:K38) -> #REF!

Sheet Gastos mensuales
B3: Presupuestos | F3: l | G3: m | H3: x | I3: j | J3: v | K3: s | L3: d | M3: Total
B4: Semanal (4) | C4: 400 | F4: 5jn | G4: 6jn | H4: 7jn | I4: 8jn | J4: 9jn | K4: 10jn | L4: 11jn | O4: Cargo | P4: Monto
B5: Ganancias | C5: =Presupuesto!L38 -> #REF! | E5: Pasajes | F5: 0 | G5: 0 | H5: 0 | I5: 0 | J5: 0 | K5: 20 | L5: 0 | M5: =SUM(F5:L5) -> 20 | O5: Total | P5: =C11 -> #REF!
B6: Inversion Variable | C6: 0 | E6: Comidas | F6: 25 | G6: 25 | H6: 25 | I6: 25 | J6: 25 | K6: 10 | L6: 0 | M6: =SUM(F6:L6) -> 135 | O6: Prestamo | P6: 600
B7: Total | C7: =SUM(C4:C6) -> #REF! | E7: Extras | F7: 5 | G7: 5 | H7: 5 | I7: 5 | J7: 5 | K7: 5 | L7: 5 | M7: =SUM(F7:L7) -> 35 | O7: Telf | P7: 40
F8: =SUM(F5:F7) -> 30 | G8: =SUM(G5:G7) -> 30 | H8: =SUM(H5:H7) -> 30 | I8: =SUM(I5:I7) -> 30 | J8: =SUM(J5:J7) -> 30 | K8: =SUM(K5:K7) -> 35 | L8: =SUM(L5:L7) -> 5 | M8: =SUM(F8:L8) -> 190 | O8: Int. | P8: 90
F9: 12jn | G9: 13jn | H9: 14jn | I9: 15jn | J9: 16jn | K9: 17jn | L9: 18jn | O9: Seguridad | P9: 0
E10: Pasajes | F10: 0 | G10: 0 | H10: 0 | I10: 0 | J10: 0 | K10: 20 | L10: 0 | M10: =SUM(F10:L10) -> 20 | O10: Luz | P10: 0
B11: Total | C11: =C7 -> #REF! | E11: Comidas | F11: 25 | G11: 25 | H11: 25 | I11: 25 | J11: 25 | K11: 10 | L11: 0 | M11: =SUM(F11:L11) -> 135 | O11: Agua | P11: 0
B12: Extras?? | C12: =SUM(M7+M12+M17+M22+M27+M32+M37) -> 225 | E12: Extras | F12: 5 | G12: 5 | H12: 5 | I12: 5 | J12: 5 | K12: 5 | L12: 5 | M12: =SUM(F12:L12) -> 35 | O12: Mercado | P12: 0
B13: Prestamo | C13: 600 | F13: =SUM(F10:F12) -> 30 | G13: =SUM(G10:G12) -> 30 | H13: =SUM(H10:H12) -> 30 | I13: =SUM(I10:I12) -> 30 | J13: =SUM(J10:J12) -> 30 | K13: =SUM(K10:K12) -> 35 | L13: =SUM(L10:L12) -> 5 | M13: =SUM(F13:L13) -> 190 | O13: Diario | P13: =SUM(M8+M13+M18+M23+M28+M33+M38) -> 1230
B14: Luz, Agua y Seg. | C14: 0 | F14: 19jn | G14: 20jn | H14: 21jn | I14: 22jn | J14: 23jn | K14: 24jn | L14: 25jn | P14: =P5-SUM(P6:P13) -> #REF!
B15: Movistar y WoW | C15: =SUM(P7+P8) -> 130 | E15: Pasajes | F15: 0 | G15: 0 | H15: 0 | I15: 0 | J15: 0 | K15: 20 | L15: 0 | M15: =SUM(F15:L15) -> 20
B16: Pasajes | C16: =SUM(M5+M10+M15+M20+M25+M30+M35) -> 120 | E16: Comidas | F16: 25 | G16: 25 | H16: 25 | I16: 25 | J16: 25 | K16: 10 | L16: 0 | M16: =SUM(F16:L16) -> 135
B17: Comida | C17: =SUM(M6+M11+M16+M21+M26+M31+M36) -> 885 | E17: Extras | F17: 5 | G17: 5 | H17: 5 | I17: 5 | J17: 5 | K17: 5 | L17: 5 | M17: =SUM(F17:L17) -> 35
B18: TOTAL | C18: =SUM(C11-C12-C13-C14-C15-C16-C17) -> #REF! | F18: =SUM(F15:F17) -> 30 | G18: =SUM(G15:G17) -> 30 | H18: =SUM(H15:H17) -> 30 | I18: =SUM(I15:I17) -> 30 | J18: =SUM(J15:J17) -> 30 | K18: =SUM(K15:K17) -> 35 | L18: =SUM(L15:L17) -> 5 | M18: =SUM(F18:L18) -> 190
F19: 26jn | G19: 27jn | H19: 28jn | I19: 29jn | J19: 30jn | K19: 1jl | L19: 2jl | O19: =M23*4 -> 760 | P19: 650 | Q19: 350
E20: Pasajes | F20: 0 | G20: 0 | H20: 0 | I20: 0 | J20: 0 | K20: 20 | L20: 0 | M20: =SUM(F20:L20) -> 20
E21: Comidas | F21: 25 | G21: 25 | H21: 25 | I21: 25 | J21: 25 | K21: 10 | L21: 0 | M21: =SUM(F21:L21) -> 135
E22: Extras | F22: 5 | G22: 5 | H22: 5 | I22: 5 | J22: 5 | K22: 5 | L22: 5 | M22: =SUM(F22:L22) -> 35
F23: =SUM(F20:F22) -> 30 | G23: =SUM(G20:G22) -> 30 | H23: =SUM(H20:H22) -> 30 | I23: =SUM(I20:I22) -> 30 | J23: =SUM(J20:J22) -> 30 | K23: =SUM(K20:K22) -> 35 | L23: =SUM(L20:L22) -> 5 | M23: =SUM(F23:L23) -> 190
F24: 3jl | G24: 4jl | H24: 5jl | I24: 6jl | J24: 7jl | K24: 8jl | L24: 9jl | O24: Cargo | P24: Monto
E25: Pasajes | F25: 0 | G25: 0 | H25: 0 | I25: 0 | J25: 0 | K25: 20 | L25: 0 | M25: =SUM(F25:L25) -> 20 | O25: Total | P25: 1600
E26: Comidas | F26: 25 | G26: 25 | H26: 25 | I26: 25 | J26: 25 | K26: 10 | L26: 0 | M26: =SUM(F26:L26) -> 135 | O26: Prestamo | P26: 300
E27: Extras | F27: 5 | G27: 5 | H27: 5 | I27: 5 | J27: 5 | K27: 5 | L27: 5 | M27: =SUM(F27:L27) -> 35 | O27: Telf | P27: 40
F28: =SUM(F25:F27) -> 30 | G28: =SUM(G25:G27) -> 30 | H28: =SUM(H25:H27) -> 30 | I28: =SUM(I25:I27) -> 30 | J28: =SUM(J25:J27) -> 30 | K28: =SUM(K25:K27) -> 35 | L28: =SUM(L25:L27) -> 5 | M28: =SUM(F28:L28) -> 190 | O28: Int. | P28: 70
F29: 10jl | G29: 11jl | H29: 12jl | I29: 13jl | J29: 14jl | K29: 15jl | L29: 16jl | O29: Seguridad | P29: 0
E30: Pasajes | F30: 0 | G30: 0 | H30: 0 | I30: 0 | J30: 0 | K30: 20 | L30: 0 | M30: =SUM(F30:L30) -> 20 | O30: Luz | P30: 0
E31: Comidas | F31: 25 | G31: 25 | H31: 25 | I31: 25 | J31: 25 | K31: 10 | L31: 0 | M31: =SUM(F31:L31) -> 135 | O31: Agua | P31: 0
E32: Extras | F32: 5 | G32: 5 | H32: 5 | I32: 5 | J32: 5 | K32: 5 | L32: 5 | M32: =SUM(F32:L32) -> 35 | O32: Viaje | P32: 200
F33: =SUM(F30:F32) -> 30 | G33: =SUM(G30:G32) -> 30 | H33: =SUM(H30:H32) -> 30 | I33: =SUM(I30:I32) -> 30 | J33: =SUM(J30:J32) -> 30 | K33: =SUM(K30:K32) -> 35 | L33: =SUM(L30:L32) -> 5 | M33: =SUM(F33:L33) -> 190 | O33: Diario | P33: =SUM(F28:L28,F33:L33,F38:L38) -> 470
F34: 17jl | G34: 18jl | H34: 19jl | P34: =P25-SUM(P26:P33) -> 520
E35: Pasajes | F35: 0 | G35: 0 | H35: 0 | M35: =SUM(F35:L35) -> 0
E36: Comidas | F36: 25 | G36: 25 | H36: 25 | M36: =SUM(F36:L36) -> 75
E37: Extras | F37: 5 | G37: 5 | H37: 5 | M37: =SUM(F37:L37) -> 15
F38: =SUM(F35:F37) -> 30 | G38: =SUM(G35:G37) -> 30 | H38: =SUM(H35:H37) -> 30 | M38: =SUM(F38:L38) -> 90

Sheet Mod Gastos

Sheet Hoja1

Sheet Hoja2
